Workbook

Sheet Board
D5: VENUE | E5: WALL | F5: PRICE | G5: DECIMAL | H5: IMPLIED | I5: BOOK | J5: TRUE | K5: RANK | L5: STATUS | M5: CHECKED
D6: Bet 365 | E6: OPEN | F6: 8/1 | G6: =IFERROR(LEFT(F6,FIND("/",F6)-1)/MID(F6,FIND("/",F6)+1,9)+1,"ERR PRICE") -> 9 | H6: =IFERROR(1/G6,"ERR") -> 0.11111111 | I6: 1.178 | J6: =IFERROR(H6/I6,"ERR") -> 0.094321826 | K6: 4 | L6: LIVE | M6: 0.51041667
D7: Draftkings | E7: BLOCKED | F7: 8/1 | G7: =IFERROR(LEFT(F7,FIND("/",F7)-1)/MID(F7,FIND("/",F7)+1,9)+1,"ERR PRICE") -> 9 | H7: =IFERROR(1/G7,"ERR") -> 0.11111111 | I7: 1.1604 | J7: =IFERROR(H7/I7,"ERR") -> 0.095752423 | K7: 3 | L7: NO ACCESS | M7: 0.50069444
D8: Ladbrokes | E8: OPEN | F8: 8/1 | G8: =IFERROR(LEFT(F8,FIND("/",F8)-1)/MID(F8,FIND("/",F8)+1,9)+1,"ERR PRICE") -> 9 | H8: =IFERROR(1/G8,"ERR") -> 0.11111111 | I8: 1.1231 | J8: =IFERROR(H8/I8,"ERR") -> 0.098932518 | K8: 1 | L8: LIVE | M8: 0.50138889
D9: AK Bets | E9: OPEN | F9: 9/1 | G9: =IFERROR(LEFT(F9,FIND("/",F9)-1)/MID(F9,FIND("/",F9)+1,9)+1,"ERR PRICE") -> 10 | H9: =IFERROR(1/G9,"ERR") -> 0.1 | I9: 1.0361 | J9: =IFERROR(H9/I9,"ERR") -> 0.09651578 | K9: 2 | L9: LIVE | M9: 0.51180556
D10: Betfair | E10: OPEN | F10: 17/2 | G10: =IFERROR(LEFT(F10,FIND("/",F10)-1)/MID(F10,FIND("/",F10)+1,9)+1,"ERR PRICE") -> 9.5 | H10: =IFERROR(1/G10,"ERR") -> 0.10526316 | I10: 1.1495 | J10: =IFERROR(H10/I10,"ERR") -> 0.091572995 | K10: 5 | L10: LIVE | M10: 0.5125
D13: THE HONEST NUMBER 9.8% | G13: BEST PAYOUT 9/1 | J13: EDGE AT BEST PRICE -0.11pp
D16: Ladbrokes fancies Chelsea most at a 9.9% true probability

Sheet Market
A1: PREDICTION | B1: 0
E2: BET 365 | I2: AK BETS | M2: BETFAIR | Q2: Draftkings | U2: Ladbrokes
A4: BEST BACK | B4: EXCH LAY | C4: GAP % | D4: SEEN AT | E4: Team | F4: BET365 DEC | G4: BET365 IMPLIED | I4: Team | J4: AK BETS DEC | K4: AK BETS IMPLIED | M4: Team | N4: BETFAIR DEC | O4: BETFAIR IMPLIED | Q4: Team | R4: DRAFTKINGS DEC | S4: DRAFTKINGS IMPLIED | U4: Team | V4: LADBROKES DEC | W4: LADBROKES IMPLIED
A5: =MAX(F5,J5,N5,R5,V5) -> 2.5 | B5: 1.92 | C5: =IFERROR(A5/B5-1,"ERR") -> 0.30208333 | D5: 0.49652778 | E5: Arsenal | F5: 2.5 | G5: =1/F5 -> 0.4 | I5: Arsenal | J5: 2.25 | K5: =1/J5 -> 0.44444444 | M5: Arsenal | N5: 2.25 | O5: =1/N5 -> 0.44444444 | Q5: Arsenal | R5: 2.4 | S5: =1/R5 -> 0.41666667 | U5: Arsenal | V5: 2.25 | W5: =1/V5 -> 0.44444444
A6: =MAX(F6,J6,N6,R6,V6) -> 81 | B6: 180 | C6: =IFERROR(A6/B6-1,"ERR") -> -0.55 | D6: 0.49722222 | E6: Aston Villa | F6: 41 | G6: =1/F6 -> 0.024390244 | I6: Aston Villa | J6: 81 | K6: =1/J6 -> 0.012345679 | M6: Aston Villa | N6: 41 | O6: =1/N6 -> 0.024390244 | Q6: Aston Villa | R6: 51 | S6: =1/R6 -> 0.019607843 | U6: Aston Villa | V6: 67 | W6: =1/V6 -> 0.014925373
A7: =MAX(F7,J7,N7,R7,V7) -> 501 | B7: 1000 | C7: =IFERROR(A7/B7-1,"ERR") -> -0.499 | D7: 0.49722222 | E7: Bournemouth | F7: 201 | G7: =1/F7 -> 0.0049751244 | I7: Bournemouth | J7: 501 | K7: =1/J7 -> 0.001996008 | M7: Bournemouth | N7: 301 | O7: =1/N7 -> 0.0033222591 | Q7: Bournemouth | R7: 251 | S7: =1/R7 -> 0.0039840637 | U7: Bournemouth | V7: 201 | W7: =1/V7 -> 0.0049751244
A8: =MAX(F8,J8,N8,R8,V8) -> 301 | B8: 180 | C8: =IFERROR(A8/B8-1,"ERR") -> 0.67222222 | D8: 0.49722222 | E8: Brentford | F8: 251 | G8: =1/F8 -> 0.0039840637 | I8: Brentford | J8: 301 | K8: =1/J8 -> 0.0033222591 | M8: Brentford | N8: 301 | O8: =1/N8 -> 0.0033222591 | Q8: Brentford | R8: 251 | S8: =1/R8 -> 0.0039840637 | U8: Brentford | V8: 251 | W8: =1/V8 -> 0.0039840637
A9: =MAX(F9,J9,N9,R9,V9) -> 301 | B9: 190 | C9: =IFERROR(A9/B9-1,"ERR") -> 0.58421053 | D9: 0.49722222 | E9: Brighton | F9: 151 | G9: =1/F9 -> 0.0066225166 | I9: Brighton | J9: 301 | K9: =1/J9 -> 0.0033222591 | M9: Brighton | N9: 176 | O9: =1/N9 -> 0.0056818182 | Q9: Brighton | R9: 151 | S9: =1/R9 -> 0.0066225166 | U9: Brighton | V9: 201 | W9: =1/V9 -> 0.0049751244
A10: =MAX(F10,J10,N10,R10,V10) -> 10 | B10: 10 | C10: =IFERROR(A10/B10-1,"ERR") -> 0 | D10: 0.49722222 | E10: Chelsea | F10: 9 | G10: =1/F10 -> 0.11111111 | I10: Chelsea | J10: 10 | K10: =1/J10 -> 0.1 | M10: Chelsea | N10: 9 | O10: =1/N10 -> 0.11111111 | Q10: Chelsea | R10: 9 | S10: =1/R10 -> 0.11111111 | U10: Chelsea | V10: 9 | W10: =1/V10 -> 0.11111111
A11: =MAX(F11,J11,N11,R11,V11) -> 2001 | C11: =IFERROR(A11/B11-1,"ERR") -> ERR | D11: 0.49722222 | E11: Coventry City | F11: 2001 | G11: =1/F11 -> 0.00049975012 | I11: Coventry City | J11: 1001 | K11: =1/J11 -> 0.000999001 | M11: Coventry City | N11: 501 | O11: =1/N11 -> 0.001996008 | Q11: Coventry City | R11: 1001 | S11: =1/R11 -> 0.000999001 | U11: Coventry City | V11: 1001 | W11: =1/V11 -> 0.000999001
A12: =MAX(F12,J12,N12,R12,V12) -> 1001 | C12: =IFERROR(A12/B12-1,"ERR") -> ERR | D12: 0.49722222 | E12: Crystal Palace | F12: 501 | G12: =1/F12 -> 0.001996008 | I12: Crystal Palace | J12: 1001 | K12: =1/J12 -> 0.000999001 | M12: Crystal Palace | N12: 501 | O12: =1/N12 -> 0.001996008 | Q12: Crystal Palace | R12: 251 | S12: =1/R12 -> 0.0039840637 | U12: Crystal Palace | V12: 501 | W12: =1/V12 -> 0.001996008
A13: =MAX(F13,J13,N13,R13,V13) -> 501 | B13: 950 | C13: =IFERROR(A13/B13-1,"ERR") -> -0.47263158 | D13: 0.49722222 | E13: Everton | F13: 251 | G13: =1/F13 -> 0.0039840637 | I13: Everton | J13: 501 | K13: =1/J13 -> 0.001996008 | M13: Everton | N13: 301 | O13: =1/N13 -> 0.0033222591 | Q13: Everton | R13: 251 | S13: =1/R13 -> 0.0039840637 | U13: Everton | V13: 251 | W13: =1/V13 -> 0.0039840637
A14: =MAX(F14,J14,N14,R14,V14) -> 501 | C14: =IFERROR(A14/B14-1,"ERR") -> ERR | D14: 0.49722222 | E14: Fulham | F14: 501 | G14: =1/F14 -> 0.001996008 | I14: Fulham | J14: 501 | K14: =1/J14 -> 0.001996008 | M14: Fulham | N14: 501 | O14: =1/N14 -> 0.001996008 | Q14: Fulham | R14: 501 | S14: =1/R14 -> 0.001996008 | U14: Fulham | V14: 501 | W14: =1/V14 -> 0.001996008
A15: =MAX(F15,J15,N15,R15,V15) -> 2001 | C15: =IFERROR(A15/B15-1,"ERR") -> ERR | D15: 0.49722222 | E15: Hull City | F15: 2001 | G15: =1/F15 -> 0.00049975012 | I15: Hull City | J15: 2001 | K15: =1/J15 -> 0.00049975012 | M15: Hull City | N15: 501 | O15: =1/N15 -> 0.001996008 | Q15: Hull City | R15: 2001 | S15: =1/R15 -> 0.00049975012 | U15: Hull City | V15: 2001 | W15: =1/V15 -> 0.00049975012
A16: =MAX(F16,J16,N16,R16,V16) -> 3001 | C16: =IFERROR(A16/B16-1,"ERR") -> ERR | D16: 0.49722222 | E16: Ipswich Town | F16: 3001 | G16: =1/F16 -> 0.00033322226 | I16: Ipswich Town | J16: 1001 | K16: =1/J16 -> 0.000999001 | M16: Ipswich Town | N16: 501 | O16: =1/N16 -> 0.001996008 | Q16: Ipswich Town | R16: 1001 | S16: =1/R16 -> 0.000999001 | U16: Ipswich Town | V16: 1001 | W16: =1/V16 -> 0.000999001
A17: =MAX(F17,J17,N17,R17,V17) -> 501 | B17: 400 | C17: =IFERROR(A17/B17-1,"ERR") -> 0.2525 | D17: 0.49722222 | E17: Leeds United | F17: 501 | G17: =1/F17 -> 0.001996008 | I17: Leeds United | J17: 501 | K17: =1/J17 -> 0.001996008 | M17: Leeds United | N17: 301 | O17: =1/N17 -> 0.0033222591 | Q17: Leeds United | R17: 251 | S17: =1/R17 -> 0.0039840637 | U17: Leeds United | V17: 501 | W17: =1/V17 -> 0.001996008
A18: =MAX(F18,J18,N18,R18,V18) -> 7 | B18: 10.5 | C18: =IFERROR(A18/B18-1,"ERR") -> -0.33333333 | D18: 0.49722222 | E18: Liverpool | F18: 6 | G18: =1/F18 -> 0.16666667 | I18: Liverpool | J18: 7 | K18: =1/J18 -> 0.14285714 | M18: Liverpool | N18: 6.5 | O18: =1/N18 -> 0.15384615 | Q18: Liverpool | R18: 6 | S18: =1/R18 -> 0.16666667 | U18: Liverpool | V18: 7 | W18: =1/V18 -> 0.14285714
A19: =MAX(F19,J19,N19,R19,V19) -> 4.75 | B19: 5.4 | C19: =IFERROR(A19/B19-1,"ERR") -> -0.12037037 | D19: 0.49722222 | E19: Manchester City | F19: 3.75 | G19: =1/F19 -> 0.26666667 | I19: Manchester City | J19: 4.75 | K19: =1/J19 -> 0.21052632 | M19: Manchester City | N19: 4 | O19: =1/N19 -> 0.25 | Q19: Manchester City | R19: 4 | S19: =1/R19 -> 0.25 | U19: Manchester City | V19: 4.33 | W19: =1/V19 -> 0.23094688
A20: =MAX(F20,J20,N20,R20,V20) -> 13 | B20: 21 | C20: =IFERROR(A20/B20-1,"ERR") -> -0.38095238 | D20: 0.49722222 | E20: Manchester United | F20: 8 | G20: =1/F20 -> 0.125 | I20: Manchester United | J20: 13 | K20: =1/J20 -> 0.076923077 | M20: Manchester United | N20: 9.5 | O20: =1/N20 -> 0.10526316 | Q20: Manchester United | R20: 9 | S20: =1/R20 -> 0.11111111 | U20: Manchester United | V20: 9 | W20: =1/V20 -> 0.11111111
A21: =MAX(F21,J21,N21,R21,V21) -> 276 | B21: 370 | C21: =IFERROR(A21/B21-1,"ERR") -> -0.25405405 | D21: 0.49722222 | E21: Newcastle United | F21: 151 | G21: =1/F21 -> 0.0066225166 | I21: Newcastle United | J21: 276 | K21: =1/J21 -> 0.0036231884 | M21: Newcastle United | N21: 176 | O21: =1/N21 -> 0.0056818182 | Q21: Newcastle United | R21: 151 | S21: =1/R21 -> 0.0066225166 | U21: Newcastle United | V21: 151 | W21: =1/V21 -> 0.0066225166
A22: =MAX(F22,J22,N22,R22,V22) -> 501 | B22: 1000 | C22: =IFERROR(A22/B22-1,"ERR") -> -0.499 | D22: 0.49722222 | E22: Nottingham Forest | F22: 501 | G22: =1/F22 -> 0.001996008 | I22: Nottingham Forest | J22: 501 | K22: =1/J22 -> 0.001996008 | M22: Nottingham Forest | N22: 301 | O22: =1/N22 -> 0.0033222591 | Q22: Nottingham Forest | R22: 501 | S22: =1/R22 -> 0.001996008 | U22: Nottingham Forest | V22: 251 | W22: =1/V22 -> 0.0039840637
A23: =MAX(F23,J23,N23,R23,V23) -> 1001 | B23: 1000 | C23: =IFERROR(A23/B23-1,"ERR") -> 0.001 | D23: 0.49722222 | E23: Sunderland | F23: 751 | G23: =1/F23 -> 0.0013315579 | I23: Sunderland | J23: 1001 | K23: =1/J23 -> 0.000999001 | M23: Sunderland | N23: 501 | O23: =1/N23 -> 0.001996008 | Q23: Sunderland | R23: 501 | S23: =1/R23 -> 0.001996008 | U23: Sunderland | V23: 751 | W23: =1/V23 -> 0.0013315579
A24: =MAX(F24,J24,N24,R24,V24) -> 41 | B24: 60 | C24: =IFERROR(A24/B24-1,"ERR") -> -0.31666667 | D24: 0.49722222 | E24: Tottenham | F24: 21 | G24: =1/F24 -> 0.047619048 | I24: Tottenham | J24: 41 | K24: =1/J24 -> 0.024390244 | M24: Tottenham | N24: 29 | O24: =1/N24 -> 0.034482759 | Q24: Tottenham | R24: 23 | S24: =1/R24 -> 0.043478261 | U24: Tottenham | V24: 34 | W24: =1/V24 -> 0.029411765
G25: 1.1783 | K25: 1.0361 | O25: 1.1634 | S25: 1.1604 | W25: 1.1231

Sheet Matches
D1: =IF(COUNTIF(D3:D5,"ERR")>0,"ERR IN BOOK",SUM(D3:D5)) -> 1.0847159 | E1: =IF(ISNUMBER($D$1),$D$1-1,"ERR") -> 0.084715938
A2: WHO | B2: PRICE | C2: DEC | D2: IMPLIED | E2: TRUE
A3: HOME | B3: 12/5 | C3: =IFERROR(IF(ISNUMBER(FIND("/",B3)),LEFT(B3,FIND("/",B3)-1)/MID(B3,FIND("/",B3)+1,9)+1,VALUE(B3)),"ERR") -> 3.4 | D3: =IFERROR(1/C3,"ERR") -> 0.29411765 | E3: =IFERROR(D3/SUM($D$3:$D$5), "") -> 0.27114716
A4: DRAW | B4: 13/5 | C4: =IFERROR(IF(ISNUMBER(FIND("/",B4)),LEFT(B4,FIND("/",B4)-1)/MID(B4,FIND("/",B4)+1,9)+1,VALUE(B4)),"ERR") -> 3.6 | D4: =IFERROR(1/C4,"ERR") -> 0.27777778 | E4: =IFERROR(D4/$D$1,"ERR") -> 0.25608343
A5: AWAY | B5: 19/20 | C5: =IFERROR(IF(ISNUMBER(FIND("/",B5)),LEFT(B5,FIND("/",B5)-1)/MID(B5,FIND("/",B5)+1,9)+1,VALUE(B5)),"ERR") -> 1.95 | D5: =IFERROR(1/C5,"ERR") -> 0.51282051 | E5: =IFERROR(D5/$D$1,"ERR") -> 0.47276941
B8: Fulham vs Chelsea

Sheet Scorers
D1: =IF(COUNTIF(D3:D5,"ERR")>0,"ERR IN BOOK",SUM(D3:D12)) -> 0.91992477
A2: WHO | B2: PRICE | C2: DEC | D2: IMPLIED
A3: Cole Palmer | B3: 46027 | C3: =IFERROR(IF(ISNUMBER(FIND("/",B3)),LEFT(B3,FIND("/",B3)-1)/MID(B3,FIND("/",B3)+1,9)+1,VALUE(B3)),"ERR") -> 6 | D3: =IFERROR(1/C3,"ERR") -> 0.16666667
A4: Danny Welbeck | B4: 46064 | C4: =IFERROR(IF(ISNUMBER(FIND("/",B4)),LEFT(B4,FIND("/",B4)-1)/MID(B4,FIND("/",B4)+1,9)+1,VALUE(B4)),"ERR") -> 6.5 | D4: =IFERROR(1/C4,"ERR") -> 0.15384615 | G4: PARTIAL — more scorers exist, real total higher.
A5: Rodrigo Muniz | B5: 46066 | C5: =IFERROR(IF(ISNUMBER(FIND("/",B5)),LEFT(B5,FIND("/",B5)-1)/MID(B5,FIND("/",B5)+1,9)+1,VALUE(B5)),"ERR") -> 7.5 | D5: =IFERROR(1/C5,"ERR") -> 0.13333333
A6: Jamie Gittens | B6: 46032 | C6: =IFERROR(IF(ISNUMBER(FIND("/",B6)),LEFT(B6,FIND("/",B6)-1)/MID(B6,FIND("/",B6)+1,9)+1,VALUE(B6)),"ERR") -> 11 | D6: =IFERROR(1/C6,"ERR") -> 0.090909091
A7: Gonzalo Garcia | B7: 46030 | C7: =IFERROR(IF(ISNUMBER(FIND("/",B7)),LEFT(B7,FIND("/",B7)-1)/MID(B7,FIND("/",B7)+1,9)+1,VALUE(B7)),"ERR") -> 9 | D7: =IFERROR(1/C7,"ERR") -> 0.11111111
A8: Enzo Fernandez | B8: 46034 | C8: =IFERROR(IF(ISNUMBER(FIND("/",B8)),LEFT(B8,FIND("/",B8)-1)/MID(B8,FIND("/",B8)+1,9)+1,VALUE(B8)),"ERR") -> 13 | D8: =IFERROR(1/C8,"ERR") -> 0.076923077
A9: Oscar Bobb | B9: 46036 | C9: =IFERROR(IF(ISNUMBER(FIND("/",B9)),LEFT(B9,FIND("/",B9)-1)/MID(B9,FIND("/",B9)+1,9)+1,VALUE(B9)),"ERR") -> 15 | D9: =IFERROR(1/C9,"ERR") -> 0.066666667
A10: Mamadou Sarr | B10: 33/1 | C10: =IFERROR(IF(ISNUMBER(FIND("/",B10)),LEFT(B10,FIND("/",B10)-1)/MID(B10,FIND("/",B10)+1,9)+1,VALUE(B10)),"ERR") -> 34 | D10: =IFERROR(1/C10,"ERR") -> 0.029411765
A11: Calvin Bassey | B11: 40/1 | C11: =IFERROR(IF(ISNUMBER(FIND("/",B11)),LEFT(B11,FIND("/",B11)-1)/MID(B11,FIND("/",B11)+1,9)+1,VALUE(B11)),"ERR") -> 41 | D11: =IFERROR(1/C11,"ERR") -> 0.024390244
A12: No SCORER | B12: 46036 | C12: =IFERROR(IF(ISNUMBER(FIND("/",B12)),LEFT(B12,FIND("/",B12)-1)/MID(B12,FIND("/",B12)+1,9)+1,VALUE(B12)),"ERR") -> 15 | D12: =IFERROR(1/C12,"ERR") -> 0.066666667

Sheet COMPS
B2: DATE | C2: TITLE | D2: SOLD (£) | E2: POSTAGE (£) | F2: Seller (UK) | G2: Link
B3: 46235 | C3: Pokémon Korean Munikis / Nihil Zero [M3] Booster Box | D3: 39.95 | E3: 0 | F3: Ebay | G3: https://www.ebay.co.uk/itm/257415479506?_skw=korean+pokemon+booster+box&itmmeta=01M0CTJWS454E7H3TGB6Z8T11P&hash=item3bef2880d2:g:uTsAAeSwv7lpvG5Q&itmprp=enc%3AAQALAAAA8GfYFPkwiKCW4ZNSs2u11xAOe0Y58Js%2B8RHEq5TKs8wMXUMb3beNuLDqUuExKwTXVKoWWWUueiMT5F99hK5accjm1lOrwbttUJ%2BV8I34vz%2BmlnpQ83b1U--iayGn%2B0p6r2g89dEwQ%2BffpaGSWDeLSlsXIERxiYV5wyeLEUwW6lFF3I8mU0yRk1QHIZjdspPlfSOS6m8MqDoHaFMtXB8WINWQBJ7mfUG89slouFk%2FzYtxBZYw6NbVK64B5rtovdZlJIAB2EqAcU%2BUrfaBc2cSTS485O0eGigMZOd0b8oAbvD0cWiPybwjjpI4Vo1SR2kWJQ%3D%3D%7Ctkp%3ABFBM6szLmoNo
B4: 46236 | C4: Pokemon TCG | Nihil Zero | Munikis Zero | M3 | Korean | Booster Box | D4: 54.99 | E4: 3.95 | F4: Amazon | G4: https://www.amazon.co.uk/Pokemon-Munikis-M3-Booster-Collectors/dp/B0H37N66LC/ref=asc_df_B0H37N66LC?mcid=befdc165edbb3acfad3c53eb7ba906f5&tag=googshopuk-21&linkCode=df0&hvadid=791198028413&hvpos=&hvnetw=g&hvrand=16774976478424918764&hvpone=&hvptwo=&hvqmt=&hvdev=c&hvdvcmdl=&hvlocint=&hvlocphy=9044956&hvtargid=pla-2493029932772&psc=1&hvocijid=16774976478424918764-B0H37N66LC-&hvexpln=0&gad_source=1
B5: 46237 | C5: Pokemon TCG: Nihil Zero m3 - Korean Booster Box (30 Packs) | D5: 44.95 | E5: 0 | F5: Romulus Games | G5: https://romulusgames.com/products/pokemon-tcg-nihil-zero-m3-korean-booster-box?variant=56867831218553&country=GB&currency=GBP&utm_medium=product_sync&utm_source=google&utm_content=sag_organic&utm_campaign=sag_organic&gad_source=1&gad_campaignid=20585219644&gbraid=0AAAAApH777K0fokTM5za5Rs05rz-fveve&gclid=CjwKCAjwqJXUBhBNEiwA8BgG7uSRVQ4z-9z_6xslNDGygv5RBdgz10-SUkFXSRZp-d2-7fEzdKy3JRoCByAQAvD_BwE
B6: 46238 | C6: Pokémon Korean Munikis / Nihil Zero [M3] Booster Box (30 Packs) | D6: 41.99 | E6: 0 | F6: Ebay | G6: https://www.ebay.co.uk/itm/147403148576?_skw=Pok%C3%A9mon+Korean+Munikis+%2F+Nihil+Zero+%5BM3%5D+Booster+Box&itmmeta=01M0CV3R2A2MYZ78QKCDBZ0JPY&hash=item2251e98d20:g:BuAAAeSwlQtqQVCn&itmprp=enc%3AAQALAAABEGfYFPkwiKCW4ZNSs2u11xC04i%2BbhZ9eovUPyp4BY5rumLEpnPmrrXtddn0gIe35QWBAeJMb9nKnc2MXMcs6kF0NoEEdlj9TUQr9MxgsuK4wCYVGHpDkLkA83g4bZvCWwa3P8YJ3paPvwo%2FQxv3QfXpRqqL2kNkry8V%2Fw2TGgWnFYv940ewIiGWBnCg8%2BWlXPtbkxsQNfQbiCjyUd5MRqHeJ0fyl%2BUhIt9tHXfkGHFInMXv4YmM9U0NPEHwhAZd7szwqFgTNDJcj%2FuRL2YrvQlrMBZk6HRNBcCnaGAUz3UcS--Xd%2BixhAkJC6d9VMHvOwIpCrr1hXg2hx0TOyThtZ3kin%2Fc7%2FB6vnZoufe0750Rq%7Ctkp%3ABk9SR8aBj5uDaA
B7: 46239 | C7: Pokémon Korean Munikis / Nihil Zero [M3] Booster Box (30 Packs) - New & Sealed | D7: 37.1 | E7: 0 | F7: Ebay | G7: https://www.ebay.co.uk/itm/236848103670?_skw=Pok%C3%A9mon+Korean+Munikis+booster+box&itmmeta=01M0CVAKR99V6JF7XDXWTHWJ99&hash=item37253f40f6:g:0QQAAeSwS5JqHAsS&itmprp=enc%3AAQALAAAA4GfYFPkwiKCW4ZNSs2u11xCJ3tsYl1tLw6U%2Bdonc36czC0JLTSwmqipIFNdQmMzpxLq5xUa8mfnOVjfnYdJDL0O7B6ATr6AE6IiM8VVwWhwMl1s12HJTTY%2Fa%2BbEKj%2B7XQAB%2FgFLDm2i0HYDRc1PCqTYaVdJd%2BBTtI3oUeWQAi7XbnMS6QLH%2B76OH436UmOHpAs%2BcYQZBgo6R2XaSTQxvE6o9t12qKYOsPhk8wwIXW7lp4WQ9inY33nQu6t1zUr9HoGHc9khKqiHFes1eD0RRGhLLy8htDwWNXBDR%2FrrLWxkt%7Ctkp%3ABk9SR_C8qpuDaA
B8: 46240 | C8: Munikis Zero ( Nihil Zero ) M3 Booster Box Sealed Pokemon Card Korean | D8: 37.31 | E8: 0 | F8: Ebay | G8: https://www.ebay.co.uk/itm/287474275860?_skw=Pok%C3%A9mon+Korean+Munikis+booster+box&itmmeta=01M0CVAKR9QS66SQE1T55Q0VEK&hash=item42eecd5614:g:hAcAAeSwR09psZzA&itmprp=enc%3AAQALAAAA4GfYFPkwiKCW4ZNSs2u11xDhufR63EVsNQ2Rx9VdcxjU7IatzaqVoq5MnADiVWG1%2FCyrIEj4xf3z2pXQ1cy06yQ6eyY%2FPL1kR%2B1595Blo2gwc7XcTuVXpZov8DXbmTbN47vZlQ95d2oNBct1Dk2SS29QxPd6o2SqaUM3i8sAJK3dTVR8MxdOkk5ytTh%2BWzDi%2FctUZsGLOpV14cmy7rhmNuFk1KOAJPLZ11wn%2BRVyJztd2fO%2F8KR9DzSy4nO8fg5rS6p%2F1Pv8w0k%2FaX5ZE3V231TcFw0ydez6h4MPf61qOyC%2F%7Ctkp%3ABk9SR_C8qpuDaA
B9: 46241 | C9: Pokémon Korean Munikis / Nihil Zero [M3] Booster Box (30 Packs) | D9: 34.49 | E9: 0 | F9: Ebay | G9: https://www.ebay.co.uk/itm/178383913139?_skw=Pok%C3%A9mon+Korean+Munikis+booster+box&itmmeta=01M0CVAKR9VY8YQF8W09HBAXDA&hash=item29888280b3:g:-6gAAeSwrJFqdk26&itmprp=enc%3AAQALAAABAGfYFPkwiKCW4ZNSs2u11xDRq06oRWd8NO7NxxtIutA95MKgvJwplUdI%2FIOR%2Bt5XdYX4TEunYkyeQOuzjQohNh0Y7V3I2YanWqPY8SXwSNiSqjdyziRBlz8tggW%2FAcVPoL80khBYs7FR6B8buf%2Fo9WZMLVA94emklwafVlMn%2Fi2lbeyoZgo6FTOm3crCsBD3YuRltr4V158xUMFMCBK%2FkudqrxksCQLiub7yD7NRd2kPyse7Xz1I4bTXxxPXyIC7%2F8Dm%2FAX7xFMEBpT1IV1Rfg8egpqGHWEfi88rt8caVG%2BVT5cDUzrkeT9YuKrrnhjKfSdmSjjRymzLlWkbU8R9btI%3D%7Ctkp%3ABk9SR_C8qpuDaA
B10: 46242 | C10: Pokémon Korean Munikis / Nihil Zero [M3] Booster Box (30 Packs) | D10: 36.99 | E10: 0 | F10: Ebay | G10: https://www.ebay.co.uk/itm/336728009466?_skw=Pok%C3%A9mon+Korean+Munikis+booster+box&itmmeta=01M0CVAKR98098Y7B6NX6NJ1ZH&hash=item4e668daafa:g:UXUAAeSw65Bqc2~Y&itmprp=enc%3AAQALAAAA4GfYFPkwiKCW4ZNSs2u11xBHGC2pu2%2BWuVixxpTUmOluSewWntr%2FtCevCzMWInYYz7%2FUvmeVh67tlC783mAn94Ze7NjgGGD4YL07hx50XL6CsXLjOaTAqUBBBsSkURPvDzFfMYJM6BOqL1Mtbt5NLsvz4Oc%2FMKI%2BPOD3g%2F0NClDgVahSGFOxQ8SL0tQAavcIAlKcxQtwXwVjW5560gcH0NhC30RL9m1VQZwqKmKX6ciu8ajZTh0jTemq%2BnlJ%2Fhn9sR0brVdvqHgDLxXD8Ogwz8s%2Bio34j92pc3eZNzrn7PKW%7Ctkp%3ABk9SR_C8qpuDaA
B11: 46243 | C11: Pokémon Korean Munikis / Nihil Zero Booster Box (30 Packs) | D11: 44.99 | E11: 0 | F11: Ebay | G11: https://www.ebay.co.uk/itm/306859714047?_skw=Pok%C3%A9mon+Korean+Munikis+booster+box&itmmeta=01M0CVAKR8T3797J8TK113AHNE&hash=item477243a5ff:g:h0gAAeSwjAVpz--2&itmprp=enc%3AAQALAAABAGfYFPkwiKCW4ZNSs2u11xBXFRXEw%2BMdhLObwP0abaUWTp48DSmZ%2FHzgOWZt36zFBhA9XJpLIbnK1aVoq2KaPYm0kw1Ca%2Fx00OII%2F4ZpLOGZs%2Fp2TgLZiXtEtSz9EeLgT56Kh2Iuzd%2FwVH0SuiDdMEiLiY6F2iNvOwPLWbgOtfqN4vj17GGALg6avQqtWtt9iqVG%2F8fVBycsBpaIYKLbTRNXUjoXiLAQOYMBiuoiMtIqWYPGAB9xyJyOXIl3Kbc4DO4hC2RdkYTugCBXRYdRgz%2FSUPBA8d44r5Z2c0dyQFIUEm0LSMgLKpL9Bht5k1VQW9M0%2Bc3fTLR%2BNeRjBP3rh3Q%3D%7Ctkp%3ABk9SR_C8qpuDaA
B14: Average Sold Price = £41.42
B15: Worst/lowest comp = £34.49

Sheet LEDGER
B2: ITEM | C2: PREDICTED | D2: ACTUAL
B3: eBay Sold Price £ | C3: 41.42 | D3: 41.42
B4: eBay Fee % | C4: 0.1 | D4: 0.13
B5: Postage £ | C5: 0 | D5: 0.44
B6: Import VAT £ | C6: 7.5 | D6: 8.28
B7: Seoul → UK Shipping £ | C7: 14 | D7: 18
B8: FX Cost £ | C8: 0.3 | D8: 0.3
B9: Seoul Shelf Price ₩ | C9: 37776 | D9: 37776
B10: FX Rate ₩/£ | C10: 1800 | D10: 1900
B11: NET REALISABLE | C11: =C3*(1-C4)-C5-C6 -> 29.778 | D11: =D3*(1-D4)-D5-D6 -> 27.3154
B12: TOTAL COST | C12: =C9/C10+C7+C8 -> 35.286667 | D12: =D9/D10+D7+D8 -> 38.182105
B13: MARGIN £ | C13: =C11-C12 -> -5.5086667 | D13: =D11-D12 -> -10.866705
B14: MARGIN % | C14: =C13/C12 -> -0.15611185 | D14: =D13/D12 -> -0.28460205
B15: BREAKEVEN SEOUL PRICE ₩ | C15: 27860.4 | D15: 17129.26
B16: INPUT CHECK | C16: =IF(COUNTBLANK(C3:C10)>0,"ERR — INPUT MISSING","OK") -> OK | D16: =IF(COUNTBLANK(D3:D10)>0,"ERR — INPUT MISSING","OK") -> OK

Sheet Sheet22

Sheet CAMPUS
A1: VENTURE | B1: QUOTED PROFIT £ | C1: TRUE COST £ | D1: HOURS | E1: PROFIT £ | F1: £ PER HOUR | G1: RANK | H1: HONEST | I1: WALL | J1: VERDICT
A2: Car Washing | B2: 200 | C2: 40 | D2: 10 | E2: =IF(OR(NOT(ISNUMBER(B2)),NOT(ISNUMBER(C2))),"ERR",B2-C2) -> 160 | F2: =IF(OR(NOT(ISNUMBER(E2)),NOT(ISNUMBER(D2)),D2=0),"ERR",ROUND(E2/D2,2)) -> 16 | G2: =IF(NOT(ISNUMBER(F2)),"ERR",RANK(F2,$F$2:$F$9,0)) -> 5 | H2: =IF(OR(NOT(ISNUMBER(B2)),NOT(ISNUMBER(C2))),"ERR",B2-C2) -> 160 | I2: Customers pay for convenience; equipment, location and travel make it difficult to offer cheaper washes profitably. | J2: DIG
A3: Tutoring | B3: 200 | C3: 10 | D3: 9 | E3: =IF(OR(NOT(ISNUMBER(B3)),NOT(ISNUMBER(C3))),"ERR",B3-C3) -> 190 | F3: =IF(OR(NOT(ISNUMBER(E3)),NOT(ISNUMBER(D3)),D3=0),"ERR",ROUND(E3/D3,2)) -> 21.11 | G3: =IF(NOT(ISNUMBER(F3)),"ERR",RANK(F3,$F$2:$F$9,0)) -> 3 | H3: =IF(OR(NOT(ISNUMBER(B3)),NOT(ISNUMBER(C3))),"ERR",B3-C3) -> 190 | I3: Parents pay more for trusted tutors; reputation, qualifications and trust make it difficult for new tutors to compete. | J3: DIG
A4: Reselling Clothes | B4: 300 | C4: 170 | D4: 8 | E4: =IF(OR(NOT(ISNUMBER(B4)),NOT(ISNUMBER(C4))),"ERR",B4-C4) -> 130 | F4: =IF(OR(NOT(ISNUMBER(E4)),NOT(ISNUMBER(D4)),D4=0),"ERR",ROUND(E4/D4,2)) -> 16.25 | G4: =IF(NOT(ISNUMBER(F4)),"ERR",RANK(F4,$F$2:$F$9,0)) -> 4 | H4: =IF(OR(NOT(ISNUMBER(B4)),NOT(ISNUMBER(C4))),"ERR",B4-C4) -> 130 | I4: Cheap stock is scattered across marketplaces/charity shops; finding undervalued items takes time and product knowledge. | J4: DIG
A5: Dog Walking | B5: 150 | C5: 15 | D5: 12 | E5: =IF(OR(NOT(ISNUMBER(B5)),NOT(ISNUMBER(C5))),"ERR",B5-C5) -> 135 | F5: =IF(OR(NOT(ISNUMBER(E5)),NOT(ISNUMBER(D5)),D5=0),"ERR",ROUND(E5/D5,2)) -> 11.25 | G5: =IF(NOT(ISNUMBER(F5)),"ERR",RANK(F5,$F$2:$F$9,0)) -> 7 | H5: =IF(OR(NOT(ISNUMBER(B5)),NOT(ISNUMBER(C5))),"ERR",B5-C5) -> 135 | I5: Owners need someone they trust with their pet/home; trust and reputation stop cheaper new competitors entering easily | J5: DROP
A6: Bartender | B6: 140 | C6: 10 | D6: 10 | E6: =IF(OR(NOT(ISNUMBER(B6)),NOT(ISNUMBER(C6))),"ERR",B6-C6) -> 130 | F6: =IF(OR(NOT(ISNUMBER(E6)),NOT(ISNUMBER(D6)),D6=0),"ERR",ROUND(E6/D6,2)) -> 13 | G6: =IF(NOT(ISNUMBER(F6)),"ERR",RANK(F6,$F$2:$F$9,0)) -> 6 | H6: =IF(OR(NOT(ISNUMBER(B6)),NOT(ISNUMBER(C6))),"ERR",B6-C6) -> 130 | I6: Venues control hiring and require reliable/experienced staff; you cannot simply undercut their existing staffing arrangements. | J6: DROP
A7: Social Media Management | B7: 250 | C7: 20 | D7: 10 | E7: =IF(OR(NOT(ISNUMBER(B7)),NOT(ISNUMBER(C7))),"ERR",B7-C7) -> 230 | F7: =IF(OR(NOT(ISNUMBER(E7)),NOT(ISNUMBER(D7)),D7=0),"ERR",ROUND(E7/D7,2)) -> 23 | G7: =IF(NOT(ISNUMBER(F7)),"ERR",RANK(F7,$F$2:$F$9,0)) -> 2 | H7: =IF(OR(NOT(ISNUMBER(B7)),NOT(ISNUMBER(C7))),"ERR",B7-C7) -> 230 | I7: Businesses lack the time and skills to make consistent content; agencies can charge more because switching or doing it in-house takes effort. | J7: DIG
A8: Babysitting | B8: 120 | C8: 10 | D8: 10 | E8: =IF(OR(NOT(ISNUMBER(B8)),NOT(ISNUMBER(C8))),"ERR",B8-C8) -> 110 | F8: =IF(OR(NOT(ISNUMBER(E8)),NOT(ISNUMBER(D8)),D8=0),"ERR",ROUND(E8/D8,2)) -> 11 | G8: =IF(NOT(ISNUMBER(F8)),"ERR",RANK(F8,$F$2:$F$9,0)) -> 8 | H8: =IF(OR(NOT(ISNUMBER(B8)),NOT(ISNUMBER(C8))),"ERR",B8-C8) -> 110 | I8: Parents prioritise trust and recommendations over price; safeguarding and reputation make it hard for unknown cheaper sitters to compete. | J8: DROP
A9: Video Editing | B9: 200 | C9: 15 | D9: 8 | E9: =IF(OR(NOT(ISNUMBER(B9)),NOT(ISNUMBER(C9))),"ERR",B9-C9) -> 185 | F9: =IF(OR(NOT(ISNUMBER(E9)),NOT(ISNUMBER(D9)),D9=0),"ERR",ROUND(E9/D9,2)) -> 23.13 | G9: =IF(NOT(ISNUMBER(F9)),"ERR",RANK(F9,$F$2:$F$9,0)) -> 1 | H9: =IF(OR(NOT(ISNUMBER(B9)),NOT(ISNUMBER(C9))),"ERR",B9-C9) -> 185 | I9: Editing requires time, software and skill; clients pay more because learning it or hiring someone in-house is inconvenient. | J9: DIG

Sheet File_A
A1: PRACTICE FILE — NOT LIVE | G1: PRACTICE FILE — NOT LIVE | M1: `
A2: FILE A — REAL? | G2: FILE B — STALE? | M2: FILE C — EATEN?
A3: Match (invented): Everton v Crystal Palace · The outcome being priced: EVERTON TO WIN | G3: Match (invented): Fulham v Wolves · The outcome being priced: THE DRAW | M3: Match (invented): Sunderland v Brentford · The outcome being priced: SUNDERLAND TO WIN
A4: Invented prices — do not check them against live markets. Everything you need is on this sheet. | G4: Invented prices — do not check them against live markets. Everything you need is on this sheet. | M4: Invented prices — do not check them against live markets. Everything you need is on this sheet.
A6: VENUE | B6: SIDE | C6: PRICE (fraction) | D6: PRICE (decimal) | E6: TAKEN AT | G6: VENUE | H6: SIDE | I6: PRICE (fraction) | J6: PRICE (decimal) | K6: TAKEN AT | M6: VENUE | N6: SIDE | O6: PRICE (fraction) | P6: PRICE (decimal) | Q6: TAKEN AT
A7: Betfred (bookie) | B7: BACK | C7: 46316 | D7: 3.1 | E7: 0.4875 | G7: Bet365 (bookie) | H7: BACK | I7: 14/5 | J7: 3.80 | K7: 13:07 | M7: Bet365 (bookie) | N7: BACK | O7: 31/10 | P7: 4.10 | Q7: 14:03
A8: Smarkets (exchange) | B8: LAY | C8: — | D8: 3 | E8: 0.4875 | G8: Betfair (exchange) | H8: LAY | I8: — | J8: 3.45 | K8: 12:39 | M8: Betfair (exchange) | N8: LAY | O8: — | P8: 4.05 | Q8: 14:03
A9: Exchange commission on winnings: 2% | G9: Exchange commission on winnings: 2% | M9: Exchange commission on winnings: 2%
G10: Wire note, 12:45 — Fulham starting XI announced: first-choice goalkeeper returns from injury.
A11: YOUR WORK — yellow cells only | M11: YOUR WORK — yellow cells only
A12: Back stake (given) | B12: 10 | G12: YOUR WORK — yellow cells only | M12: Back stake (given) | N12: 10
A13: Lay stake — reminder: back stake × back decimal ÷ (lay decimal − commission) | B13: =B12*D7/(D8-0.02) -> 10.402685 | G13: Back stake (given) | H13: 10 | M13: Lay stake — reminder: back stake × back decimal ÷ (lay decimal − commission) | N13: =N12*P7/(P8-0.02) -> 10.173697
G14: Lay stake — reminder: back stake × back decimal ÷ (lay decimal − commission) | H14: =H13*J7/(J8-0.02) -> 11.078717
B15: BOOKIE £ | C15: EXCHANGE £ | D15: NET £ | N15: BOOKIE £ | O15: EXCHANGE £ | P15: NET £
A16: IF EVERTON WIN | B16: =B12*(D7-1) -> 21 | C16: =-B13*(D8-1) -> -20.805369 | D16: =B16+C16 -> 0.19463087 | H16: BOOKIE £ | I16: EXCHANGE £ | J16: NET £ | M16: IF SUNDERLAND WIN | N16: =N12*(P7-1) -> 31 | O16: =-N13*(P8-1) -> -31.029777 | P16: =N16+O16 -> -0.029776675
A17: IF EVERTON DON'T WIN | B17: =-B12 -> -10 | C17: =B13*(1-0.02) -> 10.194631 | D17: =B17+C17 -> 0.19463087 | G17: IF IT'S A DRAW | H17: =H13*(J7-1) -> 28 | I17: =-H14*(J8-1) -> -27.142857 | J17: =H17+I17 -> 0.85714286 | M17: IF THEY DON'T | N17: =-N12 -> -10 | O17: =N13*(1-0.02) -> 9.9702233 | P17: =N17+O17 -> -0.029776675
A18: Money you pay out goes in as a minus, e.g. -0.35 for a 35p loss. | G18: IF IT ISN'T | H18: =-H13 -> -10 | I18: =H14*(1-0.02) -> 10.857143 | J18: =H18+I18 -> 0.85714286 | M18: Money you pay out goes in as a minus, e.g. -0.35 for a 35p loss.
G19: Money you pay out goes in as a minus, e.g. -0.35 for a 35p loss.
A20: VERDICT (REAL / STALE / EATEN) | B20: REAL | M20: NET per side if commission were 0% | N20: 0.12
A21: ONE LINE OF PROOF | B21: Both prices were taken at 11:42 and both outcomes make a profit after 2% commission. | G21: VERDICT (REAL / STALE / EATEN) | H21: STALE | M21: NET per side at the real 2% | N21: -0.03
G22: ONE LINE OF PROOF | H22: The lay price was taken at 12:39 before the 12:45 team news, while the back price was taken at 13:07 after the news. | M22: Same trade at £100 stakes — NET | N22: -0.3
A23: Then post the verdict + proof line in #trading-floor. 5 points a file.
G24: Then post the verdict + proof line in #trading-floor. 5 points a file. | M24: VERDICT (REAL / STALE / EATEN) | N24: EATEN
M25: ONE LINE OF PROOF | N25: Without commission the trade makes about £0.12 per side, but the real 2% commission turns it into about a £0.03 loss per side.
M27: Then post the verdict + proof line in #trading-floor. 5 points a file.

Sheet RADAR
A1: FALSE | B1: LIVE Wed 10:38 | D1: COMMISSION | E1: 0.05 | F1: LEAGUE | G1: La Liga
A3: MATCH | B3: OUTCOME | C3: BEST | D3: WHERE | E3: BACK | F3: LAY | G3: GAP | H3: RATING | I3: VERDICT
A4: Real Madrid v Real Sociedad | B4: Real Madrid | C4: 1.26 | D4: Grosvenor | E4: 1.3 | F4: 1.31 | G4: =IF(OR($C4="",$C4=0,$F4=""),"",$C4/$F4-1) -> -0.038167939 | H4: =IF($G4="","",($C4*(1-$E$1))/($F4-$E$1)) -> 0.95 | I4: =IF($H4="","",IF($H4>1,"LOOK","NO")) -> NO
A5: Real Madrid v Real Sociedad | B5: Draw | C5: 6.5 | D5: LeoVegas | E5: 6.6 | F5: 6.8 | G5: =IF(OR($C5="",$C5=0,$F5=""),"",$C5/$F5-1) -> -0.044117647 | H5: =IF($G5="","",($C5*(1-$E$1))/($F5-$E$1)) -> 0.91481481 | I5: =IF($H5="","",IF($H5>1,"LOOK","NO")) -> NO
A6: Real Madrid v Real Sociedad | B6: Real Sociedad | C6: 11 | D6: Betfred (UK) | E6: 12 | F6: 12.5 | G6: =IF(OR($C6="",$C6=0,$F6=""),"",$C6/$F6-1) -> -0.12 | H6: =IF($G6="","",($C6*(1-$E$1))/($F6-$E$1)) -> 0.83935743 | I6: =IF($H6="","",IF($H6>1,"LOOK","NO")) -> NO
A7: Celta Vigo v CA Osasuna | B7: Celta Vigo | C7: 2 | D7: Grosvenor | E7: 2.04 | F7: 2.08 | G7: =IF(OR($C7="",$C7=0,$F7=""),"",$C7/$F7-1) -> -0.038461538 | H7: =IF($G7="","",($C7*(1-$E$1))/($F7-$E$1)) -> 0.93596059 | I7: =IF($H7="","",IF($H7>1,"LOOK","NO")) -> NO
A8: Celta Vigo v CA Osasuna | B8: Draw | C8: 3.4 | D8: Grosvenor | E8: 3.5 | F8: 3.55 | G8: =IF(OR($C8="",$C8=0,$F8=""),"",$C8/$F8-1) -> -0.042253521 | H8: =IF($G8="","",($C8*(1-$E$1))/($F8-$E$1)) -> 0.92285714 | I8: =IF($H8="","",IF($H8>1,"LOOK","NO")) -> NO
A9: Celta Vigo v CA Osasuna | B9: CA Osasuna | C9: 4.2 | D9: Coral | E9: 4.3 | F9: 4.4 | G9: =IF(OR($C9="",$C9=0,$F9=""),"",$C9/$F9-1) -> -0.045454545 | H9: =IF($G9="","",($C9*(1-$E$1))/($F9-$E$1)) -> 0.91724138 | I9: =IF($H9="","",IF($H9>1,"LOOK","NO")) -> NO
A10: Barcelona v Athletic Bilbao | B10: Barcelona | C10: 1.35 | D10: Coral | E10: 1.34 | F10: 1.35 | G10: =IF(OR($C10="",$C10=0,$F10=""),"",$C10/$F10-1) -> 0 | H10: =IF($G10="","",($C10*(1-$E$1))/($F10-$E$1)) -> 0.98653846 | I10: =IF($H10="","",IF($H10>1,"LOOK","NO")) -> NO
A11: Barcelona v Athletic Bilbao | B11: Draw | C11: 6.1 | D11: Grosvenor | E11: 6.4 | F11: 6.6 | G11: =IF(OR($C11="",$C11=0,$F11=""),"",$C11/$F11-1) -> -0.075757576 | H11: =IF($G11="","",($C11*(1-$E$1))/($F11-$E$1)) -> 0.88473282 | I11: =IF($H11="","",IF($H11>1,"LOOK","NO")) -> NO
A12: Barcelona v Athletic Bilbao | B12: Athletic Bilbao | C12: 9.5 | D12: Grosvenor | E12: 10 | F12: 10.5 | G12: =IF(OR($C12="",$C12=0,$F12=""),"",$C12/$F12-1) -> -0.095238095 | H12: =IF($G12="","",($C12*(1-$E$1))/($F12-$E$1)) -> 0.86363636 | I12: =IF($H12="","",IF($H12>1,"LOOK","NO")) -> NO
A13: Real Racing Club de Santander v Elche CF | B13: Real Racing Club de Santander | C13: 2.2 | D13: Ladbrokes | E13: 2.22 | F13: 2.26 | G13: =IF(OR($C13="",$C13=0,$F13=""),"",$C13/$F13-1) -> -0.026548673 | H13: =IF($G13="","",($C13*(1-$E$1))/($F13-$E$1)) -> 0.94570136 | I13: =IF($H13="","",IF($H13>1,"LOOK","NO")) -> NO
A14: Real Racing Club de Santander v Elche CF | B14: Draw | C14: 3.6 | D14: Betfred (UK) | E14: 3.6 | F14: 3.7 | G14: =IF(OR($C14="",$C14=0,$F14=""),"",$C14/$F14-1) -> -0.027027027 | H14: =IF($G14="","",($C14*(1-$E$1))/($F14-$E$1)) -> 0.9369863 | I14: =IF($H14="","",IF($H14>1,"LOOK","NO")) -> NO
A15: Real Racing Club de Santander v Elche CF | B15: Elche CF | C15: 3.5 | D15: Grosvenor | E15: 3.5 | F15: 3.65 | G15: =IF(OR($C15="",$C15=0,$F15=""),"",$C15/$F15-1) -> -0.04109589 | H15: =IF($G15="","",($C15*(1-$E$1))/($F15-$E$1)) -> 0.92361111 | I15: =IF($H15="","",IF($H15>1,"LOOK","NO")) -> NO
... A42: Barcelona v Rayo Vallecano | B42: Rayo Vallecano | C42: 13 | D42: Paddy Power | E42: 13 | F42: 15 | G42: =IF(OR($C42="",$C42=0,$F42=""),"",$C42/$F42-1) -> -0.13333333 | H42: =IF($G42="","",($C42*(1-$E$1))/($F42-$E$1)) -> 0.82608696 | I42: =IF($H42="","",IF($H42>1,"LOOK","NO")) -> NO
G43: =IF(OR($C43="",$C43=0,$F43=""),"",$C43/$F43-1) | H43: =IF($G43="","",($C43*(1-$E$1))/($F43-$E$1)) | I43: =IF($H43="","",IF($H43>1,"LOOK","NO"))
G44: =IF(OR($C44="",$C44=0,$F44=""),"",$C44/$F44-1) | H44: =IF($G44="","",($C44*(1-$E$1))/($F44-$E$1)) | I44: =IF($H44="","",IF($H44>1,"LOOK","NO"))
G45: =IF(OR($C45="",$C45=0,$F45=""),"",$C45/$F45-1) | H45: =IF($G45="","",($C45*(1-$E$1))/($F45-$E$1)) | I45: =IF($H45="","",IF($H45>1,"LOOK","NO"))
G46: =IF(OR($C46="",$C46=0,$F46=""),"",$C46/$F46-1) | H46: =IF($G46="","",($C46*(1-$E$1))/($F46-$E$1)) | I46: =IF($H46="","",IF($H46>1,"LOOK","NO"))
G47: =IF(OR($C47="",$C47=0,$F47=""),"",$C47/$F47-1) | H47: =IF($G47="","",($C47*(1-$E$1))/($F47-$E$1)) | I47: =IF($H47="","",IF($H47>1,"LOOK","NO"))
G48: =IF(OR($C48="",$C48=0,$F48=""),"",$C48/$F48-1) | H48: =IF($G48="","",($C48*(1-$E$1))/($F48-$E$1)) | I48: =IF($H48="","",IF($H48>1,"LOOK","NO"))
G49: =IF(OR($C49="",$C49=0,$F49=""),"",$C49/$F49-1) | H49: =IF($G49="","",($C49*(1-$E$1))/($F49-$E$1)) | I49: =IF($H49="","",IF($H49>1,"LOOK","NO"))
G50: =IF(OR($C50="",$C50=0,$F50=""),"",$C50/$F50-1) | H50: =IF($G50="","",($C50*(1-$E$1))/($F50-$E$1)) | I50: =IF($H50="","",IF($H50>1,"LOOK","NO"))
G51: =IF(OR($C51="",$C51=0,$F51=""),"",$C51/$F51-1) | H51: =IF($G51="","",($C51*(1-$E$1))/($F51-$E$1)) | I51: =IF($H51="","",IF($H51>1,"LOOK","NO"))
G52: =IF(OR($C52="",$C52=0,$F52=""),"",$C52/$F52-1) | H52: =IF($G52="","",($C52*(1-$E$1))/($F52-$E$1)) | I52: =IF($H52="","",IF($H52>1,"LOOK","NO"))
G53: =IF(OR($C53="",$C53=0,$F53=""),"",$C53/$F53-1) | H53: =IF($G53="","",($C53*(1-$E$1))/($F53-$E$1)) | I53: =IF($H53="","",IF($H53>1,"LOOK","NO"))
G54: =IF(OR($C54="",$C54=0,$F54=""),"",$C54/$F54-1) | H54: =IF($G54="","",($C54*(1-$E$1))/($F54-$E$1)) | I54: =IF($H54="","",IF($H54>1,"LOOK","NO"))
... G63: =IF(OR($C63="",$C63=0,$F63=""),"",$C63/$F63-1) | H63: =IF($G63="","",($C63*(1-$E$1))/($F63-$E$1)) | I63: =IF($H63="","",IF($H63>1,"LOOK","NO"))
A501: Dallas Cowboys v Philadelphia Eagles | B501: Philadelphia Eagles | C501: 2.04 | D501: Unibet (UK)
A502: Buffalo Bills v Kansas City Chiefs | B502: Buffalo Bills | C502: 1.65 | D502: Unibet (UK)
A503: Buffalo Bills v Kansas City Chiefs | B503: Draw | C503: 0
A504: Buffalo Bills v Kansas City Chiefs | B504: Kansas City Chiefs | C504: 2.25 | D504: Paddy Power
A505: Pittsburgh Steelers v Denver Broncos | B505: Pittsburgh Steelers | C505: 2.1 | D505: Paddy Power
A506: Pittsburgh Steelers v Denver Broncos | B506: Draw | C506: 0
A507: Pittsburgh Steelers v Denver Broncos | B507: Denver Broncos | C507: 1.73 | D507: Paddy Power
A508: Minnesota Vikings v Atlanta Falcons | B508: Minnesota Vikings | C508: 0
A509: Minnesota Vikings v Atlanta Falcons | B509: Draw | C509: 0
A510: Minnesota Vikings v Atlanta Falcons | B510: Atlanta Falcons | C510: 0
A511: Houston Texans v Baltimore Ravens | B511: Houston Texans | C511: 0
A512: Houston Texans v Baltimore Ravens | B512: Draw | C512: 0
A513: Houston Texans v Baltimore Ravens | B513: Baltimore Ravens | C513: 0
A514: Cincinnati Bengals v New Orleans Saints | B514: Cincinnati Bengals | C514: 0
A515: Cincinnati Bengals v New Orleans Saints | B515: Draw | C515: 0
A516: Cincinnati Bengals v New Orleans Saints | B516: New Orleans Saints | C516: 0
A517: Cleveland Browns v Las Vegas Raiders | B517: Cleveland Browns | C517: 0
A518: Cleveland Browns v Las Vegas Raiders | B518: Draw | C518: 0
A519: Cleveland Browns v Las Vegas Raiders | B519: Las Vegas Raiders | C519: 0
... A675: Kansas City Chiefs v New England Patriots | B675: New England Patriots | C675: 0
A676: Philadelphia Eagles v Houston Texans | B676: Philadelphia Eagles | C676: 1.75 | D676: Unibet (UK)
A677: Philadelphia Eagles v Houston Texans | B677: Draw | C677: 0
A678: Philadelphia Eagles v Houston Texans | B678: Houston Texans | C678: 2.1 | D678: Paddy Power
A679: Chicago Bears v Green Bay Packers | B679: Chicago Bears | C679: 1.83 | D679: Unibet (UK)
A680: Chicago Bears v Green Bay Packers | B680: Draw | C680: 0
A681: Chicago Bears v Green Bay Packers | B681: Green Bay Packers | C681: 2 | D681: Paddy Power
A682: Denver Broncos v Buffalo Bills | B682: Denver Broncos | C682: 2.1 | D682: Unibet (UK)
A683: Denver Broncos v Buffalo Bills | B683: Draw | C683: 0
A684: Denver Broncos v Buffalo Bills | B684: Buffalo Bills | C684: 1.75 | D684: Unibet (UK)
A685: Seattle Seahawks v Los Angeles Rams | B685: Seattle Seahawks | C685: 2 | D685: Paddy Power
A686: Seattle Seahawks v Los Angeles Rams | B686: Draw | C686: 0
A687: Seattle Seahawks v Los Angeles Rams | B687: Los Angeles Rams | C687: 1.9 | D687: Unibet (UK)
A688: New Orleans Saints v Arizona Cardinals | B688: New Orleans Saints | C688: 0
A689: New Orleans Saints v Arizona Cardinals | B689: Draw | C689: 0
A690: New Orleans Saints v Arizona Cardinals | B690: Arizona Cardinals | C690: 0
A691: Atlanta Falcons v Tampa Bay Buccaneers | B691: Atlanta Falcons | C691: 0
A692: Atlanta Falcons v Tampa Bay Buccaneers | B692: Draw | C692: 0
A693: Atlanta Falcons v Tampa Bay Buccaneers | B693: Tampa Bay Buccaneers | C693: 0
A694: Baltimore Ravens v Cleveland Browns | B694: Baltimore Ravens | C694: 0
A695: Baltimore Ravens v Cleveland Browns | B695: Draw | C695: 0
A696: Baltimore Ravens v Cleveland Browns | B696: Cleveland Browns | C696: 0
A697: Pittsburgh Steelers v Carolina Panthers | B697: Pittsburgh Steelers | C697: 0
A698: Pittsburgh Steelers v Carolina Panthers | B698: Draw | C698: 0
A699: Pittsburgh Steelers v Carolina Panthers | B699: Carolina Panthers | C699: 0
... A819: Los Angeles Rams v Seattle Seahawks | B819: Seattle Seahawks | C819: 0

Sheet LOG
A1: DATE | B1: MATCH + OUTCOME | C1: GAP | D1: RATING | E1: YOUR CALL | F1: PRICE AT KICK OFF | G1: RIGHT?

Sheet CARD
A1: IDEA | B1: STATUS | C1: KILLING FILTER
A2: DEADLINE — A one-screen tool that shows me exactly what uni work I need to do next, based on urgency and deadline | B2: SURVIVED
A3: MATCHDAY — A one-screen matchday tool that tells me the one football match most worth watching today and why. | B3: KILLED | C3: Problem — not a strong enough problem I actually have
A4: SPLIT — A one-screen tool for nights out that lets me enter a bill and instantly shows exactly what each mate owes. | B4: KILLED | C4: One action — splitting different bills can quickly require multiple inputs/actions
A7: PRODUCT CARD - DEADLINE
A9: WHAT IT DOES | B9: A one-screen tool that tells me which piece of uni work I should do next based on its deadline and urgency.
A10: THE MOMENT | B10: A student opens it when they sit down to work and don't know which assignment or task to start first.
A11: WHAT PEOPLE DO NOW | B11: Check different course pages, calendars and notes, then decide manually what is most urgent.
A12: THE 30 SECOND DEMO | B12: Enter my current assignments and deadlines → press one button → the tool shows the task I should work on next.
A13: VERSION 1 | B13: Enter tasks and deadlines, then rank them by urgency and show the highest-priority task.
A14: DONE WHEN | B14: Tasks can be entered; deadlines are accepted; one action ranks them; the most urgent task is clearly shown; missing/invalid information produces a clear error.
A17: PITCH
A18: VERDICT | B18: FUND
A19: TARGET DATE | B19: 46266
A20: WHAT WILL EXIST | B20: A working one-screen version of DEADLINE where I can enter tasks and deadlines, press one button, and it clearly shows me the most urgent task to work on next. Missing or invalid information will show a clear error.

Sheet DEADLINE (starter
A1: DEADLINE | B1: RANKED Wed 11:08 | F1: WHAT SHOULD I DO NEXT
A3: TASK | B3: DEADLINE | C3: URGENCY | D3: STATUS | F3: NEXT TASK
A4: SUBMIT PRESENTATION | B4: 46260 | C4: HIGH | D4: NOT DONE | F4: =IFERROR(__xludf.DUMMYFUNCTION("IFERROR(INDEX(SORT(FILTER({A4:A100,B4:B100,IF(C4:C100=""HIGH"",1,IF(C4:C100=""MEDIUM"",2,3))},A4:A100<>"""",D4:D100<>""DONE""),3,TRUE,2,TRUE),1,1),""NO TASKS"")"),"SUBMIT PRESENTATION") -> SUBMIT PRESENTATION
A5: FINISH ESSAY | B5: 46262 | C5: MEDIUM | D5: NOT DONE
A6: REVISE BUSINESS | B6: 46264 | C6: HIGH | D6: NOT DONE | F6: STATUS
F7: =IF(COUNTA(A4:A100)=0,"NO TASKS",IF(COUNTIFS(A4:A100,"<>",B4:B100,"")+COUNTIFS(A4:A100,"<>",C4:C100,"")+COUNTIFS(A4:A100,"<>",D4:D100,"")>0,"MISSING INFORMATION","READY")) -> READY

Sheet DEADLINE
A1: FALSE | B1: RANKED Wed 11:17
A2: {=IF(COUNTA(A4:A100)=0,"ADD A TASK BELOW",IF(COUNTIF(D4:D100,"NO DATE")>0,"FIX THE RED ROW FIRST","DO NEXT → "&INDEX(A4:A100,MATCH(MIN(B4:B100),B4:B100,0))))} -> DO NEXT → Submit Seminar reflection
A3: TASK | B3: DUE | C3: DAYS LEFT | D3: STATUS
A4: Submit Seminar reflection | B4: 46261 | C4: =IF($A4="","",IF(NOT(ISNUMBER($B4)),"ERR",$B4-TODAY())) -> -4 | D4: =IF($A4="","",IF(NOT(ISNUMBER($B4)),"NO DATE",IF($B4<TODAY(),"OVERDUE",IF($B4=TODAY(),"DUE TODAY","OK")))) -> OVERDUE
A5: Speak to tutor about Extra Time | B5: 46262 | C5: =IF($A5="","",IF(NOT(ISNUMBER($B5)),"ERR",$B5-TODAY())) -> -3 | D5: =IF($A5="","",IF(NOT(ISNUMBER($B5)),"NO DATE",IF($B5<TODAY(),"OVERDUE",IF($B5=TODAY(),"DUE TODAY","OK")))) -> OVERDUE
A6: Make accounting formula flashcards | B6: 46263 | C6: =IF($A6="","",IF(NOT(ISNUMBER($B6)),"ERR",$B6-TODAY())) -> -2 | D6: =IF($A6="","",IF(NOT(ISNUMBER($B6)),"NO DATE",IF($B6<TODAY(),"OVERDUE",IF($B6=TODAY(),"DUE TODAY","OK")))) -> OVERDUE
A7: Complete Business Ethics quiz | B7: 46265 | C7: =IF($A7="","",IF(NOT(ISNUMBER($B7)),"ERR",$B7-TODAY())) -> 0 | D7: =IF($A7="","",IF(NOT(ISNUMBER($B7)),"NO DATE",IF($B7<TODAY(),"OVERDUE",IF($B7=TODAY(),"DUE TODAY","OK")))) -> DUE TODAY
A8: prepare questions for marketing seminar | B8: 46267 | C8: =IF($A8="","",IF(NOT(ISNUMBER($B8)),"ERR",$B8-TODAY())) -> 2 | D8: =IF($A8="","",IF(NOT(ISNUMBER($B8)),"NO DATE",IF($B8<TODAY(),"OVERDUE",IF($B8=TODAY(),"DUE TODAY","OK")))) -> OK
A9: Qualitative Analysis revision for exam | B9: 46269 | C9: =IF($A9="","",IF(NOT(ISNUMBER($B9)),"ERR",$B9-TODAY())) -> 4 | D9: =IF($A9="","",IF(NOT(ISNUMBER($B9)),"NO DATE",IF($B9<TODAY(),"OVERDUE",IF($B9=TODAY(),"DUE TODAY","OK")))) -> OK
A10: Work and Society group presentation | B10: 46276 | C10: =IF($A10="","",IF(NOT(ISNUMBER($B10)),"ERR",$B10-TODAY())) -> 11 | D10: =IF($A10="","",IF(NOT(ISNUMBER($B10)),"NO DATE",IF($B10<TODAY(),"OVERDUE",IF($B10=TODAY(),"DUE TODAY","OK")))) -> OK
A11: Business Economics Coursework | B11: 46283 | C11: =IF($A11="","",IF(NOT(ISNUMBER($B11)),"ERR",$B11-TODAY())) -> 18 | D11: =IF($A11="","",IF(NOT(ISNUMBER($B11)),"NO DATE",IF($B11<TODAY(),"OVERDUE",IF($B11=TODAY(),"DUE TODAY","OK")))) -> OK

Sheet COMPASS
A1: COMPASS
A2: WHAT SHOULD I AIM FOR NEXT?
A3: 🎯 DO NOW | B3: {=IFERROR(INDEX($A$11:$A$100,MATCH(1,$N$11:$N$100,0)),"ADD GOALS")} -> Go to the gym 4x a week
A4: 🔥 MOST WANTED | B4: {=IFERROR(INDEX($A$11:$A$100,MATCH(1,$T$11:$T$100,0)),"ADD GOALS")} -> Travel to Australia | D4: 💰 CURRENT FUNDS | E4: 350
A5: 📅 BEST IN 1 YEAR | B5: {=IFERROR(INDEX($A$11:$A$100,MATCH(1,$U$11:$U$100,0)),"ADD GOALS")} -> Go to the gym 4x a week | D5: 💵 MONTHLY INCOME | E5: 50
A6: 🚀 BEST IN 3 YEARS | B6: {=IFERROR(INDEX($A$11:$A$100,MATCH(1,$V$11:$V$100,0)),"ADD GOALS")} -> Go to the gym 4x a week | D6: 💸 MONTHLY SPARE MONEY | E6: 70
A7: QUICK WIN | B7: =IFERROR(__xludf.DUMMYFUNCTION("IFERROR(INDEX($A$11:$A$100,MATCH(MAX(FILTER($F$11:$F$100+$J$11:$J$100,$D$11:$D$100<=MAX(0,$E$4-$E$8))),FILTER($F$11:$F$100+$J$11:$J$100,$D$11:$D$100<=MAX(0,$E$4-$E$8)),0)),""NONE YET"")"),"Look into USA semester/term abroad for 3rd year") -> Look into USA semester/term abroad for 3rd year | D7: ⏰ FREE HOURS / WEEK | E7: 40
D8: 🛟 CASH BUFFER | E8: 50
A10: GOAL | B10: CATEGORY | C10: TIMEFRAME | D10: COST £ | E10: HOURS/WEEK | F10: WANT /10 | G10: MONEY /10 | H10: TIME /10 | I10: DIFFICULTY /10 | J10: NOW /10 | K10: 1 YEAR /10 | L10: 3 YEARS /10 | M10: PRIORITY | N10: RANK | O10: VERDICT | P10: BLOCKER | Q10: NEXT MOVE | R10: FUNDING GAP | S10: Months to Afford | T10: WANT RANK | U10: 1 YEAR PRIORITY | V10: 3 YEAR PRIORITY
A11: Travel to Australia | B11: Travel | C11: 1-3 YEARS | D11: 7000 | E11: 1 | F11: 10 | G11: =IF(A11="","",IF(D11<=0,10,ROUND(MAX(1,MIN(10,(MAX(0,$E$4-$E$8)/D11)*10)),1))) -> 1 | H11: =IF(A11="","",IF(E11<=0,10,ROUND(MAX(1,MIN(10,10-(E11/MAX(1,$E$7)*10))),1))) -> 9.8 | I11: =IF(A11="","",ROUND(MIN(10,MAX(1, ((11-G11)*0.45)+ ((11-H11)*0.25)+ (MIN(10,E11/2)*0.2)+ (IF(C11="NOW",1,IF(C11="THIS YEAR",2,IF(C11="1 YEAR",3,IF(C11="1-3 YEARS",5,IF(C11="3 YEARS",7,6)))))*0.1) )),1)) -> 5.4 | J11: =IF(A11="","",ROUND((G11*0.4)+(H11*0.3)+((11-I11)*0.3),1)) -> 5 | K11: =IF(A11="","",ROUND( (MAX(1,MIN(10,IF(D11<=0,10,(MAX(0,$E$4-$E$8)+($E$6*12))/D11*10)))*0.4) + (MIN(10,H11+0.5)*0.3) + (MIN(10,12-I11)*0.3) ,1)) -> 5.6 | L11: =IF(A11="","",ROUND( (MAX(1,MIN(10,IF(D11<=0,10,(MAX(0,$E$4-$E$8)+($E$6*36))/D11*10)))*0.4) + (MIN(10,H11+1.5)*0.3) + (MIN(10,14-I11)*0.3) ,1)) -> 7.2 | M11: =IF(A11="","",ROUND((F11*0.45)+(J11*0.4)+((11-I11)*0.15),2)) -> 7.34 | N11: =IFERROR(__xludf.DUMMYFUNCTION("IF(A11="""","""",RANK(M11,FILTER($M$11:$M$100,$A$11:$A$100<>""""),0))"),18.0) -> 18 | O11: =IF(A11="","",IF(AND(F11>=8,J11<4),"DREAM",IF(J11>=8,"DO NOW",IF(J11>=6,"START PLANNING",IF(K11>=7,"BUILD TOWARDS","PARK"))))) -> PARK | P11: =IF(A11="","",IF(J11>=9,"NONE",IF(G11<=H11,IF(G11<=11-I11,"MONEY","DIFFICULTY"),IF(H11<=11-I11,"TIME","DIFFICULTY")))) -> MONEY | R11: =IF(A11="","",MAX(0,D11-MAX(0,$E$4-$E$8))) -> 6700 | S11: =IF(A11="","",IF(R11=0,0,IF($E$6<=0,"NO SAVINGS",ROUNDUP(R11/$E$6,0)))) -> 96 | T11: =IFERROR(__xludf.DUMMYFUNCTION("IF(A11="""","""",RANK(F11,FILTER($F$11:$F$100,$A$11:$A$100<>""""),0))"),1.0) -> 1 | U11: =IFERROR(__xludf.DUMMYFUNCTION("IF(A11="""","""",RANK( (F11*0.5+K11*0.5), FILTER($F$11:$F$100*0.5+$K$11:$K$100*0.5,$A$11:$A$100<>""""), 0))"),16.0) -> 16 | V11: =IFERROR(__xludf.DUMMYFUNCTION("IF(A11="""","""",RANK( (F11*0.65+L11*0.35), FILTER($F$11:$F$100*0.65+$L$11:$L$100*0.35,$A$11:$A$100<>""""), 0))"),6.0) -> 6
A12: Play tennis once a week | B12: Hobby | C12: NOW | D12: 0 | E12: 2 | F12: 7 | G12: =IF(A12="","",IF(D12<=0,10,ROUND(MAX(1,MIN(10,(MAX(0,$E$4-$E$8)/D12)*10)),1))) -> 10 | H12: =IF(A12="","",IF(E12<=0,10,ROUND(MAX(1,MIN(10,10-(E12/MAX(1,$E$7)*10))),1))) -> 9.5 | I12: =IF(A12="","",ROUND(MIN(10,MAX(1, ((11-G12)*0.45)+ ((11-H12)*0.25)+ (MIN(10,E12/2)*0.2)+ (IF(C12="NOW",1,IF(C12="THIS YEAR",2,IF(C12="1 YEAR",3,IF(C12="1-3 YEARS",5,IF(C12="3 YEARS",7,6)))))*0.1) )),1)) -> 1.1 | J12: =IF(A12="","",ROUND((G12*0.4)+(H12*0.3)+((11-I12)*0.3),1)) -> 9.8 | K12: =IF(A12="","",ROUND( (MAX(1,MIN(10,IF(D12<=0,10,(MAX(0,$E$4-$E$8)+($E$6*12))/D12*10)))*0.4) + (MIN(10,H12+0.5)*0.3) + (MIN(10,12-I12)*0.3) ,1)) -> 10 | L12: =IF(A12="","",ROUND( (MAX(1,MIN(10,IF(D12<=0,10,(MAX(0,$E$4-$E$8)+($E$6*36))/D12*10)))*0.4) + (MIN(10,H12+1.5)*0.3) + (MIN(10,14-I12)*0.3) ,1)) -> 10 | M12: =IF(A12="","",ROUND((F12*0.45)+(J12*0.4)+((11-I12)*0.15),2)) -> 8.56 | N12: =IFERROR(__xludf.DUMMYFUNCTION("IF(A12="""","""",RANK(M12,FILTER($M$11:$M$100,$A$11:$A$100<>""""),0))"),8.0) -> 8 | O12: =IF(A12="","",IF(AND(F12>=8,J12<4),"DREAM",IF(J12>=8,"DO NOW",IF(J12>=6,"START PLANNING",IF(K12>=7,"BUILD TOWARDS","PARK"))))) -> DO NOW | P12: =IF(A12="","",IF(J12>=9,"NONE",IF(G12<=H12,IF(G12<=11-I12,"MONEY","DIFFICULTY"),IF(H12<=11-I12,"TIME","DIFFICULTY")))) -> NONE | R12: =IF(A12="","",MAX(0,D12-MAX(0,$E$4-$E$8))) -> 0 | S12: =IF(A12="","",IF(R12=0,0,IF($E$6<=0,"NO SAVINGS",ROUNDUP(R12/$E$6,0)))) -> 0 | T12: =IFERROR(__xludf.DUMMYFUNCTION("IF(A12="""","""",RANK(F12,FILTER($F$11:$F$100,$A$11:$A$100<>""""),0))"),9.0) -> 9 | U12: =IFERROR(__xludf.DUMMYFUNCTION("IF(A12="""","""",RANK( (F12*0.5+K12*0.5), FILTER($F$11:$F$100*0.5+$K$11:$K$100*0.5,$A$11:$A$100<>""""), 0))"),7.0) -> 7 | V12: =IFERROR(__xludf.DUMMYFUNCTION("IF(A12="""","""",RANK( (F12*0.65+L12*0.35), FILTER($F$11:$F$100*0.65+$L$11:$L$100*0.35,$A$11:$A$100<>""""), 0))"),9.0) -> 9
A13: Get a First in university second year | B13: University | C13: THIS YEAR | D13: 0 | E13: 12 | F13: 10 | G13: =IF(A13="","",IF(D13<=0,10,ROUND(MAX(1,MIN(10,(MAX(0,$E$4-$E$8)/D13)*10)),1))) -> 10 | H13: =IF(A13="","",IF(E13<=0,10,ROUND(MAX(1,MIN(10,10-(E13/MAX(1,$E$7)*10))),1))) -> 7 | I13: =IF(A13="","",ROUND(MIN(10,MAX(1, ((11-G13)*0.45)+ ((11-H13)*0.25)+ (MIN(10,E13/2)*0.2)+ (IF(C13="NOW",1,IF(C13="THIS YEAR",2,IF(C13="1 YEAR",3,IF(C13="1-3 YEARS",5,IF(C13="3 YEARS",7,6)))))*0.1) )),1)) -> 2.9 | J13: =IF(A13="","",ROUND((G13*0.4)+(H13*0.3)+((11-I13)*0.3),1)) -> 8.5 | K13: =IF(A13="","",ROUND( (MAX(1,MIN(10,IF(D13<=0,10,(MAX(0,$E$4-$E$8)+($E$6*12))/D13*10)))*0.4) + (MIN(10,H13+0.5)*0.3) + (MIN(10,12-I13)*0.3) ,1)) -> 9 | L13: =IF(A13="","",ROUND( (MAX(1,MIN(10,IF(D13<=0,10,(MAX(0,$E$4-$E$8)+($E$6*36))/D13*10)))*0.4) + (MIN(10,H13+1.5)*0.3) + (MIN(10,14-I13)*0.3) ,1)) -> 9.6 | M13: =IF(A13="","",ROUND((F13*0.45)+(J13*0.4)+((11-I13)*0.15),2)) -> 9.12 | N13: =IFERROR(__xludf.DUMMYFUNCTION("IF(A13="""","""",RANK(M13,FILTER($M$11:$M$100,$A$11:$A$100<>""""),0))"),3.0) -> 3 | O13: =IF(A13="","",IF(AND(F13>=8,J13<4),"DREAM",IF(J13>=8,"DO NOW",IF(J13>=6,"START PLANNING",IF(K13>=7,"BUILD TOWARDS","PARK"))))) -> DO NOW | P13: =IF(A13="","",IF(J13>=9,"NONE",IF(G13<=H13,IF(G13<=11-I13,"MONEY","DIFFICULTY"),IF(H13<=11-I13,"TIME","DIFFICULTY")))) -> TIME | R13: =IF(A13="","",MAX(0,D13-MAX(0,$E$4-$E$8))) -> 0 | S13: =IF(A13="","",IF(R13=0,0,IF($E$6<=0,"NO SAVINGS",ROUNDUP(R13/$E$6,0)))) -> 0 | T13: =IFERROR(__xludf.DUMMYFUNCTION("IF(A13="""","""",RANK(F13,FILTER($F$11:$F$100,$A$11:$A$100<>""""),0))"),1.0) -> 1 | U13: =IFERROR(__xludf.DUMMYFUNCTION("IF(A13="""","""",RANK( (F13*0.5+K13*0.5), FILTER($F$11:$F$100*0.5+$K$11:$K$100*0.5,$A$11:$A$100<>""""), 0))"),2.0) -> 2 | V13: =IFERROR(__xludf.DUMMYFUNCTION("IF(A13="""","""",RANK( (F13*0.65+L13*0.35), FILTER($F$11:$F$100*0.65+$L$11:$L$100*0.35,$A$11:$A$100<>""""), 0))"),2.0) -> 2
A14: Save £2000 | B14: Money | C14: 1 YEAR | D14: 0 | E14: 0 | F14: 8 | G14: =IF(A14="","",IF(D14<=0,10,ROUND(MAX(1,MIN(10,(MAX(0,$E$4-$E$8)/D14)*10)),1))) -> 10 | H14: =IF(A14="","",IF(E14<=0,10,ROUND(MAX(1,MIN(10,10-(E14/MAX(1,$E$7)*10))),1))) -> 10 | I14: =IF(A14="","",ROUND(MIN(10,MAX(1, ((11-G14)*0.45)+ ((11-H14)*0.25)+ (MIN(10,E14/2)*0.2)+ (IF(C14="NOW",1,IF(C14="THIS YEAR",2,IF(C14="1 YEAR",3,IF(C14="1-3 YEARS",5,IF(C14="3 YEARS",7,6)))))*0.1) )),1)) -> 1 | J14: =IF(A14="","",ROUND((G14*0.4)+(H14*0.3)+((11-I14)*0.3),1)) -> 10 | K14: =IF(A14="","",ROUND( (MAX(1,MIN(10,IF(D14<=0,10,(MAX(0,$E$4-$E$8)+($E$6*12))/D14*10)))*0.4) + (MIN(10,H14+0.5)*0.3) + (MIN(10,12-I14)*0.3) ,1)) -> 10 | L14: =IF(A14="","",ROUND( (MAX(1,MIN(10,IF(D14<=0,10,(MAX(0,$E$4-$E$8)+($E$6*36))/D14*10)))*0.4) + (MIN(10,H14+1.5)*0.3) + (MIN(10,14-I14)*0.3) ,1)) -> 10 | M14: =IF(A14="","",ROUND((F14*0.45)+(J14*0.4)+((11-I14)*0.15),2)) -> 9.1 | N14: =IFERROR(__xludf.DUMMYFUNCTION("IF(A14="""","""",RANK(M14,FILTER($M$11:$M$100,$A$11:$A$100<>""""),0))"),4.0) -> 4 | O14: =IF(A14="","",IF(AND(F14>=8,J14<4),"DREAM",IF(J14>=8,"DO NOW",IF(J14>=6,"START PLANNING",IF(K14>=7,"BUILD TOWARDS","PARK"))))) -> DO NOW | P14: =IF(A14="","",IF(J14>=9,"NONE",IF(G14<=H14,IF(G14<=11-I14,"MONEY","DIFFICULTY"),IF(H14<=11-I14,"TIME","DIFFICULTY")))) -> NONE | R14: =IF(A14="","",MAX(0,D14-MAX(0,$E$4-$E$8))) -> 0 | S14: =IF(A14="","",IF(R14=0,0,IF($E$6<=0,"NO SAVINGS",ROUNDUP(R14/$E$6,0)))) -> 0 | T14: =IFERROR(__xludf.DUMMYFUNCTION("IF(A14="""","""",RANK(F14,FILTER($F$11:$F$100,$A$11:$A$100<>""""),0))"),7.0) -> 7 | U14: =IFERROR(__xludf.DUMMYFUNCTION("IF(A14="""","""",RANK( (F14*0.5+K14*0.5), FILTER($F$11:$F$100*0.5+$K$11:$K$100*0.5,$A$11:$A$100<>""""), 0))"),4.0) -> 4 | V14: =IFERROR(__xludf.DUMMYFUNCTION("IF(A14="""","""",RANK( (F14*0.65+L14*0.35), FILTER($F$11:$F$100*0.65+$L$11:$L$100*0.35,$A$11:$A$100<>""""), 0))"),7.0) -> 7
A15: Start at least 2 shifts a week at Univeristy (JOB) | B15: Career | C15: THIS YEAR | D15: 100 | E15: 18 | F15: 9 | G15: =IF(A15="","",IF(D15<=0,10,ROUND(MAX(1,MIN(10,(MAX(0,$E$4-$E$8)/D15)*10)),1))) -> 10 | H15: =IF(A15="","",IF(E15<=0,10,ROUND(MAX(1,MIN(10,10-(E15/MAX(1,$E$7)*10))),1))) -> 5.5 | I15: =IF(A15="","",ROUND(MIN(10,MAX(1, ((11-G15)*0.45)+ ((11-H15)*0.25)+ (MIN(10,E15/2)*0.2)+ (IF(C15="NOW",1,IF(C15="THIS YEAR",2,IF(C15="1 YEAR",3,IF(C15="1-3 YEARS",5,IF(C15="3 YEARS",7,6)))))*0.1) )),1)) -> 3.8 | J15: =IF(A15="","",ROUND((G15*0.4)+(H15*0.3)+((11-I15)*0.3),1)) -> 7.8 | K15: =IF(A15="","",ROUND( (MAX(1,MIN(10,IF(D15<=0,10,(MAX(0,$E$4-$E$8)+($E$6*12))/D15*10)))*0.4) + (MIN(10,H15+0.5)*0.3) + (MIN(10,12-I15)*0.3) ,1)) -> 8.3 | L15: =IF(A15="","",ROUND( (MAX(1,MIN(10,IF(D15<=0,10,(MAX(0,$E$4-$E$8)+($E$6*36))/D15*10)))*0.4) + (MIN(10,H15+1.5)*0.3) + (MIN(10,14-I15)*0.3) ,1)) -> 9.1 | M15: =IF(A15="","",ROUND((F15*0.45)+(J15*0.4)+((11-I15)*0.15),2)) -> 8.25 | N15: =IFERROR(__xludf.DUMMYFUNCTION("IF(A15="""","""",RANK(M15,FILTER($M$11:$M$100,$A$11:$A$100<>""""),0))"),11.0) -> 11 | O15: =IF(A15="","",IF(AND(F15>=8,J15<4),"DREAM",IF(J15>=8,"DO NOW",IF(J15>=6,"START PLANNING",IF(K15>=7,"BUILD TOWARDS","PARK"))))) -> START PLANNING | P15: =IF(A15="","",IF(J15>=9,"NONE",IF(G15<=H15,IF(G15<=11-I15,"MONEY","DIFFICULTY"),IF(H15<=11-I15,"TIME","DIFFICULTY")))) -> TIME | R15: =IF(A15="","",MAX(0,D15-MAX(0,$E$4-$E$8))) -> 0 | S15: =IF(A15="","",IF(R15=0,0,IF($E$6<=0,"NO SAVINGS",ROUNDUP(R15/$E$6,0)))) -> 0 | T15: =IFERROR(__xludf.DUMMYFUNCTION("IF(A15="""","""",RANK(F15,FILTER($F$11:$F$100,$A$11:$A$100<>""""),0))"),5.0) -> 5 | U15: =IFERROR(__xludf.DUMMYFUNCTION("IF(A15="""","""",RANK( (F15*0.5+K15*0.5), FILTER($F$11:$F$100*0.5+$K$11:$K$100*0.5,$A$11:$A$100<>""""), 0))"),6.0) -> 6 | V15: =IFERROR(__xludf.DUMMYFUNCTION("IF(A15="""","""",RANK( (F15*0.65+L15*0.35), FILTER($F$11:$F$100*0.65+$L$11:$L$100*0.35,$A$11:$A$100<>""""), 0))"),5.0) -> 5
A16: Tidy Room Daily | B16: Personal | C16: NOW | D16: 0 | E16: 2 | F16: 6 | G16: =IF(A16="","",IF(D16<=0,10,ROUND(MAX(1,MIN(10,(MAX(0,$E$4-$E$8)/D16)*10)),1))) -> 10 | H16: =IF(A16="","",IF(E16<=0,10,ROUND(MAX(1,MIN(10,10-(E16/MAX(1,$E$7)*10))),1))) -> 9.5 | I16: =IF(A16="","",ROUND(MIN(10,MAX(1, ((11-G16)*0.45)+ ((11-H16)*0.25)+ (MIN(10,E16/2)*0.2)+ (IF(C16="NOW",1,IF(C16="THIS YEAR",2,IF(C16="1 YEAR",3,IF(C16="1-3 YEARS",5,IF(C16="3 YEARS",7,6)))))*0.1) )),1)) -> 1.1 | J16: =IF(A16="","",ROUND((G16*0.4)+(H16*0.3)+((11-I16)*0.3),1)) -> 9.8 | K16: =IF(A16="","",ROUND( (MAX(1,MIN(10,IF(D16<=0,10,(MAX(0,$E$4-$E$8)+($E$6*12))/D16*10)))*0.4) + (MIN(10,H16+0.5)*0.3) + (MIN(10,12-I16)*0.3) ,1)) -> 10 | L16: =IF(A16="","",ROUND( (MAX(1,MIN(10,IF(D16<=0,10,(MAX(0,$E$4-$E$8)+($E$6*36))/D16*10)))*0.4) + (MIN(10,H16+1.5)*0.3) + (MIN(10,14-I16)*0.3) ,1)) -> 10 | M16: =IF(A16="","",ROUND((F16*0.45)+(J16*0.4)+((11-I16)*0.15),2)) -> 8.11 | N16: =IFERROR(__xludf.DUMMYFUNCTION("IF(A16="""","""",RANK(M16,FILTER($M$11:$M$100,$A$11:$A$100<>""""),0))"),12.0) -> 12 | O16: =IF(A16="","",IF(AND(F16>=8,J16<4),"DREAM",IF(J16>=8,"DO NOW",IF(J16>=6,"START PLANNING",IF(K16>=7,"BUILD TOWARDS","PARK"))))) -> DO NOW | P16: =IF(A16="","",IF(J16>=9,"NONE",IF(G16<=H16,IF(G16<=11-I16,"MONEY","DIFFICULTY"),IF(H16<=11-I16,"TIME","DIFFICULTY")))) -> NONE | R16: =IF(A16="","",MAX(0,D16-MAX(0,$E$4-$E$8))) -> 0 | S16: =IF(A16="","",IF(R16=0,0,IF($E$6<=0,"NO SAVINGS",ROUNDUP(R16/$E$6,0)))) -> 0 | T16: =IFERROR(__xludf.DUMMYFUNCTION("IF(A16="""","""",RANK(F16,FILTER($F$11:$F$100,$A$11:$A$100<>""""),0))"),14.0) -> 14 | U16: =IFERROR(__xludf.DUMMYFUNCTION("IF(A16="""","""",RANK( (F16*0.5+K16*0.5), FILTER($F$11:$F$100*0.5+$K$11:$K$100*0.5,$A$11:$A$100<>""""), 0))"),13.0) -> 13 | V16: =IFERROR(__xludf.DUMMYFUNCTION("IF(A16="""","""",RANK( (F16*0.65+L16*0.35), FILTER($F$11:$F$100*0.65+$L$11:$L$100*0.35,$A$11:$A$100<>""""), 0))"),14.0) -> 14
A17: Look into USA semester/term abroad for 3rd year | B17: University | C17: THIS YEAR | D17: 0 | E17: 1 | F17: 7 | G17: =IF(A17="","",IF(D17<=0,10,ROUND(MAX(1,MIN(10,(MAX(0,$E$4-$E$8)/D17)*10)),1))) -> 10 | H17: =IF(A17="","",IF(E17<=0,10,ROUND(MAX(1,MIN(10,10-(E17/MAX(1,$E$7)*10))),1))) -> 9.8 | I17: =IF(A17="","",ROUND(MIN(10,MAX(1, ((11-G17)*0.45)+ ((11-H17)*0.25)+ (MIN(10,E17/2)*0.2)+ (IF(C17="NOW",1,IF(C17="THIS YEAR",2,IF(C17="1 YEAR",3,IF(C17="1-3 YEARS",5,IF(C17="3 YEARS",7,6)))))*0.1) )),1)) -> 1.1 | J17: =IF(A17="","",ROUND((G17*0.4)+(H17*0.3)+((11-I17)*0.3),1)) -> 9.9 | K17: =IF(A17="","",ROUND( (MAX(1,MIN(10,IF(D17<=0,10,(MAX(0,$E$4-$E$8)+($E$6*12))/D17*10)))*0.4) + (MIN(10,H17+0.5)*0.3) + (MIN(10,12-I17)*0.3) ,1)) -> 10 | L17: =IF(A17="","",ROUND( (MAX(1,MIN(10,IF(D17<=0,10,(MAX(0,$E$4-$E$8)+($E$6*36))/D17*10)))*0.4) + (MIN(10,H17+1.5)*0.3) + (MIN(10,14-I17)*0.3) ,1)) -> 10 | M17: =IF(A17="","",ROUND((F17*0.45)+(J17*0.4)+((11-I17)*0.15),2)) -> 8.6 | N17: =IFERROR(__xludf.DUMMYFUNCTION("IF(A17="""","""",RANK(M17,FILTER($M$11:$M$100,$A$11:$A$100<>""""),0))"),7.0) -> 7 | O17: =IF(A17="","",IF(AND(F17>=8,J17<4),"DREAM",IF(J17>=8,"DO NOW",IF(J17>=6,"START PLANNING",IF(K17>=7,"BUILD TOWARDS","PARK"))))) -> DO NOW | P17: =IF(A17="","",IF(J17>=9,"NONE",IF(G17<=H17,IF(G17<=11-I17,"MONEY","DIFFICULTY"),IF(H17<=11-I17,"TIME","DIFFICULTY")))) -> NONE | R17: =IF(A17="","",MAX(0,D17-MAX(0,$E$4-$E$8))) -> 0 | S17: =IF(A17="","",IF(R17=0,0,IF($E$6<=0,"NO SAVINGS",ROUNDUP(R17/$E$6,0)))) -> 0 | T17: =IFERROR(__xludf.DUMMYFUNCTION("IF(A17="""","""",RANK(F17,FILTER($F$11:$F$100,$A$11:$A$100<>""""),0))"),9.0) -> 9 | U17: =IFERROR(__xludf.DUMMYFUNCTION("IF(A17="""","""",RANK( (F17*0.5+K17*0.5), FILTER($F$11:$F$100*0.5+$K$11:$K$100*0.5,$A$11:$A$100<>""""), 0))"),7.0) -> 7 | V17: =IFERROR(__xludf.DUMMYFUNCTION("IF(A17="""","""",RANK( (F17*0.65+L17*0.35), FILTER($F$11:$F$100*0.65+$L$11:$L$100*0.35,$A$11:$A$100<>""""), 0))"),9.0) -> 9
A18: Go to the gym 4x a week | B18: Health/Fitness | C18: NOW | D18: 100 | E18: 6 | F18: 10 | G18: =IF(A18="","",IF(D18<=0,10,ROUND(MAX(1,MIN(10,(MAX(0,$E$4-$E$8)/D18)*10)),1))) -> 10 | H18: =IF(A18="","",IF(E18<=0,10,ROUND(MAX(1,MIN(10,10-(E18/MAX(1,$E$7)*10))),1))) -> 8.5 | I18: =IF(A18="","",ROUND(MIN(10,MAX(1, ((11-G18)*0.45)+ ((11-H18)*0.25)+ (MIN(10,E18/2)*0.2)+ (IF(C18="NOW",1,IF(C18="THIS YEAR",2,IF(C18="1 YEAR",3,IF(C18="1-3 YEARS",5,IF(C18="3 YEARS",7,6)))))*0.1) )),1)) -> 1.8 | J18: =IF(A18="","",ROUND((G18*0.4)+(H18*0.3)+((11-I18)*0.3),1)) -> 9.3 | K18: =IF(A18="","",ROUND( (MAX(1,MIN(10,IF(D18<=0,10,(MAX(0,$E$4-$E$8)+($E$6*12))/D18*10)))*0.4) + (MIN(10,H18+0.5)*0.3) + (MIN(10,12-I18)*0.3) ,1)) -> 9.7 | L18: =IF(A18="","",ROUND( (MAX(1,MIN(10,IF(D18<=0,10,(MAX(0,$E$4-$E$8)+($E$6*36))/D18*10)))*0.4) + (MIN(10,H18+1.5)*0.3) + (MIN(10,14-I18)*0.3) ,1)) -> 10 | M18: =IF(A18="","",ROUND((F18*0.45)+(J18*0.4)+((11-I18)*0.15),2)) -> 9.6 | N18: =IFERROR(__xludf.DUMMYFUNCTION("IF(A18="""","""",RANK(M18,FILTER($M$11:$M$100,$A$11:$A$100<>""""),0))"),1.0) -> 1 | O18: =IF(A18="","",IF(AND(F18>=8,J18<4),"DREAM",IF(J18>=8,"DO NOW",IF(J18>=6,"START PLANNING",IF(K18>=7,"BUILD TOWARDS","PARK"))))) -> DO NOW | P18: =IF(A18="","",IF(J18>=9,"NONE",IF(G18<=H18,IF(G18<=11-I18,"MONEY","DIFFICULTY"),IF(H18<=11-I18,"TIME","DIFFICULTY")))) -> NONE | R18: =IF(A18="","",MAX(0,D18-MAX(0,$E$4-$E$8))) -> 0 | S18: =IF(A18="","",IF(R18=0,0,IF($E$6<=0,"NO SAVINGS",ROUNDUP(R18/$E$6,0)))) -> 0 | T18: =IFERROR(__xludf.DUMMYFUNCTION("IF(A18="""","""",RANK(F18,FILTER($F$11:$F$100,$A$11:$A$100<>""""),0))"),1.0) -> 1 | U18: =IFERROR(__xludf.DUMMYFUNCTION("IF(A18="""","""",RANK( (F18*0.5+K18*0.5), FILTER($F$11:$F$100*0.5+$K$11:$K$100*0.5,$A$11:$A$100<>""""), 0))"),1.0) -> 1 | V18: =IFERROR(__xludf.DUMMYFUNCTION("IF(A18="""","""",RANK( (F18*0.65+L18*0.35), FILTER($F$11:$F$100*0.65+$L$11:$L$100*0.35,$A$11:$A$100<>""""), 0))"),1.0) -> 1
A19: Give £20 money from weekly uni money to Mum | B19: Money | C19: THIS YEAR | D19: 0 | E19: 0 | F19: 7 | G19: =IF(A19="","",IF(D19<=0,10,ROUND(MAX(1,MIN(10,(MAX(0,$E$4-$E$8)/D19)*10)),1))) -> 10 | H19: =IF(A19="","",IF(E19<=0,10,ROUND(MAX(1,MIN(10,10-(E19/MAX(1,$E$7)*10))),1))) -> 10 | I19: =IF(A19="","",ROUND(MIN(10,MAX(1, ((11-G19)*0.45)+ ((11-H19)*0.25)+ (MIN(10,E19/2)*0.2)+ (IF(C19="NOW",1,IF(C19="THIS YEAR",2,IF(C19="1 YEAR",3,IF(C19="1-3 YEARS",5,IF(C19="3 YEARS",7,6)))))*0.1) )),1)) -> 1 | J19: =IF(A19="","",ROUND((G19*0.4)+(H19*0.3)+((11-I19)*0.3),1)) -> 10 | K19: =IF(A19="","",ROUND( (MAX(1,MIN(10,IF(D19<=0,10,(MAX(0,$E$4-$E$8)+($E$6*12))/D19*10)))*0.4) + (MIN(10,H19+0.5)*0.3) + (MIN(10,12-I19)*0.3) ,1)) -> 10 | L19: =IF(A19="","",ROUND( (MAX(1,MIN(10,IF(D19<=0,10,(MAX(0,$E$4-$E$8)+($E$6*36))/D19*10)))*0.4) + (MIN(10,H19+1.5)*0.3) + (MIN(10,14-I19)*0.3) ,1)) -> 10 | M19: =IF(A19="","",ROUND((F19*0.45)+(J19*0.4)+((11-I19)*0.15),2)) -> 8.65 | N19: =IFERROR(__xludf.DUMMYFUNCTION("IF(A19="""","""",RANK(M19,FILTER($M$11:$M$100,$A$11:$A$100<>""""),0))"),6.0) -> 6 | O19: =IF(A19="","",IF(AND(F19>=8,J19<4),"DREAM",IF(J19>=8,"DO NOW",IF(J19>=6,"START PLANNING",IF(K19>=7,"BUILD TOWARDS","PARK"))))) -> DO NOW | P19: =IF(A19="","",IF(J19>=9,"NONE",IF(G19<=H19,IF(G19<=11-I19,"MONEY","DIFFICULTY"),IF(H19<=11-I19,"TIME","DIFFICULTY")))) -> NONE | R19: =IF(A19="","",MAX(0,D19-MAX(0,$E$4-$E$8))) -> 0 | S19: =IF(A19="","",IF(R19=0,0,IF($E$6<=0,"NO SAVINGS",ROUNDUP(R19/$E$6,0)))) -> 0 | T19: =IFERROR(__xludf.DUMMYFUNCTION("IF(A19="""","""",RANK(F19,FILTER($F$11:$F$100,$A$11:$A$100<>""""),0))"),9.0) -> 9 | U19: =IFERROR(__xludf.DUMMYFUNCTION("IF(A19="""","""",RANK( (F19*0.5+K19*0.5), FILTER($F$11:$F$100*0.5+$K$11:$K$100*0.5,$A$11:$A$100<>""""), 0))"),7.0) -> 7 | V19: =IFERROR(__xludf.DUMMYFUNCTION("IF(A19="""","""",RANK( (F19*0.65+L19*0.35), FILTER($F$11:$F$100*0.65+$L$11:$L$100*0.35,$A$11:$A$100<>""""), 0))"),9.0) -> 9
A20: Buy new clothes | B20: Personal | C20: NOW | D20: 300 | E20: 1 | F20: 5 | G20: =IF(A20="","",IF(D20<=0,10,ROUND(MAX(1,MIN(10,(MAX(0,$E$4-$E$8)/D20)*10)),1))) -> 10 | H20: =IF(A20="","",IF(E20<=0,10,ROUND(MAX(1,MIN(10,10-(E20/MAX(1,$E$7)*10))),1))) -> 9.8 | I20: =IF(A20="","",ROUND(MIN(10,MAX(1, ((11-G20)*0.45)+ ((11-H20)*0.25)+ (MIN(10,E20/2)*0.2)+ (IF(C20="NOW",1,IF(C20="THIS YEAR",2,IF(C20="1 YEAR",3,IF(C20="1-3 YEARS",5,IF(C20="3 YEARS",7,6)))))*0.1) )),1)) -> 1 | J20: =IF(A20="","",ROUND((G20*0.4)+(H20*0.3)+((11-I20)*0.3),1)) -> 9.9 | K20: =IF(A20="","",ROUND( (MAX(1,MIN(10,IF(D20<=0,10,(MAX(0,$E$4-$E$8)+($E$6*12))/D20*10)))*0.4) + (MIN(10,H20+0.5)*0.3) + (MIN(10,12-I20)*0.3) ,1)) -> 10 | L20: =IF(A20="","",ROUND( (MAX(1,MIN(10,IF(D20<=0,10,(MAX(0,$E$4-$E$8)+($E$6*36))/D20*10)))*0.4) + (MIN(10,H20+1.5)*0.3) + (MIN(10,14-I20)*0.3) ,1)) -> 10 | M20: =IF(A20="","",ROUND((F20*0.45)+(J20*0.4)+((11-I20)*0.15),2)) -> 7.71 | N20: =IFERROR(__xludf.DUMMYFUNCTION("IF(A20="""","""",RANK(M20,FILTER($M$11:$M$100,$A$11:$A$100<>""""),0))"),15.0) -> 15 | O20: =IF(A20="","",IF(AND(F20>=8,J20<4),"DREAM",IF(J20>=8,"DO NOW",IF(J20>=6,"START PLANNING",IF(K20>=7,"BUILD TOWARDS","PARK"))))) -> DO NOW | P20: =IF(A20="","",IF(J20>=9,"NONE",IF(G20<=H20,IF(G20<=11-I20,"MONEY","DIFFICULTY"),IF(H20<=11-I20,"TIME","DIFFICULTY")))) -> NONE | R20: =IF(A20="","",MAX(0,D20-MAX(0,$E$4-$E$8))) -> 0 | S20: =IF(A20="","",IF(R20=0,0,IF($E$6<=0,"NO SAVINGS",ROUNDUP(R20/$E$6,0)))) -> 0 | T20: =IFERROR(__xludf.DUMMYFUNCTION("IF(A20="""","""",RANK(F20,FILTER($F$11:$F$100,$A$11:$A$100<>""""),0))"),17.0) -> 17 | U20: =IFERROR(__xludf.DUMMYFUNCTION("IF(A20="""","""",RANK( (F20*0.5+K20*0.5), FILTER($F$11:$F$100*0.5+$K$11:$K$100*0.5,$A$11:$A$100<>""""), 0))"),17.0) -> 17 | V20: =IFERROR(__xludf.DUMMYFUNCTION("IF(A20="""","""",RANK( (F20*0.65+L20*0.35), FILTER($F$11:$F$100*0.65+$L$11:$L$100*0.35,$A$11:$A$100<>""""), 0))"),17.0) -> 17
A21: Get a summer internship | B21: Career | C21: 1 YEAR | D21: 100 | E21: 2 | F21: 6 | G21: =IF(A21="","",IF(D21<=0,10,ROUND(MAX(1,MIN(10,(MAX(0,$E$4-$E$8)/D21)*10)),1))) -> 10 | H21: =IF(A21="","",IF(E21<=0,10,ROUND(MAX(1,MIN(10,10-(E21/MAX(1,$E$7)*10))),1))) -> 9.5 | I21: =IF(A21="","",ROUND(MIN(10,MAX(1, ((11-G21)*0.45)+ ((11-H21)*0.25)+ (MIN(10,E21/2)*0.2)+ (IF(C21="NOW",1,IF(C21="THIS YEAR",2,IF(C21="1 YEAR",3,IF(C21="1-3 YEARS",5,IF(C21="3 YEARS",7,6)))))*0.1) )),1)) -> 1.3 | J21: =IF(A21="","",ROUND((G21*0.4)+(H21*0.3)+((11-I21)*0.3),1)) -> 9.8 | K21: =IF(A21="","",ROUND( (MAX(1,MIN(10,IF(D21<=0,10,(MAX(0,$E$4-$E$8)+($E$6*12))/D21*10)))*0.4) + (MIN(10,H21+0.5)*0.3) + (MIN(10,12-I21)*0.3) ,1)) -> 10 | L21: =IF(A21="","",ROUND( (MAX(1,MIN(10,IF(D21<=0,10,(MAX(0,$E$4-$E$8)+($E$6*36))/D21*10)))*0.4) + (MIN(10,H21+1.5)*0.3) + (MIN(10,14-I21)*0.3) ,1)) -> 10 | M21: =IF(A21="","",ROUND((F21*0.45)+(J21*0.4)+((11-I21)*0.15),2)) -> 8.08 | N21: =IFERROR(__xludf.DUMMYFUNCTION("IF(A21="""","""",RANK(M21,FILTER($M$11:$M$100,$A$11:$A$100<>""""),0))"),14.0) -> 14 | O21: =IF(A21="","",IF(AND(F21>=8,J21<4),"DREAM",IF(J21>=8,"DO NOW",IF(J21>=6,"START PLANNING",IF(K21>=7,"BUILD TOWARDS","PARK"))))) -> DO NOW | P21: =IF(A21="","",IF(J21>=9,"NONE",IF(G21<=H21,IF(G21<=11-I21,"MONEY","DIFFICULTY"),IF(H21<=11-I21,"TIME","DIFFICULTY")))) -> NONE | R21: =IF(A21="","",MAX(0,D21-MAX(0,$E$4-$E$8))) -> 0 | S21: =IF(A21="","",IF(R21=0,0,IF($E$6<=0,"NO SAVINGS",ROUNDUP(R21/$E$6,0)))) -> 0 | T21: =IFERROR(__xludf.DUMMYFUNCTION("IF(A21="""","""",RANK(F21,FILTER($F$11:$F$100,$A$11:$A$100<>""""),0))"),14.0) -> 14 | U21: =IFERROR(__xludf.DUMMYFUNCTION("IF(A21="""","""",RANK( (F21*0.5+K21*0.5), FILTER($F$11:$F$100*0.5+$K$11:$K$100*0.5,$A$11:$A$100<>""""), 0))"),13.0) -> 13 | V21: =IFERROR(__xludf.DUMMYFUNCTION("IF(A21="""","""",RANK( (F21*0.65+L21*0.35), FILTER($F$11:$F$100*0.65+$L$11:$L$100*0.35,$A$11:$A$100<>""""), 0))"),14.0) -> 14
A22: Update CV and Linkedin | B22: Career | C22: NOW | D22: 0 | E22: 2 | F22: 7 | G22: =IF(A22="","",IF(D22<=0,10,ROUND(MAX(1,MIN(10,(MAX(0,$E$4-$E$8)/D22)*10)),1))) -> 10 | H22: =IF(A22="","",IF(E22<=0,10,ROUND(MAX(1,MIN(10,10-(E22/MAX(1,$E$7)*10))),1))) -> 9.5 | I22: =IF(A22="","",ROUND(MIN(10,MAX(1, ((11-G22)*0.45)+ ((11-H22)*0.25)+ (MIN(10,E22/2)*0.2)+ (IF(C22="NOW",1,IF(C22="THIS YEAR",2,IF(C22="1 YEAR",3,IF(C22="1-3 YEARS",5,IF(C22="3 YEARS",7,6)))))*0.1) )),1)) -> 1.1 | J22: =IF(A22="","",ROUND((G22*0.4)+(H22*0.3)+((11-I22)*0.3),1)) -> 9.8 | K22: =IF(A22="","",ROUND( (MAX(1,MIN(10,IF(D22<=0,10,(MAX(0,$E$4-$E$8)+($E$6*12))/D22*10)))*0.4) + (MIN(10,H22+0.5)*0.3) + (MIN(10,12-I22)*0.3) ,1)) -> 10 | L22: =IF(A22="","",ROUND( (MAX(1,MIN(10,IF(D22<=0,10,(MAX(0,$E$4-$E$8)+($E$6*36))/D22*10)))*0.4) + (MIN(10,H22+1.5)*0.3) + (MIN(10,14-I22)*0.3) ,1)) -> 10 | M22: =IF(A22="","",ROUND((F22*0.45)+(J22*0.4)+((11-I22)*0.15),2)) -> 8.56 | N22: =IFERROR(__xludf.DUMMYFUNCTION("IF(A22="""","""",RANK(M22,FILTER($M$11:$M$100,$A$11:$A$100<>""""),0))"),8.0) -> 8 | O22: =IF(A22="","",IF(AND(F22>=8,J22<4),"DREAM",IF(J22>=8,"DO NOW",IF(J22>=6,"START PLANNING",IF(K22>=7,"BUILD TOWARDS","PARK"))))) -> DO NOW | P22: =IF(A22="","",IF(J22>=9,"NONE",IF(G22<=H22,IF(G22<=11-I22,"MONEY","DIFFICULTY"),IF(H22<=11-I22,"TIME","DIFFICULTY")))) -> NONE | R22: =IF(A22="","",MAX(0,D22-MAX(0,$E$4-$E$8))) -> 0 | S22: =IF(A22="","",IF(R22=0,0,IF($E$6<=0,"NO SAVINGS",ROUNDUP(R22/$E$6,0)))) -> 0 | T22: =IFERROR(__xludf.DUMMYFUNCTION("IF(A22="""","""",RANK(F22,FILTER($F$11:$F$100,$A$11:$A$100<>""""),0))"),9.0) -> 9 | U22: =IFERROR(__xludf.DUMMYFUNCTION("IF(A22="""","""",RANK( (F22*0.5+K22*0.5), FILTER($F$11:$F$100*0.5+$K$11:$K$100*0.5,$A$11:$A$100<>""""), 0))"),7.0) -> 7 | V22: =IFERROR(__xludf.DUMMYFUNCTION("IF(A22="""","""",RANK( (F22*0.65+L22*0.35), FILTER($F$11:$F$100*0.65+$L$11:$L$100*0.35,$A$11:$A$100<>""""), 0))"),9.0) -> 9
A23: Learn Excel to an advanced level | B23: Career | C23: THIS YEAR | D23: 30 | E23: 2 | F23: 6 | G23: =IF(A23="","",IF(D23<=0,10,ROUND(MAX(1,MIN(10,(MAX(0,$E$4-$E$8)/D23)*10)),1))) -> 10 | H23: =IF(A23="","",IF(E23<=0,10,ROUND(MAX(1,MIN(10,10-(E23/MAX(1,$E$7)*10))),1))) -> 9.5 | I23: =IF(A23="","",ROUND(MIN(10,MAX(1, ((11-G23)*0.45)+ ((11-H23)*0.25)+ (MIN(10,E23/2)*0.2)+ (IF(C23="NOW",1,IF(C23="THIS YEAR",2,IF(C23="1 YEAR",3,IF(C23="1-3 YEARS",5,IF(C23="3 YEARS",7,6)))))*0.1) )),1)) -> 1.2 | J23: =IF(A23="","",ROUND((G23*0.4)+(H23*0.3)+((11-I23)*0.3),1)) -> 9.8 | K23: =IF(A23="","",ROUND( (MAX(1,MIN(10,IF(D23<=0,10,(MAX(0,$E$4-$E$8)+($E$6*12))/D23*10)))*0.4) + (MIN(10,H23+0.5)*0.3) + (MIN(10,12-I23)*0.3) ,1)) -> 10 | L23: =IF(A23="","",ROUND( (MAX(1,MIN(10,IF(D23<=0,10,(MAX(0,$E$4-$E$8)+($E$6*36))/D23*10)))*0.4) + (MIN(10,H23+1.5)*0.3) + (MIN(10,14-I23)*0.3) ,1)) -> 10 | M23: =IF(A23="","",ROUND((F23*0.45)+(J23*0.4)+((11-I23)*0.15),2)) -> 8.09 | N23: =IFERROR(__xludf.DUMMYFUNCTION("IF(A23="""","""",RANK(M23,FILTER($M$11:$M$100,$A$11:$A$100<>""""),0))"),13.0) -> 13 | O23: =IF(A23="","",IF(AND(F23>=8,J23<4),"DREAM",IF(J23>=8,"DO NOW",IF(J23>=6,"START PLANNING",IF(K23>=7,"BUILD TOWARDS","PARK"))))) -> DO NOW | P23: =IF(A23="","",IF(J23>=9,"NONE",IF(G23<=H23,IF(G23<=11-I23,"MONEY","DIFFICULTY"),IF(H23<=11-I23,"TIME","DIFFICULTY")))) -> NONE | R23: =IF(A23="","",MAX(0,D23-MAX(0,$E$4-$E$8))) -> 0 | S23: =IF(A23="","",IF(R23=0,0,IF($E$6<=0,"NO SAVINGS",ROUNDUP(R23/$E$6,0)))) -> 0 | T23: =IFERROR(__xludf.DUMMYFUNCTION("IF(A23="""","""",RANK(F23,FILTER($F$11:$F$100,$A$11:$A$100<>""""),0))"),14.0) -> 14 | U23: =IFERROR(__xludf.DUMMYFUNCTION("IF(A23="""","""",RANK( (F23*0.5+K23*0.5), FILTER($F$11:$F$100*0.5+$K$11:$K$100*0.5,$A$11:$A$100<>""""), 0))"),13.0) -> 13 | V23: =IFERROR(__xludf.DUMMYFUNCTION("IF(A23="""","""",RANK( (F23*0.65+L23*0.35), FILTER($F$11:$F$100*0.65+$L$11:$L$100*0.35,$A$11:$A$100<>""""), 0))"),14.0) -> 14
A24: Attend every seminar for a term | B24: University | C24: THIS YEAR | D24: 0 | E24: 2 | F24: 7 | G24: =IF(A24="","",IF(D24<=0,10,ROUND(MAX(1,MIN(10,(MAX(0,$E$4-$E$8)/D24)*10)),1))) -> 10 | H24: =IF(A24="","",IF(E24<=0,10,ROUND(MAX(1,MIN(10,10-(E24/MAX(1,$E$7)*10))),1))) -> 9.5 | I24: =IF(A24="","",ROUND(MIN(10,MAX(1, ((11-G24)*0.45)+ ((11-H24)*0.25)+ (MIN(10,E24/2)*0.2)+ (IF(C24="NOW",1,IF(C24="THIS YEAR",2,IF(C24="1 YEAR",3,IF(C24="1-3 YEARS",5,IF(C24="3 YEARS",7,6)))))*0.1) )),1)) -> 1.2 | J24: =IF(A24="","",ROUND((G24*0.4)+(H24*0.3)+((11-I24)*0.3),1)) -> 9.8 | K24: =IF(A24="","",ROUND( (MAX(1,MIN(10,IF(D24<=0,10,(MAX(0,$E$4-$E$8)+($E$6*12))/D24*10)))*0.4) + (MIN(10,H24+0.5)*0.3) + (MIN(10,12-I24)*0.3) ,1)) -> 10 | L24: =IF(A24="","",ROUND( (MAX(1,MIN(10,IF(D24<=0,10,(MAX(0,$E$4-$E$8)+($E$6*36))/D24*10)))*0.4) + (MIN(10,H24+1.5)*0.3) + (MIN(10,14-I24)*0.3) ,1)) -> 10 | M24: =IF(A24="","",ROUND((F24*0.45)+(J24*0.4)+((11-I24)*0.15),2)) -> 8.54 | N24: =IFERROR(__xludf.DUMMYFUNCTION("IF(A24="""","""",RANK(M24,FILTER($M$11:$M$100,$A$11:$A$100<>""""),0))"),10.0) -> 10 | O24: =IF(A24="","",IF(AND(F24>=8,J24<4),"DREAM",IF(J24>=8,"DO NOW",IF(J24>=6,"START PLANNING",IF(K24>=7,"BUILD TOWARDS","PARK"))))) -> DO NOW | P24: =IF(A24="","",IF(J24>=9,"NONE",IF(G24<=H24,IF(G24<=11-I24,"MONEY","DIFFICULTY"),IF(H24<=11-I24,"TIME","DIFFICULTY")))) -> NONE | R24: =IF(A24="","",MAX(0,D24-MAX(0,$E$4-$E$8))) -> 0 | S24: =IF(A24="","",IF(R24=0,0,IF($E$6<=0,"NO SAVINGS",ROUNDUP(R24/$E$6,0)))) -> 0 | T24: =IFERROR(__xludf.DUMMYFUNCTION("IF(A24="""","""",RANK(F24,FILTER($F$11:$F$100,$A$11:$A$100<>""""),0))"),9.0) -> 9 | U24: =IFERROR(__xludf.DUMMYFUNCTION("IF(A24="""","""",RANK( (F24*0.5+K24*0.5), FILTER($F$11:$F$100*0.5+$K$11:$K$100*0.5,$A$11:$A$100<>""""), 0))"),7.0) -> 7 | V24: =IFERROR(__xludf.DUMMYFUNCTION("IF(A24="""","""",RANK( (F24*0.65+L24*0.35), FILTER($F$11:$F$100*0.65+$L$11:$L$100*0.35,$A$11:$A$100<>""""), 0))"),9.0) -> 9
A25: Read one business book per month | B25: Personal | C25: 1 YEAR | D25: 20 | E25: 2 | F25: 5 | G25: =IF(A25="","",IF(D25<=0,10,ROUND(MAX(1,MIN(10,(MAX(0,$E$4-$E$8)/D25)*10)),1))) -> 10 | H25: =IF(A25="","",IF(E25<=0,10,ROUND(MAX(1,MIN(10,10-(E25/MAX(1,$E$7)*10))),1))) -> 9.5 | I25: =IF(A25="","",ROUND(MIN(10,MAX(1, ((11-G25)*0.45)+ ((11-H25)*0.25)+ (MIN(10,E25/2)*0.2)+ (IF(C25="NOW",1,IF(C25="THIS YEAR",2,IF(C25="1 YEAR",3,IF(C25="1-3 YEARS",5,IF(C25="3 YEARS",7,6)))))*0.1) )),1)) -> 1.3 | J25: =IF(A25="","",ROUND((G25*0.4)+(H25*0.3)+((11-I25)*0.3),1)) -> 9.8 | K25: =IF(A25="","",ROUND( (MAX(1,MIN(10,IF(D25<=0,10,(MAX(0,$E$4-$E$8)+($E$6*12))/D25*10)))*0.4) + (MIN(10,H25+0.5)*0.3) + (MIN(10,12-I25)*0.3) ,1)) -> 10 | L25: =IF(A25="","",ROUND( (MAX(1,MIN(10,IF(D25<=0,10,(MAX(0,$E$4-$E$8)+($E$6*36))/D25*10)))*0.4) + (MIN(10,H25+1.5)*0.3) + (MIN(10,14-I25)*0.3) ,1)) -> 10 | M25: =IF(A25="","",ROUND((F25*0.45)+(J25*0.4)+((11-I25)*0.15),2)) -> 7.63 | N25: =IFERROR(__xludf.DUMMYFUNCTION("IF(A25="""","""",RANK(M25,FILTER($M$11:$M$100,$A$11:$A$100<>""""),0))"),16.0) -> 16 | O25: =IF(A25="","",IF(AND(F25>=8,J25<4),"DREAM",IF(J25>=8,"DO NOW",IF(J25>=6,"START PLANNING",IF(K25>=7,"BUILD TOWARDS","PARK"))))) -> DO NOW | P25: =IF(A25="","",IF(J25>=9,"NONE",IF(G25<=H25,IF(G25<=11-I25,"MONEY","DIFFICULTY"),IF(H25<=11-I25,"TIME","DIFFICULTY")))) -> NONE | R25: =IF(A25="","",MAX(0,D25-MAX(0,$E$4-$E$8))) -> 0 | S25: =IF(A25="","",IF(R25=0,0,IF($E$6<=0,"NO SAVINGS",ROUNDUP(R25/$E$6,0)))) -> 0 | T25: =IFERROR(__xludf.DUMMYFUNCTION("IF(A25="""","""",RANK(F25,FILTER($F$11:$F$100,$A$11:$A$100<>""""),0))"),17.0) -> 17 | U25: =IFERROR(__xludf.DUMMYFUNCTION("IF(A25="""","""",RANK( (F25*0.5+K25*0.5), FILTER($F$11:$F$100*0.5+$K$11:$K$100*0.5,$A$11:$A$100<>""""), 0))"),17.0) -> 17 | V25: =IFERROR(__xludf.DUMMYFUNCTION("IF(A25="""","""",RANK( (F25*0.65+L25*0.35), FILTER($F$11:$F$100*0.65+$L$11:$L$100*0.35,$A$11:$A$100<>""""), 0))"),17.0) -> 17
A26: Get consistently better sleep | B26: Personal | C26: NOW | D26: 0 | E26: 1 | F26: 8 | G26: =IF(A26="","",IF(D26<=0,10,ROUND(MAX(1,MIN(10,(MAX(0,$E$4-$E$8)/D26)*10)),1))) -> 10 | H26: =IF(A26="","",IF(E26<=0,10,ROUND(MAX(1,MIN(10,10-(E26/MAX(1,$E$7)*10))),1))) -> 9.8 | I26: =IF(A26="","",ROUND(MIN(10,MAX(1, ((11-G26)*0.45)+ ((11-H26)*0.25)+ (MIN(10,E26/2)*0.2)+ (IF(C26="NOW",1,IF(C26="THIS YEAR",2,IF(C26="1 YEAR",3,IF(C26="1-3 YEARS",5,IF(C26="3 YEARS",7,6)))))*0.1) )),1)) -> 1 | J26: =IF(A26="","",ROUND((G26*0.4)+(H26*0.3)+((11-I26)*0.3),1)) -> 9.9 | K26: =IF(A26="","",ROUND( (MAX(1,MIN(10,IF(D26<=0,10,(MAX(0,$E$4-$E$8)+($E$6*12))/D26*10)))*0.4) + (MIN(10,H26+0.5)*0.3) + (MIN(10,12-I26)*0.3) ,1)) -> 10 | L26: =IF(A26="","",ROUND( (MAX(1,MIN(10,IF(D26<=0,10,(MAX(0,$E$4-$E$8)+($E$6*36))/D26*10)))*0.4) + (MIN(10,H26+1.5)*0.3) + (MIN(10,14-I26)*0.3) ,1)) -> 10 | M26: =IF(A26="","",ROUND((F26*0.45)+(J26*0.4)+((11-I26)*0.15),2)) -> 9.06 | N26: =IFERROR(__xludf.DUMMYFUNCTION("IF(A26="""","""",RANK(M26,FILTER($M$11:$M$100,$A$11:$A$100<>""""),0))"),5.0) -> 5 | O26: =IF(A26="","",IF(AND(F26>=8,J26<4),"DREAM",IF(J26>=8,"DO NOW",IF(J26>=6,"START PLANNING",IF(K26>=7,"BUILD TOWARDS","PARK"))))) -> DO NOW | P26: =IF(A26="","",IF(J26>=9,"NONE",IF(G26<=H26,IF(G26<=11-I26,"MONEY","DIFFICULTY"),IF(H26<=11-I26,"TIME","DIFFICULTY")))) -> NONE | R26: =IF(A26="","",MAX(0,D26-MAX(0,$E$4-$E$8))) -> 0 | S26: =IF(A26="","",IF(R26=0,0,IF($E$6<=0,"NO SAVINGS",ROUNDUP(R26/$E$6,0)))) -> 0 | T26: =IFERROR(__xludf.DUMMYFUNCTION("IF(A26="""","""",RANK(F26,FILTER($F$11:$F$100,$A$11:$A$100<>""""),0))"),7.0) -> 7 | U26: =IFERROR(__xludf.DUMMYFUNCTION("IF(A26="""","""",RANK( (F26*0.5+K26*0.5), FILTER($F$11:$F$100*0.5+$K$11:$K$100*0.5,$A$11:$A$100<>""""), 0))"),4.0) -> 4 | V26: =IFERROR(__xludf.DUMMYFUNCTION("IF(A26="""","""",RANK( (F26*0.65+L26*0.35), FILTER($F$11:$F$100*0.65+$L$11:$L$100*0.35,$A$11:$A$100<>""""), 0))"),7.0) -> 7
A27: Visit 3 new countries | B27: Travel | C27: 1 YEAR | D27: 3000 | E27: 1 | F27: 10 | G27: =IF(A27="","",IF(D27<=0,10,ROUND(MAX(1,MIN(10,(MAX(0,$E$4-$E$8)/D27)*10)),1))) -> 1 | H27: =IF(A27="","",IF(E27<=0,10,ROUND(MAX(1,MIN(10,10-(E27/MAX(1,$E$7)*10))),1))) -> 9.8 | I27: =IF(A27="","",ROUND(MIN(10,MAX(1, ((11-G27)*0.45)+ ((11-H27)*0.25)+ (MIN(10,E27/2)*0.2)+ (IF(C27="NOW",1,IF(C27="THIS YEAR",2,IF(C27="1 YEAR",3,IF(C27="1-3 YEARS",5,IF(C27="3 YEARS",7,6)))))*0.1) )),1)) -> 5.2 | J27: =IF(A27="","",ROUND((G27*0.4)+(H27*0.3)+((11-I27)*0.3),1)) -> 5.1 | K27: =IF(A27="","",ROUND( (MAX(1,MIN(10,IF(D27<=0,10,(MAX(0,$E$4-$E$8)+($E$6*12))/D27*10)))*0.4) + (MIN(10,H27+0.5)*0.3) + (MIN(10,12-I27)*0.3) ,1)) -> 6.6 | L27: =IF(A27="","",ROUND( (MAX(1,MIN(10,IF(D27<=0,10,(MAX(0,$E$4-$E$8)+($E$6*36))/D27*10)))*0.4) + (MIN(10,H27+1.5)*0.3) + (MIN(10,14-I27)*0.3) ,1)) -> 9.4 | M27: =IF(A27="","",ROUND((F27*0.45)+(J27*0.4)+((11-I27)*0.15),2)) -> 7.41 | N27: =IFERROR(__xludf.DUMMYFUNCTION("IF(A27="""","""",RANK(M27,FILTER($M$11:$M$100,$A$11:$A$100<>""""),0))"),17.0) -> 17 | O27: =IF(A27="","",IF(AND(F27>=8,J27<4),"DREAM",IF(J27>=8,"DO NOW",IF(J27>=6,"START PLANNING",IF(K27>=7,"BUILD TOWARDS","PARK"))))) -> PARK | P27: =IF(A27="","",IF(J27>=9,"NONE",IF(G27<=H27,IF(G27<=11-I27,"MONEY","DIFFICULTY"),IF(H27<=11-I27,"TIME","DIFFICULTY")))) -> MONEY | R27: =IF(A27="","",MAX(0,D27-MAX(0,$E$4-$E$8))) -> 2700 | S27: =IF(A27="","",IF(R27=0,0,IF($E$6<=0,"NO SAVINGS",ROUNDUP(R27/$E$6,0)))) -> 39 | T27: =IFERROR(__xludf.DUMMYFUNCTION("IF(A27="""","""",RANK(F27,FILTER($F$11:$F$100,$A$11:$A$100<>""""),0))"),1.0) -> 1 | U27: =IFERROR(__xludf.DUMMYFUNCTION("IF(A27="""","""",RANK( (F27*0.5+K27*0.5), FILTER($F$11:$F$100*0.5+$K$11:$K$100*0.5,$A$11:$A$100<>""""), 0))"),12.0) -> 12 | V27: =IFERROR(__xludf.DUMMYFUNCTION("IF(A27="""","""",RANK( (F27*0.65+L27*0.35), FILTER($F$11:$F$100*0.65+$L$11:$L$100*0.35,$A$11:$A$100<>""""), 0))"),3.0) -> 3
A28: Do a semester abroad | B28: University | C28: 1-3 YEARS | D28: 0 | E28: 1 | F28: 9 | G28: =IF(A28="","",IF(D28<=0,10,ROUND(MAX(1,MIN(10,(MAX(0,$E$4-$E$8)/D28)*10)),1))) -> 10 | H28: =IF(A28="","",IF(E28<=0,10,ROUND(MAX(1,MIN(10,10-(E28/MAX(1,$E$7)*10))),1))) -> 9.8 | I28: =IF(A28="","",ROUND(MIN(10,MAX(1, ((11-G28)*0.45)+ ((11-H28)*0.25)+ (MIN(10,E28/2)*0.2)+ (IF(C28="NOW",1,IF(C28="THIS YEAR",2,IF(C28="1 YEAR",3,IF(C28="1-3 YEARS",5,IF(C28="3 YEARS",7,6)))))*0.1) )),1)) -> 1.4 | J28: =IF(A28="","",ROUND((G28*0.4)+(H28*0.3)+((11-I28)*0.3),1)) -> 9.8 | K28: =IF(A28="","",ROUND( (MAX(1,MIN(10,IF(D28<=0,10,(MAX(0,$E$4-$E$8)+($E$6*12))/D28*10)))*0.4) + (MIN(10,H28+0.5)*0.3) + (MIN(10,12-I28)*0.3) ,1)) -> 10 | L28: =IF(A28="","",ROUND( (MAX(1,MIN(10,IF(D28<=0,10,(MAX(0,$E$4-$E$8)+($E$6*36))/D28*10)))*0.4) + (MIN(10,H28+1.5)*0.3) + (MIN(10,14-I28)*0.3) ,1)) -> 10 | M28: =IF(A28="","",ROUND((F28*0.45)+(J28*0.4)+((11-I28)*0.15),2)) -> 9.41 | N28: =IFERROR(__xludf.DUMMYFUNCTION("IF(A28="""","""",RANK(M28,FILTER($M$11:$M$100,$A$11:$A$100<>""""),0))"),2.0) -> 2 | O28: =IF(A28="","",IF(AND(F28>=8,J28<4),"DREAM",IF(J28>=8,"DO NOW",IF(J28>=6,"START PLANNING",IF(K28>=7,"BUILD TOWARDS","PARK"))))) -> DO NOW | P28: =IF(A28="","",IF(J28>=9,"NONE",IF(G28<=H28,IF(G28<=11-I28,"MONEY","DIFFICULTY"),IF(H28<=11-I28,"TIME","DIFFICULTY")))) -> NONE | R28: =IF(A28="","",MAX(0,D28-MAX(0,$E$4-$E$8))) -> 0 | S28: =IF(A28="","",IF(R28=0,0,IF($E$6<=0,"NO SAVINGS",ROUNDUP(R28/$E$6,0)))) -> 0 | T28: =IFERROR(__xludf.DUMMYFUNCTION("IF(A28="""","""",RANK(F28,FILTER($F$11:$F$100,$A$11:$A$100<>""""),0))"),5.0) -> 5 | U28: =IFERROR(__xludf.DUMMYFUNCTION("IF(A28="""","""",RANK( (F28*0.5+K28*0.5), FILTER($F$11:$F$100*0.5+$K$11:$K$100*0.5,$A$11:$A$100<>""""), 0))"),2.0) -> 2 | V28: =IFERROR(__xludf.DUMMYFUNCTION("IF(A28="""","""",RANK( (F28*0.65+L28*0.35), FILTER($F$11:$F$100*0.65+$L$11:$L$100*0.35,$A$11:$A$100<>""""), 0))"),4.0) -> 4
G29: =IF(A29="","",IF(D29<=0,10,ROUND(MAX(1,MIN(10,(MAX(0,$E$4-$E$8)/D29)*10)),1))) | H29: =IF(A29="","",IF(E29<=0,10,ROUND(MAX(1,MIN(10,10-(E29/MAX(1,$E$7)*10))),1))) | I29: =IF(A29="","",ROUND(MIN(10,MAX(1, ((11-G29)*0.45)+ ((11-H29)*0.25)+ (MIN(10,E29/2)*0.2)+ (IF(C29="NOW",1,IF(C29="THIS YEAR",2,IF(C29="1 YEAR",3,IF(C29="1-3 YEARS",5,IF(C29="3 YEARS",7,6)))))*0.1) )),1)) | J29: =IF(A29="","",ROUND((G29*0.4)+(H29*0.3)+((11-I29)*0.3),1)) | K29: =IF(A29="","",ROUND( (MAX(1,MIN(10,IF(D29<=0,10,(MAX(0,$E$4-$E$8)+($E$6*12))/D29*10)))*0.4) + (MIN(10,H29+0.5)*0.3) + (MIN(10,12-I29)*0.3) ,1)) | L29: =IF(A29="","",ROUND( (MAX(1,MIN(10,IF(D29<=0,10,(MAX(0,$E$4-$E$8)+($E$6*36))/D29*10)))*0.4) + (MIN(10,H29+1.5)*0.3) + (MIN(10,14-I29)*0.3) ,1)) | M29: =IF(A29="","",ROUND((F29*0.45)+(J29*0.4)+((11-I29)*0.15),2)) | N29: =IFERROR(__xludf.DUMMYFUNCTION("IF(A29="""","""",RANK(M29,FILTER($M$11:$M$100,$A$11:$A$100<>""""),0))"),"") | O29: =IF(A29="","",IF(AND(F29>=8,J29<4),"DREAM",IF(J29>=8,"DO NOW",IF(J29>=6,"START PLANNING",IF(K29>=7,"BUILD TOWARDS","PARK"))))) | P29: =IF(A29="","",IF(J29>=9,"NONE",IF(G29<=H29,IF(G29<=11-I29,"MONEY","DIFFICULTY"),IF(H29<=11-I29,"TIME","DIFFICULTY")))) | R29: =IF(A29="","",MAX(0,D29-MAX(0,$E$4-$E$8))) | S29: =IF(A29="","",IF(R29=0,0,IF($E$6<=0,"NO SAVINGS",ROUNDUP(R29/$E$6,0)))) | T29: =IFERROR(__xludf.DUMMYFUNCTION("IF(A29="""","""",RANK(F29,FILTER($F$11:$F$100,$A$11:$A$100<>""""),0))"),"") | U29: =IFERROR(__xludf.DUMMYFUNCTION("IF(A29="""","""",RANK( (F29*0.5+K29*0.5), FILTER($F$11:$F$100*0.5+$K$11:$K$100*0.5,$A$11:$A$100<>""""), 0))"),"") | V29: =IFERROR(__xludf.DUMMYFUNCTION("IF(A29="""","""",RANK( (F29*0.65+L29*0.35), FILTER($F$11:$F$100*0.65+$L$11:$L$100*0.35,$A$11:$A$100<>""""), 0))"),"")
G30: =IF(A30="","",IF(D30<=0,10,ROUND(MAX(1,MIN(10,(MAX(0,$E$4-$E$8)/D30)*10)),1))) | H30: =IF(A30="","",IF(E30<=0,10,ROUND(MAX(1,MIN(10,10-(E30/MAX(1,$E$7)*10))),1))) | I30: =IF(A30="","",ROUND(MIN(10,MAX(1, ((11-G30)*0.45)+ ((11-H30)*0.25)+ (MIN(10,E30/2)*0.2)+ (IF(C30="NOW",1,IF(C30="THIS YEAR",2,IF(C30="1 YEAR",3,IF(C30="1-3 YEARS",5,IF(C30="3 YEARS",7,6)))))*0.1) )),1)) | J30: =IF(A30="","",ROUND((G30*0.4)+(H30*0.3)+((11-I30)*0.3),1)) | K30: =IF(A30="","",ROUND( (MAX(1,MIN(10,IF(D30<=0,10,(MAX(0,$E$4-$E$8)+($E$6*12))/D30*10)))*0.4) + (MIN(10,H30+0.5)*0.3) + (MIN(10,12-I30)*0.3) ,1)) | L30: =IF(A30="","",ROUND( (MAX(1,MIN(10,IF(D30<=0,10,(MAX(0,$E$4-$E$8)+($E$6*36))/D30*10)))*0.4) + (MIN(10,H30+1.5)*0.3) + (MIN(10,14-I30)*0.3) ,1)) | M30: =IF(A30="","",ROUND((F30*0.45)+(J30*0.4)+((11-I30)*0.15),2)) | N30: =IFERROR(__xludf.DUMMYFUNCTION("IF(A30="""","""",RANK(M30,FILTER($M$11:$M$100,$A$11:$A$100<>""""),0))"),"") | O30: =IF(A30="","",IF(AND(F30>=8,J30<4),"DREAM",IF(J30>=8,"DO NOW",IF(J30>=6,"START PLANNING",IF(K30>=7,"BUILD TOWARDS","PARK"))))) | P30: =IF(A30="","",IF(J30>=9,"NONE",IF(G30<=H30,IF(G30<=11-I30,"MONEY","DIFFICULTY"),IF(H30<=11-I30,"TIME","DIFFICULTY")))) | R30: =IF(A30="","",MAX(0,D30-MAX(0,$E$4-$E$8))) | S30: =IF(A30="","",IF(R30=0,0,IF($E$6<=0,"NO SAVINGS",ROUNDUP(R30/$E$6,0)))) | T30: =IFERROR(__xludf.DUMMYFUNCTION("IF(A30="""","""",RANK(F30,FILTER($F$11:$F$100,$A$11:$A$100<>""""),0))"),"") | U30: =IFERROR(__xludf.DUMMYFUNCTION("IF(A30="""","""",RANK( (F30*0.5+K30*0.5), FILTER($F$11:$F$100*0.5+$K$11:$K$100*0.5,$A$11:$A$100<>""""), 0))"),"") | V30: =IFERROR(__xludf.DUMMYFUNCTION("IF(A30="""","""",RANK( (F30*0.65+L30*0.35), FILTER($F$11:$F$100*0.65+$L$11:$L$100*0.35,$A$11:$A$100<>""""), 0))"),"")
G31: =IF(A31="","",IF(D31<=0,10,ROUND(MAX(1,MIN(10,(MAX(0,$E$4-$E$8)/D31)*10)),1))) | H31: =IF(A31="","",IF(E31<=0,10,ROUND(MAX(1,MIN(10,10-(E31/MAX(1,$E$7)*10))),1))) | I31: =IF(A31="","",ROUND(MIN(10,MAX(1, ((11-G31)*0.45)+ ((11-H31)*0.25)+ (MIN(10,E31/2)*0.2)+ (IF(C31="NOW",1,IF(C31="THIS YEAR",2,IF(C31="1 YEAR",3,IF(C31="1-3 YEARS",5,IF(C31="3 YEARS",7,6)))))*0.1) )),1)) | J31: =IF(A31="","",ROUND((G31*0.4)+(H31*0.3)+((11-I31)*0.3),1)) | K31: =IF(A31="","",ROUND( (MAX(1,MIN(10,IF(D31<=0,10,(MAX(0,$E$4-$E$8)+($E$6*12))/D31*10)))*0.4) + (MIN(10,H31+0.5)*0.3) + (MIN(10,12-I31)*0.3) ,1)) | L31: =IF(A31="","",ROUND( (MAX(1,MIN(10,IF(D31<=0,10,(MAX(0,$E$4-$E$8)+($E$6*36))/D31*10)))*0.4) + (MIN(10,H31+1.5)*0.3) + (MIN(10,14-I31)*0.3) ,1)) | M31: =IF(A31="","",ROUND((F31*0.45)+(J31*0.4)+((11-I31)*0.15),2)) | N31: =IFERROR(__xludf.DUMMYFUNCTION("IF(A31="""","""",RANK(M31,FILTER($M$11:$M$100,$A$11:$A$100<>""""),0))"),"") | O31: =IF(A31="","",IF(AND(F31>=8,J31<4),"DREAM",IF(J31>=8,"DO NOW",IF(J31>=6,"START PLANNING",IF(K31>=7,"BUILD TOWARDS","PARK"))))) | P31: =IF(A31="","",IF(J31>=9,"NONE",IF(G31<=H31,IF(G31<=11-I31,"MONEY","DIFFICULTY"),IF(H31<=11-I31,"TIME","DIFFICULTY")))) | R31: =IF(A31="","",MAX(0,D31-MAX(0,$E$4-$E$8))) | S31: =IF(A31="","",IF(R31=0,0,IF($E$6<=0,"NO SAVINGS",ROUNDUP(R31/$E$6,0)))) | T31: =IFERROR(__xludf.DUMMYFUNCTION("IF(A31="""","""",RANK(F31,FILTER($F$11:$F$100,$A$11:$A$100<>""""),0))"),"") | U31: =IFERROR(__xludf.DUMMYFUNCTION("IF(A31="""","""",RANK( (F31*0.5+K31*0.5), FILTER($F$11:$F$100*0.5+$K$11:$K$100*0.5,$A$11:$A$100<>""""), 0))"),"") | V31: =IFERROR(__xludf.DUMMYFUNCTION("IF(A31="""","""",RANK( (F31*0.65+L31*0.35), FILTER($F$11:$F$100*0.65+$L$11:$L$100*0.35,$A$11:$A$100<>""""), 0))"),"")
G32: =IF(A32="","",IF(D32<=0,10,ROUND(MAX(1,MIN(10,(MAX(0,$E$4-$E$8)/D32)*10)),1))) | H32: =IF(A32="","",IF(E32<=0,10,ROUND(MAX(1,MIN(10,10-(E32/MAX(1,$E$7)*10))),1))) | I32: =IF(A32="","",ROUND(MIN(10,MAX(1, ((11-G32)*0.45)+ ((11-H32)*0.25)+ (MIN(10,E32/2)*0.2)+ (IF(C32="NOW",1,IF(C32="THIS YEAR",2,IF(C32="1 YEAR",3,IF(C32="1-3 YEARS",5,IF(C32="3 YEARS",7,6)))))*0.1) )),1)) | J32: =IF(A32="","",ROUND((G32*0.4)+(H32*0.3)+((11-I32)*0.3),1)) | K32: =IF(A32="","",ROUND( (MAX(1,MIN(10,IF(D32<=0,10,(MAX(0,$E$4-$E$8)+($E$6*12))/D32*10)))*0.4) + (MIN(10,H32+0.5)*0.3) + (MIN(10,12-I32)*0.3) ,1)) | L32: =IF(A32="","",ROUND( (MAX(1,MIN(10,IF(D32<=0,10,(MAX(0,$E$4-$E$8)+($E$6*36))/D32*10)))*0.4) + (MIN(10,H32+1.5)*0.3) + (MIN(10,14-I32)*0.3) ,1)) | M32: =IF(A32="","",ROUND((F32*0.45)+(J32*0.4)+((11-I32)*0.15),2)) | N32: =IFERROR(__xludf.DUMMYFUNCTION("IF(A32="""","""",RANK(M32,FILTER($M$11:$M$100,$A$11:$A$100<>""""),0))"),"") | O32: =IF(A32="","",IF(AND(F32>=8,J32<4),"DREAM",IF(J32>=8,"DO NOW",IF(J32>=6,"START PLANNING",IF(K32>=7,"BUILD TOWARDS","PARK"))))) | P32: =IF(A32="","",IF(J32>=9,"NONE",IF(G32<=H32,IF(G32<=11-I32,"MONEY","DIFFICULTY"),IF(H32<=11-I32,"TIME","DIFFICULTY")))) | R32: =IF(A32="","",MAX(0,D32-MAX(0,$E$4-$E$8))) | S32: =IF(A32="","",IF(R32=0,0,IF($E$6<=0,"NO SAVINGS",ROUNDUP(R32/$E$6,0)))) | T32: =IFERROR(__xludf.DUMMYFUNCTION("IF(A32="""","""",RANK(F32,FILTER($F$11:$F$100,$A$11:$A$100<>""""),0))"),"") | U32: =IFERROR(__xludf.DUMMYFUNCTION("IF(A32="""","""",RANK( (F32*0.5+K32*0.5), FILTER($F$11:$F$100*0.5+$K$11:$K$100*0.5,$A$11:$A$100<>""""), 0))"),"") | V32: =IFERROR(__xludf.DUMMYFUNCTION("IF(A32="""","""",RANK( (F32*0.65+L32*0.35), FILTER($F$11:$F$100*0.65+$L$11:$L$100*0.35,$A$11:$A$100<>""""), 0))"),"")
G33: =IF(A33="","",IF(D33<=0,10,ROUND(MAX(1,MIN(10,(MAX(0,$E$4-$E$8)/D33)*10)),1))) | H33: =IF(A33="","",IF(E33<=0,10,ROUND(MAX(1,MIN(10,10-(E33/MAX(1,$E$7)*10))),1))) | I33: =IF(A33="","",ROUND(MIN(10,MAX(1, ((11-G33)*0.45)+ ((11-H33)*0.25)+ (MIN(10,E33/2)*0.2)+ (IF(C33="NOW",1,IF(C33="THIS YEAR",2,IF(C33="1 YEAR",3,IF(C33="1-3 YEARS",5,IF(C33="3 YEARS",7,6)))))*0.1) )),1)) | J33: =IF(A33="","",ROUND((G33*0.4)+(H33*0.3)+((11-I33)*0.3),1)) | K33: =IF(A33="","",ROUND( (MAX(1,MIN(10,IF(D33<=0,10,(MAX(0,$E$4-$E$8)+($E$6*12))/D33*10)))*0.4) + (MIN(10,H33+0.5)*0.3) + (MIN(10,12-I33)*0.3) ,1)) | L33: =IF(A33="","",ROUND( (MAX(1,MIN(10,IF(D33<=0,10,(MAX(0,$E$4-$E$8)+($E$6*36))/D33*10)))*0.4) + (MIN(10,H33+1.5)*0.3) + (MIN(10,14-I33)*0.3) ,1)) | M33: =IF(A33="","",ROUND((F33*0.45)+(J33*0.4)+((11-I33)*0.15),2)) | N33: =IFERROR(__xludf.DUMMYFUNCTION("IF(A33="""","""",RANK(M33,FILTER($M$11:$M$100,$A$11:$A$100<>""""),0))"),"") | O33: =IF(A33="","",IF(AND(F33>=8,J33<4),"DREAM",IF(J33>=8,"DO NOW",IF(J33>=6,"START PLANNING",IF(K33>=7,"BUILD TOWARDS","PARK"))))) | P33: =IF(A33="","",IF(J33>=9,"NONE",IF(G33<=H33,IF(G33<=11-I33,"MONEY","DIFFICULTY"),IF(H33<=11-I33,"TIME","DIFFICULTY")))) | R33: =IF(A33="","",MAX(0,D33-MAX(0,$E$4-$E$8))) | S33: =IF(A33="","",IF(R33=0,0,IF($E$6<=0,"NO SAVINGS",ROUNDUP(R33/$E$6,0)))) | T33: =IFERROR(__xludf.DUMMYFUNCTION("IF(A33="""","""",RANK(F33,FILTER($F$11:$F$100,$A$11:$A$100<>""""),0))"),"") | U33: =IFERROR(__xludf.DUMMYFUNCTION("IF(A33="""","""",RANK( (F33*0.5+K33*0.5), FILTER($F$11:$F$100*0.5+$K$11:$K$100*0.5,$A$11:$A$100<>""""), 0))"),"") | V33: =IFERROR(__xludf.DUMMYFUNCTION("IF(A33="""","""",RANK( (F33*0.65+L33*0.35), FILTER($F$11:$F$100*0.65+$L$11:$L$100*0.35,$A$11:$A$100<>""""), 0))"),"")
G34: =IF(A34="","",IF(D34<=0,10,ROUND(MAX(1,MIN(10,(MAX(0,$E$4-$E$8)/D34)*10)),1))) | H34: =IF(A34="","",IF(E34<=0,10,ROUND(MAX(1,MIN(10,10-(E34/MAX(1,$E$7)*10))),1))) | I34: =IF(A34="","",ROUND(MIN(10,MAX(1, ((11-G34)*0.45)+ ((11-H34)*0.25)+ (MIN(10,E34/2)*0.2)+ (IF(C34="NOW",1,IF(C34="THIS YEAR",2,IF(C34="1 YEAR",3,IF(C34="1-3 YEARS",5,IF(C34="3 YEARS",7,6)))))*0.1) )),1)) | J34: =IF(A34="","",ROUND((G34*0.4)+(H34*0.3)+((11-I34)*0.3),1)) | K34: =IF(A34="","",ROUND( (MAX(1,MIN(10,IF(D34<=0,10,(MAX(0,$E$4-$E$8)+($E$6*12))/D34*10)))*0.4) + (MIN(10,H34+0.5)*0.3) + (MIN(10,12-I34)*0.3) ,1)) | L34: =IF(A34="","",ROUND( (MAX(1,MIN(10,IF(D34<=0,10,(MAX(0,$E$4-$E$8)+($E$6*36))/D34*10)))*0.4) + (MIN(10,H34+1.5)*0.3) + (MIN(10,14-I34)*0.3) ,1)) | M34: =IF(A34="","",ROUND((F34*0.45)+(J34*0.4)+((11-I34)*0.15),2)) | N34: =IFERROR(__xludf.DUMMYFUNCTION("IF(A34="""","""",RANK(M34,FILTER($M$11:$M$100,$A$11:$A$100<>""""),0))"),"") | O34: =IF(A34="","",IF(AND(F34>=8,J34<4),"DREAM",IF(J34>=8,"DO NOW",IF(J34>=6,"START PLANNING",IF(K34>=7,"BUILD TOWARDS","PARK"))))) | P34: =IF(A34="","",IF(J34>=9,"NONE",IF(G34<=H34,IF(G34<=11-I34,"MONEY","DIFFICULTY"),IF(H34<=11-I34,"TIME","DIFFICULTY")))) | R34: =IF(A34="","",MAX(0,D34-MAX(0,$E$4-$E$8))) | S34: =IF(A34="","",IF(R34=0,0,IF($E$6<=0,"NO SAVINGS",ROUNDUP(R34/$E$6,0)))) | T34: =IFERROR(__xludf.DUMMYFUNCTION("IF(A34="""","""",RANK(F34,FILTER($F$11:$F$100,$A$11:$A$100<>""""),0))"),"") | U34: =IFERROR(__xludf.DUMMYFUNCTION("IF(A34="""","""",RANK( (F34*0.5+K34*0.5), FILTER($F$11:$F$100*0.5+$K$11:$K$100*0.5,$A$11:$A$100<>""""), 0))"),"") | V34: =IFERROR(__xludf.DUMMYFUNCTION("IF(A34="""","""",RANK( (F34*0.65+L34*0.35), FILTER($F$11:$F$100*0.65+$L$11:$L$100*0.35,$A$11:$A$100<>""""), 0))"),"")
G35: =IF(A35="","",IF(D35<=0,10,ROUND(MAX(1,MIN(10,(MAX(0,$E$4-$E$8)/D35)*10)),1))) | H35: =IF(A35="","",IF(E35<=0,10,ROUND(MAX(1,MIN(10,10-(E35/MAX(1,$E$7)*10))),1))) | I35: =IF(A35="","",ROUND(MIN(10,MAX(1, ((11-G35)*0.45)+ ((11-H35)*0.25)+ (MIN(10,E35/2)*0.2)+ (IF(C35="NOW",1,IF(C35="THIS YEAR",2,IF(C35="1 YEAR",3,IF(C35="1-3 YEARS",5,IF(C35="3 YEARS",7,6)))))*0.1) )),1)) | J35: =IF(A35="","",ROUND((G35*0.4)+(H35*0.3)+((11-I35)*0.3),1)) | K35: =IF(A35="","",ROUND( (MAX(1,MIN(10,IF(D35<=0,10,(MAX(0,$E$4-$E$8)+($E$6*12))/D35*10)))*0.4) + (MIN(10,H35+0.5)*0.3) + (MIN(10,12-I35)*0.3) ,1)) | L35: =IF(A35="","",ROUND( (MAX(1,MIN(10,IF(D35<=0,10,(MAX(0,$E$4-$E$8)+($E$6*36))/D35*10)))*0.4) + (MIN(10,H35+1.5)*0.3) + (MIN(10,14-I35)*0.3) ,1)) | M35: =IF(A35="","",ROUND((F35*0.45)+(J35*0.4)+((11-I35)*0.15),2)) | N35: =IFERROR(__xludf.DUMMYFUNCTION("IF(A35="""","""",RANK(M35,FILTER($M$11:$M$100,$A$11:$A$100<>""""),0))"),"") | O35: =IF(A35="","",IF(AND(F35>=8,J35<4),"DREAM",IF(J35>=8,"DO NOW",IF(J35>=6,"START PLANNING",IF(K35>=7,"BUILD TOWARDS","PARK"))))) | P35: =IF(A35="","",IF(J35>=9,"NONE",IF(G35<=H35,IF(G35<=11-I35,"MONEY","DIFFICULTY"),IF(H35<=11-I35,"TIME","DIFFICULTY")))) | R35: =IF(A35="","",MAX(0,D35-MAX(0,$E$4-$E$8))) | S35: =IF(A35="","",IF(R35=0,0,IF($E$6<=0,"NO SAVINGS",ROUNDUP(R35/$E$6,0)))) | T35: =IFERROR(__xludf.DUMMYFUNCTION("IF(A35="""","""",RANK(F35,FILTER($F$11:$F$100,$A$11:$A$100<>""""),0))"),"") | U35: =IFERROR(__xludf.DUMMYFUNCTION("IF(A35="""","""",RANK( (F35*0.5+K35*0.5), FILTER($F$11:$F$100*0.5+$K$11:$K$100*0.5,$A$11:$A$100<>""""), 0))"),"") | V35: =IFERROR(__xludf.DUMMYFUNCTION("IF(A35="""","""",RANK( (F35*0.65+L35*0.35), FILTER($F$11:$F$100*0.65+$L$11:$L$100*0.35,$A$11:$A$100<>""""), 0))"),"")
G36: =IF(A36="","",IF(D36<=0,10,ROUND(MAX(1,MIN(10,(MAX(0,$E$4-$E$8)/D36)*10)),1))) | H36: =IF(A36="","",IF(E36<=0,10,ROUND(MAX(1,MIN(10,10-(E36/MAX(1,$E$7)*10))),1))) | I36: =IF(A36="","",ROUND(MIN(10,MAX(1, ((11-G36)*0.45)+ ((11-H36)*0.25)+ (MIN(10,E36/2)*0.2)+ (IF(C36="NOW",1,IF(C36="THIS YEAR",2,IF(C36="1 YEAR",3,IF(C36="1-3 YEARS",5,IF(C36="3 YEARS",7,6)))))*0.1) )),1)) | J36: =IF(A36="","",ROUND((G36*0.4)+(H36*0.3)+((11-I36)*0.3),1)) | K36: =IF(A36="","",ROUND( (MAX(1,MIN(10,IF(D36<=0,10,(MAX(0,$E$4-$E$8)+($E$6*12))/D36*10)))*0.4) + (MIN(10,H36+0.5)*0.3) + (MIN(10,12-I36)*0.3) ,1)) | L36: =IF(A36="","",ROUND( (MAX(1,MIN(10,IF(D36<=0,10,(MAX(0,$E$4-$E$8)+($E$6*36))/D36*10)))*0.4) + (MIN(10,H36+1.5)*0.3) + (MIN(10,14-I36)*0.3) ,1)) | M36: =IF(A36="","",ROUND((F36*0.45)+(J36*0.4)+((11-I36)*0.15),2)) | N36: =IFERROR(__xludf.DUMMYFUNCTION("IF(A36="""","""",RANK(M36,FILTER($M$11:$M$100,$A$11:$A$100<>""""),0))"),"") | O36: =IF(A36="","",IF(AND(F36>=8,J36<4),"DREAM",IF(J36>=8,"DO NOW",IF(J36>=6,"START PLANNING",IF(K36>=7,"BUILD TOWARDS","PARK"))))) | P36: =IF(A36="","",IF(J36>=9,"NONE",IF(G36<=H36,IF(G36<=11-I36,"MONEY","DIFFICULTY"),IF(H36<=11-I36,"TIME","DIFFICULTY")))) | R36: =IF(A36="","",MAX(0,D36-MAX(0,$E$4-$E$8))) | S36: =IF(A36="","",IF(R36=0,0,IF($E$6<=0,"NO SAVINGS",ROUNDUP(R36/$E$6,0)))) | T36: =IFERROR(__xludf.DUMMYFUNCTION("IF(A36="""","""",RANK(F36,FILTER($F$11:$F$100,$A$11:$A$100<>""""),0))"),"") | U36: =IFERROR(__xludf.DUMMYFUNCTION("IF(A36="""","""",RANK( (F36*0.5+K36*0.5), FILTER($F$11:$F$100*0.5+$K$11:$K$100*0.5,$A$11:$A$100<>""""), 0))"),"") | V36: =IFERROR(__xludf.DUMMYFUNCTION("IF(A36="""","""",RANK( (F36*0.65+L36*0.35), FILTER($F$11:$F$100*0.65+$L$11:$L$100*0.35,$A$11:$A$100<>""""), 0))"),"")
G37: =IF(A37="","",IF(D37<=0,10,ROUND(MAX(1,MIN(10,(MAX(0,$E$4-$E$8)/D37)*10)),1))) | H37: =IF(A37="","",IF(E37<=0,10,ROUND(MAX(1,MIN(10,10-(E37/MAX(1,$E$7)*10))),1))) | I37: =IF(A37="","",ROUND(MIN(10,MAX(1, ((11-G37)*0.45)+ ((11-H37)*0.25)+ (MIN(10,E37/2)*0.2)+ (IF(C37="NOW",1,IF(C37="THIS YEAR",2,IF(C37="1 YEAR",3,IF(C37="1-3 YEARS",5,IF(C37="3 YEARS",7,6)))))*0.1) )),1)) | J37: =IF(A37="","",ROUND((G37*0.4)+(H37*0.3)+((11-I37)*0.3),1)) | K37: =IF(A37="","",ROUND( (MAX(1,MIN(10,IF(D37<=0,10,(MAX(0,$E$4-$E$8)+($E$6*12))/D37*10)))*0.4) + (MIN(10,H37+0.5)*0.3) + (MIN(10,12-I37)*0.3) ,1)) | L37: =IF(A37="","",ROUND( (MAX(1,MIN(10,IF(D37<=0,10,(MAX(0,$E$4-$E$8)+($E$6*36))/D37*10)))*0.4) + (MIN(10,H37+1.5)*0.3) + (MIN(10,14-I37)*0.3) ,1)) | M37: =IF(A37="","",ROUND((F37*0.45)+(J37*0.4)+((11-I37)*0.15),2)) | N37: =IFERROR(__xludf.DUMMYFUNCTION("IF(A37="""","""",RANK(M37,FILTER($M$11:$M$100,$A$11:$A$100<>""""),0))"),"") | O37: =IF(A37="","",IF(AND(F37>=8,J37<4),"DREAM",IF(J37>=8,"DO NOW",IF(J37>=6,"START PLANNING",IF(K37>=7,"BUILD TOWARDS","PARK"))))) | P37: =IF(A37="","",IF(J37>=9,"NONE",IF(G37<=H37,IF(G37<=11-I37,"MONEY","DIFFICULTY"),IF(H37<=11-I37,"TIME","DIFFICULTY")))) | R37: =IF(A37="","",MAX(0,D37-MAX(0,$E$4-$E$8))) | S37: =IF(A37="","",IF(R37=0,0,IF($E$6<=0,"NO SAVINGS",ROUNDUP(R37/$E$6,0)))) | T37: =IFERROR(__xludf.DUMMYFUNCTION("IF(A37="""","""",RANK(F37,FILTER($F$11:$F$100,$A$11:$A$100<>""""),0))"),"") | U37: =IFERROR(__xludf.DUMMYFUNCTION("IF(A37="""","""",RANK( (F37*0.5+K37*0.5), FILTER($F$11:$F$100*0.5+$K$11:$K$100*0.5,$A$11:$A$100<>""""), 0))"),"") | V37: =IFERROR(__xludf.DUMMYFUNCTION("IF(A37="""","""",RANK( (F37*0.65+L37*0.35), FILTER($F$11:$F$100*0.65+$L$11:$L$100*0.35,$A$11:$A$100<>""""), 0))"),"")
G38: =IF(A38="","",IF(D38<=0,10,ROUND(MAX(1,MIN(10,(MAX(0,$E$4-$E$8)/D38)*10)),1))) | H38: =IF(A38="","",IF(E38<=0,10,ROUND(MAX(1,MIN(10,10-(E38/MAX(1,$E$7)*10))),1))) | I38: =IF(A38="","",ROUND(MIN(10,MAX(1, ((11-G38)*0.45)+ ((11-H38)*0.25)+ (MIN(10,E38/2)*0.2)+ (IF(C38="NOW",1,IF(C38="THIS YEAR",2,IF(C38="1 YEAR",3,IF(C38="1-3 YEARS",5,IF(C38="3 YEARS",7,6)))))*0.1) )),1)) | J38: =IF(A38="","",ROUND((G38*0.4)+(H38*0.3)+((11-I38)*0.3),1)) | K38: =IF(A38="","",ROUND( (MAX(1,MIN(10,IF(D38<=0,10,(MAX(0,$E$4-$E$8)+($E$6*12))/D38*10)))*0.4) + (MIN(10,H38+0.5)*0.3) + (MIN(10,12-I38)*0.3) ,1)) | L38: =IF(A38="","",ROUND( (MAX(1,MIN(10,IF(D38<=0,10,(MAX(0,$E$4-$E$8)+($E$6*36))/D38*10)))*0.4) + (MIN(10,H38+1.5)*0.3) + (MIN(10,14-I38)*0.3) ,1)) | M38: =IF(A38="","",ROUND((F38*0.45)+(J38*0.4)+((11-I38)*0.15),2)) | N38: =IFERROR(__xludf.DUMMYFUNCTION("IF(A38="""","""",RANK(M38,FILTER($M$11:$M$100,$A$11:$A$100<>""""),0))"),"") | O38: =IF(A38="","",IF(AND(F38>=8,J38<4),"DREAM",IF(J38>=8,"DO NOW",IF(J38>=6,"START PLANNING",IF(K38>=7,"BUILD TOWARDS","PARK"))))) | P38: =IF(A38="","",IF(J38>=9,"NONE",IF(G38<=H38,IF(G38<=11-I38,"MONEY","DIFFICULTY"),IF(H38<=11-I38,"TIME","DIFFICULTY")))) | R38: =IF(A38="","",MAX(0,D38-MAX(0,$E$4-$E$8))) | S38: =IF(A38="","",IF(R38=0,0,IF($E$6<=0,"NO SAVINGS",ROUNDUP(R38/$E$6,0)))) | T38: =IFERROR(__xludf.DUMMYFUNCTION("IF(A38="""","""",RANK(F38,FILTER($F$11:$F$100,$A$11:$A$100<>""""),0))"),"") | U38: =IFERROR(__xludf.DUMMYFUNCTION("IF(A38="""","""",RANK( (F38*0.5+K38*0.5), FILTER($F$11:$F$100*0.5+$K$11:$K$100*0.5,$A$11:$A$100<>""""), 0))"),"") | V38: =IFERROR(__xludf.DUMMYFUNCTION("IF(A38="""","""",RANK( (F38*0.65+L38*0.35), FILTER($F$11:$F$100*0.65+$L$11:$L$100*0.35,$A$11:$A$100<>""""), 0))"),"")
G39: =IF(A39="","",IF(D39<=0,10,ROUND(MAX(1,MIN(10,(MAX(0,$E$4-$E$8)/D39)*10)),1))) | H39: =IF(A39="","",IF(E39<=0,10,ROUND(MAX(1,MIN(10,10-(E39/MAX(1,$E$7)*10))),1))) | I39: =IF(A39="","",ROUND(MIN(10,MAX(1, ((11-G39)*0.45)+ ((11-H39)*0.25)+ (MIN(10,E39/2)*0.2)+ (IF(C39="NOW",1,IF(C39="THIS YEAR",2,IF(C39="1 YEAR",3,IF(C39="1-3 YEARS",5,IF(C39="3 YEARS",7,6)))))*0.1) )),1)) | J39: =IF(A39="","",ROUND((G39*0.4)+(H39*0.3)+((11-I39)*0.3),1)) | K39: =IF(A39="","",ROUND( (MAX(1,MIN(10,IF(D39<=0,10,(MAX(0,$E$4-$E$8)+($E$6*12))/D39*10)))*0.4) + (MIN(10,H39+0.5)*0.3) + (MIN(10,12-I39)*0.3) ,1)) | L39: =IF(A39="","",ROUND( (MAX(1,MIN(10,IF(D39<=0,10,(MAX(0,$E$4-$E$8)+($E$6*36))/D39*10)))*0.4) + (MIN(10,H39+1.5)*0.3) + (MIN(10,14-I39)*0.3) ,1)) | M39: =IF(A39="","",ROUND((F39*0.45)+(J39*0.4)+((11-I39)*0.15),2)) | N39: =IFERROR(__xludf.DUMMYFUNCTION("IF(A39="""","""",RANK(M39,FILTER($M$11:$M$100,$A$11:$A$100<>""""),0))"),"") | O39: =IF(A39="","",IF(AND(F39>=8,J39<4),"DREAM",IF(J39>=8,"DO NOW",IF(J39>=6,"START PLANNING",IF(K39>=7,"BUILD TOWARDS","PARK"))))) | P39: =IF(A39="","",IF(J39>=9,"NONE",IF(G39<=H39,IF(G39<=11-I39,"MONEY","DIFFICULTY"),IF(H39<=11-I39,"TIME","DIFFICULTY")))) | R39: =IF(A39="","",MAX(0,D39-MAX(0,$E$4-$E$8))) | S39: =IF(A39="","",IF(R39=0,0,IF($E$6<=0,"NO SAVINGS",ROUNDUP(R39/$E$6,0)))) | T39: =IFERROR(__xludf.DUMMYFUNCTION("IF(A39="""","""",RANK(F39,FILTER($F$11:$F$100,$A$11:$A$100<>""""),0))"),"") | U39: =IFERROR(__xludf.DUMMYFUNCTION("IF(A39="""","""",RANK( (F39*0.5+K39*0.5), FILTER($F$11:$F$100*0.5+$K$11:$K$100*0.5,$A$11:$A$100<>""""), 0))"),"") | V39: =IFERROR(__xludf.DUMMYFUNCTION("IF(A39="""","""",RANK( (F39*0.65+L39*0.35), FILTER($F$11:$F$100*0.65+$L$11:$L$100*0.35,$A$11:$A$100<>""""), 0))"),"")
G40: =IF(A40="","",IF(D40<=0,10,ROUND(MAX(1,MIN(10,(MAX(0,$E$4-$E$8)/D40)*10)),1))) | H40: =IF(A40="","",IF(E40<=0,10,ROUND(MAX(1,MIN(10,10-(E40/MAX(1,$E$7)*10))),1))) | I40: =IF(A40="","",ROUND(MIN(10,MAX(1, ((11-G40)*0.45)+ ((11-H40)*0.25)+ (MIN(10,E40/2)*0.2)+ (IF(C40="NOW",1,IF(C40="THIS YEAR",2,IF(C40="1 YEAR",3,IF(C40="1-3 YEARS",5,IF(C40="3 YEARS",7,6)))))*0.1) )),1)) | J40: =IF(A40="","",ROUND((G40*0.4)+(H40*0.3)+((11-I40)*0.3),1)) | K40: =IF(A40="","",ROUND( (MAX(1,MIN(10,IF(D40<=0,10,(MAX(0,$E$4-$E$8)+($E$6*12))/D40*10)))*0.4) + (MIN(10,H40+0.5)*0.3) + (MIN(10,12-I40)*0.3) ,1)) | L40: =IF(A40="","",ROUND( (MAX(1,MIN(10,IF(D40<=0,10,(MAX(0,$E$4-$E$8)+($E$6*36))/D40*10)))*0.4) + (MIN(10,H40+1.5)*0.3) + (MIN(10,14-I40)*0.3) ,1)) | M40: =IF(A40="","",ROUND((F40*0.45)+(J40*0.4)+((11-I40)*0.15),2)) | N40: =IFERROR(__xludf.DUMMYFUNCTION("IF(A40="""","""",RANK(M40,FILTER($M$11:$M$100,$A$11:$A$100<>""""),0))"),"") | O40: =IF(A40="","",IF(AND(F40>=8,J40<4),"DREAM",IF(J40>=8,"DO NOW",IF(J40>=6,"START PLANNING",IF(K40>=7,"BUILD TOWARDS","PARK"))))) | P40: =IF(A40="","",IF(J40>=9,"NONE",IF(G40<=H40,IF(G40<=11-I40,"MONEY","DIFFICULTY"),IF(H40<=11-I40,"TIME","DIFFICULTY")))) | R40: =IF(A40="","",MAX(0,D40-MAX(0,$E$4-$E$8))) | S40: =IF(A40="","",IF(R40=0,0,IF($E$6<=0,"NO SAVINGS",ROUNDUP(R40/$E$6,0)))) | T40: =IFERROR(__xludf.DUMMYFUNCTION("IF(A40="""","""",RANK(F40,FILTER($F$11:$F$100,$A$11:$A$100<>""""),0))"),"") | U40: =IFERROR(__xludf.DUMMYFUNCTION("IF(A40="""","""",RANK( (F40*0.5+K40*0.5), FILTER($F$11:$F$100*0.5+$K$11:$K$100*0.5,$A$11:$A$100<>""""), 0))"),"") | V40: =IFERROR(__xludf.DUMMYFUNCTION("IF(A40="""","""",RANK( (F40*0.65+L40*0.35), FILTER($F$11:$F$100*0.65+$L$11:$L$100*0.35,$A$11:$A$100<>""""), 0))"),"")
G41: =IF(A41="","",IF(D41<=0,10,ROUND(MAX(1,MIN(10,(MAX(0,$E$4-$E$8)/D41)*10)),1))) | H41: =IF(A41="","",IF(E41<=0,10,ROUND(MAX(1,MIN(10,10-(E41/MAX(1,$E$7)*10))),1))) | I41: =IF(A41="","",ROUND(MIN(10,MAX(1, ((11-G41)*0.45)+ ((11-H41)*0.25)+ (MIN(10,E41/2)*0.2)+ (IF(C41="NOW",1,IF(C41="THIS YEAR",2,IF(C41="1 YEAR",3,IF(C41="1-3 YEARS",5,IF(C41="3 YEARS",7,6)))))*0.1) )),1)) | J41: =IF(A41="","",ROUND((G41*0.4)+(H41*0.3)+((11-I41)*0.3),1)) | K41: =IF(A41="","",ROUND( (MAX(1,MIN(10,IF(D41<=0,10,(MAX(0,$E$4-$E$8)+($E$6*12))/D41*10)))*0.4) + (MIN(10,H41+0.5)*0.3) + (MIN(10,12-I41)*0.3) ,1)) | L41: =IF(A41="","",ROUND( (MAX(1,MIN(10,IF(D41<=0,10,(MAX(0,$E$4-$E$8)+($E$6*36))/D41*10)))*0.4) + (MIN(10,H41+1.5)*0.3) + (MIN(10,14-I41)*0.3) ,1)) | M41: =IF(A41="","",ROUND((F41*0.45)+(J41*0.4)+((11-I41)*0.15),2)) | N41: =IFERROR(__xludf.DUMMYFUNCTION("IF(A41="""","""",RANK(M41,FILTER($M$11:$M$100,$A$11:$A$100<>""""),0))"),"") | O41: =IF(A41="","",IF(AND(F41>=8,J41<4),"DREAM",IF(J41>=8,"DO NOW",IF(J41>=6,"START PLANNING",IF(K41>=7,"BUILD TOWARDS","PARK"))))) | P41: =IF(A41="","",IF(J41>=9,"NONE",IF(G41<=H41,IF(G41<=11-I41,"MONEY","DIFFICULTY"),IF(H41<=11-I41,"TIME","DIFFICULTY")))) | R41: =IF(A41="","",MAX(0,D41-MAX(0,$E$4-$E$8))) | S41: =IF(A41="","",IF(R41=0,0,IF($E$6<=0,"NO SAVINGS",ROUNDUP(R41/$E$6,0)))) | T41: =IFERROR(__xludf.DUMMYFUNCTION("IF(A41="""","""",RANK(F41,FILTER($F$11:$F$100,$A$11:$A$100<>""""),0))"),"") | U41: =IFERROR(__xludf.DUMMYFUNCTION("IF(A41="""","""",RANK( (F41*0.5+K41*0.5), FILTER($F$11:$F$100*0.5+$K$11:$K$100*0.5,$A$11:$A$100<>""""), 0))"),"") | V41: =IFERROR(__xludf.DUMMYFUNCTION("IF(A41="""","""",RANK( (F41*0.65+L41*0.35), FILTER($F$11:$F$100*0.65+$L$11:$L$100*0.35,$A$11:$A$100<>""""), 0))"),"")
G42: =IF(A42="","",IF(D42<=0,10,ROUND(MAX(1,MIN(10,(MAX(0,$E$4-$E$8)/D42)*10)),1))) | H42: =IF(A42="","",IF(E42<=0,10,ROUND(MAX(1,MIN(10,10-(E42/MAX(1,$E$7)*10))),1))) | I42: =IF(A42="","",ROUND(MIN(10,MAX(1, ((11-G42)*0.45)+ ((11-H42)*0.25)+ (MIN(10,E42/2)*0.2)+ (IF(C42="NOW",1,IF(C42="THIS YEAR",2,IF(C42="1 YEAR",3,IF(C42="1-3 YEARS",5,IF(C42="3 YEARS",7,6)))))*0.1) )),1)) | J42: =IF(A42="","",ROUND((G42*0.4)+(H42*0.3)+((11-I42)*0.3),1)) | K42: =IF(A42="","",ROUND( (MAX(1,MIN(10,IF(D42<=0,10,(MAX(0,$E$4-$E$8)+($E$6*12))/D42*10)))*0.4) + (MIN(10,H42+0.5)*0.3) + (MIN(10,12-I42)*0.3) ,1)) | L42: =IF(A42="","",ROUND( (MAX(1,MIN(10,IF(D42<=0,10,(MAX(0,$E$4-$E$8)+($E$6*36))/D42*10)))*0.4) + (MIN(10,H42+1.5)*0.3) + (MIN(10,14-I42)*0.3) ,1)) | M42: =IF(A42="","",ROUND((F42*0.45)+(J42*0.4)+((11-I42)*0.15),2)) | N42: =IFERROR(__xludf.DUMMYFUNCTION("IF(A42="""","""",RANK(M42,FILTER($M$11:$M$100,$A$11:$A$100<>""""),0))"),"") | O42: =IF(A42="","",IF(AND(F42>=8,J42<4),"DREAM",IF(J42>=8,"DO NOW",IF(J42>=6,"START PLANNING",IF(K42>=7,"BUILD TOWARDS","PARK"))))) | P42: =IF(A42="","",IF(J42>=9,"NONE",IF(G42<=H42,IF(G42<=11-I42,"MONEY","DIFFICULTY"),IF(H42<=11-I42,"TIME","DIFFICULTY")))) | R42: =IF(A42="","",MAX(0,D42-MAX(0,$E$4-$E$8))) | S42: =IF(A42="","",IF(R42=0,0,IF($E$6<=0,"NO SAVINGS",ROUNDUP(R42/$E$6,0)))) | T42: =IFERROR(__xludf.DUMMYFUNCTION("IF(A42="""","""",RANK(F42,FILTER($F$11:$F$100,$A$11:$A$100<>""""),0))"),"") | U42: =IFERROR(__xludf.DUMMYFUNCTION("IF(A42="""","""",RANK( (F42*0.5+K42*0.5), FILTER($F$11:$F$100*0.5+$K$11:$K$100*0.5,$A$11:$A$100<>""""), 0))"),"") | V42: =IFERROR(__xludf.DUMMYFUNCTION("IF(A42="""","""",RANK( (F42*0.65+L42*0.35), FILTER($F$11:$F$100*0.65+$L$11:$L$100*0.35,$A$11:$A$100<>""""), 0))"),"")
G43: =IF(A43="","",IF(D43<=0,10,ROUND(MAX(1,MIN(10,(MAX(0,$E$4-$E$8)/D43)*10)),1))) | H43: =IF(A43="","",IF(E43<=0,10,ROUND(MAX(1,MIN(10,10-(E43/MAX(1,$E$7)*10))),1))) | I43: =IF(A43="","",ROUND(MIN(10,MAX(1, ((11-G43)*0.45)+ ((11-H43)*0.25)+ (MIN(10,E43/2)*0.2)+ (IF(C43="NOW",1,IF(C43="THIS YEAR",2,IF(C43="1 YEAR",3,IF(C43="1-3 YEARS",5,IF(C43="3 YEARS",7,6)))))*0.1) )),1)) | J43: =IF(A43="","",ROUND((G43*0.4)+(H43*0.3)+((11-I43)*0.3),1)) | K43: =IF(A43="","",ROUND( (MAX(1,MIN(10,IF(D43<=0,10,(MAX(0,$E$4-$E$8)+($E$6*12))/D43*10)))*0.4) + (MIN(10,H43+0.5)*0.3) + (MIN(10,12-I43)*0.3) ,1)) | L43: =IF(A43="","",ROUND( (MAX(1,MIN(10,IF(D43<=0,10,(MAX(0,$E$4-$E$8)+($E$6*36))/D43*10)))*0.4) + (MIN(10,H43+1.5)*0.3) + (MIN(10,14-I43)*0.3) ,1)) | M43: =IF(A43="","",ROUND((F43*0.45)+(J43*0.4)+((11-I43)*0.15),2)) | N43: =IFERROR(__xludf.DUMMYFUNCTION("IF(A43="""","""",RANK(M43,FILTER($M$11:$M$100,$A$11:$A$100<>""""),0))"),"") | O43: =IF(A43="","",IF(AND(F43>=8,J43<4),"DREAM",IF(J43>=8,"DO NOW",IF(J43>=6,"START PLANNING",IF(K43>=7,"BUILD TOWARDS","PARK"))))) | P43: =IF(A43="","",IF(J43>=9,"NONE",IF(G43<=H43,IF(G43<=11-I43,"MONEY","DIFFICULTY"),IF(H43<=11-I43,"TIME","DIFFICULTY")))) | R43: =IF(A43="","",MAX(0,D43-MAX(0,$E$4-$E$8))) | S43: =IF(A43="","",IF(R43=0,0,IF($E$6<=0,"NO SAVINGS",ROUNDUP(R43/$E$6,0)))) | T43: =IFERROR(__xludf.DUMMYFUNCTION("IF(A43="""","""",RANK(F43,FILTER($F$11:$F$100,$A$11:$A$100<>""""),0))"),"") | U43: =IFERROR(__xludf.DUMMYFUNCTION("IF(A43="""","""",RANK( (F43*0.5+K43*0.5), FILTER($F$11:$F$100*0.5+$K$11:$K$100*0.5,$A$11:$A$100<>""""), 0))"),"") | V43: =IFERROR(__xludf.DUMMYFUNCTION("IF(A43="""","""",RANK( (F43*0.65+L43*0.35), FILTER($F$11:$F$100*0.65+$L$11:$L$100*0.35,$A$11:$A$100<>""""), 0))"),"")
G44: =IF(A44="","",IF(D44<=0,10,ROUND(MAX(1,MIN(10,(MAX(0,$E$4-$E$8)/D44)*10)),1))) | H44: =IF(A44="","",IF(E44<=0,10,ROUND(MAX(1,MIN(10,10-(E44/MAX(1,$E$7)*10))),1))) | I44: =IF(A44="","",ROUND(MIN(10,MAX(1, ((11-G44)*0.45)+ ((11-H44)*0.25)+ (MIN(10,E44/2)*0.2)+ (IF(C44="NOW",1,IF(C44="THIS YEAR",2,IF(C44="1 YEAR",3,IF(C44="1-3 YEARS",5,IF(C44="3 YEARS",7,6)))))*0.1) )),1)) | J44: =IF(A44="","",ROUND((G44*0.4)+(H44*0.3)+((11-I44)*0.3),1)) | K44: =IF(A44="","",ROUND( (MAX(1,MIN(10,IF(D44<=0,10,(MAX(0,$E$4-$E$8)+($E$6*12))/D44*10)))*0.4) + (MIN(10,H44+0.5)*0.3) + (MIN(10,12-I44)*0.3) ,1)) | L44: =IF(A44="","",ROUND( (MAX(1,MIN(10,IF(D44<=0,10,(MAX(0,$E$4-$E$8)+($E$6*36))/D44*10)))*0.4) + (MIN(10,H44+1.5)*0.3) + (MIN(10,14-I44)*0.3) ,1)) | M44: =IF(A44="","",ROUND((F44*0.45)+(J44*0.4)+((11-I44)*0.15),2)) | N44: =IFERROR(__xludf.DUMMYFUNCTION("IF(A44="""","""",RANK(M44,FILTER($M$11:$M$100,$A$11:$A$100<>""""),0))"),"") | O44: =IF(A44="","",IF(AND(F44>=8,J44<4),"DREAM",IF(J44>=8,"DO NOW",IF(J44>=6,"START PLANNING",IF(K44>=7,"BUILD TOWARDS","PARK"))))) | P44: =IF(A44="","",IF(J44>=9,"NONE",IF(G44<=H44,IF(G44<=11-I44,"MONEY","DIFFICULTY"),IF(H44<=11-I44,"TIME","DIFFICULTY")))) | R44: =IF(A44="","",MAX(0,D44-MAX(0,$E$4-$E$8))) | S44: =IF(A44="","",IF(R44=0,0,IF($E$6<=0,"NO SAVINGS",ROUNDUP(R44/$E$6,0)))) | T44: =IFERROR(__xludf.DUMMYFUNCTION("IF(A44="""","""",RANK(F44,FILTER($F$11:$F$100,$A$11:$A$100<>""""),0))"),"") | U44: =IFERROR(__xludf.DUMMYFUNCTION("IF(A44="""","""",RANK( (F44*0.5+K44*0.5), FILTER($F$11:$F$100*0.5+$K$11:$K$100*0.5,$A$11:$A$100<>""""), 0))"),"") | V44: =IFERROR(__xludf.DUMMYFUNCTION("IF(A44="""","""",RANK( (F44*0.65+L44*0.35), FILTER($F$11:$F$100*0.65+$L$11:$L$100*0.35,$A$11:$A$100<>""""), 0))"),"")
G45: =IF(A45="","",IF(D45<=0,10,ROUND(MAX(1,MIN(10,(MAX(0,$E$4-$E$8)/D45)*10)),1))) | H45: =IF(A45="","",IF(E45<=0,10,ROUND(MAX(1,MIN(10,10-(E45/MAX(1,$E$7)*10))),1))) | I45: =IF(A45="","",ROUND(MIN(10,MAX(1, ((11-G45)*0.45)+ ((11-H45)*0.25)+ (MIN(10,E45/2)*0.2)+ (IF(C45="NOW",1,IF(C45="THIS YEAR",2,IF(C45="1 YEAR",3,IF(C45="1-3 YEARS",5,IF(C45="3 YEARS",7,6)))))*0.1) )),1)) | J45: =IF(A45="","",ROUND((G45*0.4)+(H45*0.3)+((11-I45)*0.3),1)) | K45: =IF(A45="","",ROUND( (MAX(1,MIN(10,IF(D45<=0,10,(MAX(0,$E$4-$E$8)+($E$6*12))/D45*10)))*0.4) + (MIN(10,H45+0.5)*0.3) + (MIN(10,12-I45)*0.3) ,1)) | L45: =IF(A45="","",ROUND( (MAX(1,MIN(10,IF(D45<=0,10,(MAX(0,$E$4-$E$8)+($E$6*36))/D45*10)))*0.4) + (MIN(10,H45+1.5)*0.3) + (MIN(10,14-I45)*0.3) ,1)) | M45: =IF(A45="","",ROUND((F45*0.45)+(J45*0.4)+((11-I45)*0.15),2)) | N45: =IFERROR(__xludf.DUMMYFUNCTION("IF(A45="""","""",RANK(M45,FILTER($M$11:$M$100,$A$11:$A$100<>""""),0))"),"") | O45: =IF(A45="","",IF(AND(F45>=8,J45<4),"DREAM",IF(J45>=8,"DO NOW",IF(J45>=6,"START PLANNING",IF(K45>=7,"BUILD TOWARDS","PARK"))))) | P45: =IF(A45="","",IF(J45>=9,"NONE",IF(G45<=H45,IF(G45<=11-I45,"MONEY","DIFFICULTY"),IF(H45<=11-I45,"TIME","DIFFICULTY")))) | R45: =IF(A45="","",MAX(0,D45-MAX(0,$E$4-$E$8))) | S45: =IF(A45="","",IF(R45=0,0,IF($E$6<=0,"NO SAVINGS",ROUNDUP(R45/$E$6,0)))) | T45: =IFERROR(__xludf.DUMMYFUNCTION("IF(A45="""","""",RANK(F45,FILTER($F$11:$F$100,$A$11:$A$100<>""""),0))"),"") | U45: =IFERROR(__xludf.DUMMYFUNCTION("IF(A45="""","""",RANK( (F45*0.5+K45*0.5), FILTER($F$11:$F$100*0.5+$K$11:$K$100*0.5,$A$11:$A$100<>""""), 0))"),"") | V45: =IFERROR(__xludf.DUMMYFUNCTION("IF(A45="""","""",RANK( (F45*0.65+L45*0.35), FILTER($F$11:$F$100*0.65+$L$11:$L$100*0.35,$A$11:$A$100<>""""), 0))"),"")
G46: =IF(A46="","",IF(D46<=0,10,ROUND(MAX(1,MIN(10,(MAX(0,$E$4-$E$8)/D46)*10)),1))) | H46: =IF(A46="","",IF(E46<=0,10,ROUND(MAX(1,MIN(10,10-(E46/MAX(1,$E$7)*10))),1))) | I46: =IF(A46="","",ROUND(MIN(10,MAX(1, ((11-G46)*0.45)+ ((11-H46)*0.25)+ (MIN(10,E46/2)*0.2)+ (IF(C46="NOW",1,IF(C46="THIS YEAR",2,IF(C46="1 YEAR",3,IF(C46="1-3 YEARS",5,IF(C46="3 YEARS",7,6)))))*0.1) )),1)) | J46: =IF(A46="","",ROUND((G46*0.4)+(H46*0.3)+((11-I46)*0.3),1)) | K46: =IF(A46="","",ROUND( (MAX(1,MIN(10,IF(D46<=0,10,(MAX(0,$E$4-$E$8)+($E$6*12))/D46*10)))*0.4) + (MIN(10,H46+0.5)*0.3) + (MIN(10,12-I46)*0.3) ,1)) | L46: =IF(A46="","",ROUND( (MAX(1,MIN(10,IF(D46<=0,10,(MAX(0,$E$4-$E$8)+($E$6*36))/D46*10)))*0.4) + (MIN(10,H46+1.5)*0.3) + (MIN(10,14-I46)*0.3) ,1)) | M46: =IF(A46="","",ROUND((F46*0.45)+(J46*0.4)+((11-I46)*0.15),2)) | N46: =IFERROR(__xludf.DUMMYFUNCTION("IF(A46="""","""",RANK(M46,FILTER($M$11:$M$100,$A$11:$A$100<>""""),0))"),"") | O46: =IF(A46="","",IF(AND(F46>=8,J46<4),"DREAM",IF(J46>=8,"DO NOW",IF(J46>=6,"START PLANNING",IF(K46>=7,"BUILD TOWARDS","PARK"))))) | P46: =IF(A46="","",IF(J46>=9,"NONE",IF(G46<=H46,IF(G46<=11-I46,"MONEY","DIFFICULTY"),IF(H46<=11-I46,"TIME","DIFFICULTY")))) | R46: =IF(A46="","",MAX(0,D46-MAX(0,$E$4-$E$8))) | S46: =IF(A46="","",IF(R46=0,0,IF($E$6<=0,"NO SAVINGS",ROUNDUP(R46/$E$6,0)))) | T46: =IFERROR(__xludf.DUMMYFUNCTION("IF(A46="""","""",RANK(F46,FILTER($F$11:$F$100,$A$11:$A$100<>""""),0))"),"") | U46: =IFERROR(__xludf.DUMMYFUNCTION("IF(A46="""","""",RANK( (F46*0.5+K46*0.5), FILTER($F$11:$F$100*0.5+$K$11:$K$100*0.5,$A$11:$A$100<>""""), 0))"),"") | V46: =IFERROR(__xludf.DUMMYFUNCTION("IF(A46="""","""",RANK( (F46*0.65+L46*0.35), FILTER($F$11:$F$100*0.65+$L$11:$L$100*0.35,$A$11:$A$100<>""""), 0))"),"")
G47: =IF(A47="","",IF(D47<=0,10,ROUND(MAX(1,MIN(10,(MAX(0,$E$4-$E$8)/D47)*10)),1))) | H47: =IF(A47="","",IF(E47<=0,10,ROUND(MAX(1,MIN(10,10-(E47/MAX(1,$E$7)*10))),1))) | I47: =IF(A47="","",ROUND(MIN(10,MAX(1, ((11-G47)*0.45)+ ((11-H47)*0.25)+ (MIN(10,E47/2)*0.2)+ (IF(C47="NOW",1,IF(C47="THIS YEAR",2,IF(C47="1 YEAR",3,IF(C47="1-3 YEARS",5,IF(C47="3 YEARS",7,6)))))*0.1) )),1)) | J47: =IF(A47="","",ROUND((G47*0.4)+(H47*0.3)+((11-I47)*0.3),1)) | K47: =IF(A47="","",ROUND( (MAX(1,MIN(10,IF(D47<=0,10,(MAX(0,$E$4-$E$8)+($E$6*12))/D47*10)))*0.4) + (MIN(10,H47+0.5)*0.3) + (MIN(10,12-I47)*0.3) ,1)) | L47: =IF(A47="","",ROUND( (MAX(1,MIN(10,IF(D47<=0,10,(MAX(0,$E$4-$E$8)+($E$6*36))/D47*10)))*0.4) + (MIN(10,H47+1.5)*0.3) + (MIN(10,14-I47)*0.3) ,1)) | M47: =IF(A47="","",ROUND((F47*0.45)+(J47*0.4)+((11-I47)*0.15),2)) | N47: =IFERROR(__xludf.DUMMYFUNCTION("IF(A47="""","""",RANK(M47,FILTER($M$11:$M$100,$A$11:$A$100<>""""),0))"),"") | O47: =IF(A47="","",IF(AND(F47>=8,J47<4),"DREAM",IF(J47>=8,"DO NOW",IF(J47>=6,"START PLANNING",IF(K47>=7,"BUILD TOWARDS","PARK"))))) | P47: =IF(A47="","",IF(J47>=9,"NONE",IF(G47<=H47,IF(G47<=11-I47,"MONEY","DIFFICULTY"),IF(H47<=11-I47,"TIME","DIFFICULTY")))) | R47: =IF(A47="","",MAX(0,D47-MAX(0,$E$4-$E$8))) | S47: =IF(A47="","",IF(R47=0,0,IF($E$6<=0,"NO SAVINGS",ROUNDUP(R47/$E$6,0)))) | T47: =IFERROR(__xludf.DUMMYFUNCTION("IF(A47="""","""",RANK(F47,FILTER($F$11:$F$100,$A$11:$A$100<>""""),0))"),"") | U47: =IFERROR(__xludf.DUMMYFUNCTION("IF(A47="""","""",RANK( (F47*0.5+K47*0.5), FILTER($F$11:$F$100*0.5+$K$11:$K$100*0.5,$A$11:$A$100<>""""), 0))"),"") | V47: =IFERROR(__xludf.DUMMYFUNCTION("IF(A47="""","""",RANK( (F47*0.65+L47*0.35), FILTER($F$11:$F$100*0.65+$L$11:$L$100*0.35,$A$11:$A$100<>""""), 0))"),"")
G48: =IF(A48="","",IF(D48<=0,10,ROUND(MAX(1,MIN(10,(MAX(0,$E$4-$E$8)/D48)*10)),1))) | H48: =IF(A48="","",IF(E48<=0,10,ROUND(MAX(1,MIN(10,10-(E48/MAX(1,$E$7)*10))),1))) | I48: =IF(A48="","",ROUND(MIN(10,MAX(1, ((11-G48)*0.45)+ ((11-H48)*0.25)+ (MIN(10,E48/2)*0.2)+ (IF(C48="NOW",1,IF(C48="THIS YEAR",2,IF(C48="1 YEAR",3,IF(C48="1-3 YEARS",5,IF(C48="3 YEARS",7,6)))))*0.1) )),1)) | J48: =IF(A48="","",ROUND((G48*0.4)+(H48*0.3)+((11-I48)*0.3),1)) | K48: =IF(A48="","",ROUND( (MAX(1,MIN(10,IF(D48<=0,10,(MAX(0,$E$4-$E$8)+($E$6*12))/D48*10)))*0.4) + (MIN(10,H48+0.5)*0.3) + (MIN(10,12-I48)*0.3) ,1)) | L48: =IF(A48="","",ROUND( (MAX(1,MIN(10,IF(D48<=0,10,(MAX(0,$E$4-$E$8)+($E$6*36))/D48*10)))*0.4) + (MIN(10,H48+1.5)*0.3) + (MIN(10,14-I48)*0.3) ,1)) | M48: =IF(A48="","",ROUND((F48*0.45)+(J48*0.4)+((11-I48)*0.15),2)) | N48: =IFERROR(__xludf.DUMMYFUNCTION("IF(A48="""","""",RANK(M48,FILTER($M$11:$M$100,$A$11:$A$100<>""""),0))"),"") | O48: =IF(A48="","",IF(AND(F48>=8,J48<4),"DREAM",IF(J48>=8,"DO NOW",IF(J48>=6,"START PLANNING",IF(K48>=7,"BUILD TOWARDS","PARK"))))) | P48: =IF(A48="","",IF(J48>=9,"NONE",IF(G48<=H48,IF(G48<=11-I48,"MONEY","DIFFICULTY"),IF(H48<=11-I48,"TIME","DIFFICULTY")))) | R48: =IF(A48="","",MAX(0,D48-MAX(0,$E$4-$E$8))) | S48: =IF(A48="","",IF(R48=0,0,IF($E$6<=0,"NO SAVINGS",ROUNDUP(R48/$E$6,0)))) | T48: =IFERROR(__xludf.DUMMYFUNCTION("IF(A48="""","""",RANK(F48,FILTER($F$11:$F$100,$A$11:$A$100<>""""),0))"),"") | U48: =IFERROR(__xludf.DUMMYFUNCTION("IF(A48="""","""",RANK( (F48*0.5+K48*0.5), FILTER($F$11:$F$100*0.5+$K$11:$K$100*0.5,$A$11:$A$100<>""""), 0))"),"") | V48: =IFERROR(__xludf.DUMMYFUNCTION("IF(A48="""","""",RANK( (F48*0.65+L48*0.35), FILTER($F$11:$F$100*0.65+$L$11:$L$100*0.35,$A$11:$A$100<>""""), 0))"),"")
G49: =IF(A49="","",IF(D49<=0,10,ROUND(MAX(1,MIN(10,(MAX(0,$E$4-$E$8)/D49)*10)),1))) | H49: =IF(A49="","",IF(E49<=0,10,ROUND(MAX(1,MIN(10,10-(E49/MAX(1,$E$7)*10))),1))) | I49: =IF(A49="","",ROUND(MIN(10,MAX(1, ((11-G49)*0.45)+ ((11-H49)*0.25)+ (MIN(10,E49/2)*0.2)+ (IF(C49="NOW",1,IF(C49="THIS YEAR",2,IF(C49="1 YEAR",3,IF(C49="1-3 YEARS",5,IF(C49="3 YEARS",7,6)))))*0.1) )),1)) | J49: =IF(A49="","",ROUND((G49*0.4)+(H49*0.3)+((11-I49)*0.3),1)) | K49: =IF(A49="","",ROUND( (MAX(1,MIN(10,IF(D49<=0,10,(MAX(0,$E$4-$E$8)+($E$6*12))/D49*10)))*0.4) + (MIN(10,H49+0.5)*0.3) + (MIN(10,12-I49)*0.3) ,1)) | L49: =IF(A49="","",ROUND( (MAX(1,MIN(10,IF(D49<=0,10,(MAX(0,$E$4-$E$8)+($E$6*36))/D49*10)))*0.4) + (MIN(10,H49+1.5)*0.3) + (MIN(10,14-I49)*0.3) ,1)) | M49: =IF(A49="","",ROUND((F49*0.45)+(J49*0.4)+((11-I49)*0.15),2)) | N49: =IFERROR(__xludf.DUMMYFUNCTION("IF(A49="""","""",RANK(M49,FILTER($M$11:$M$100,$A$11:$A$100<>""""),0))"),"") | O49: =IF(A49="","",IF(AND(F49>=8,J49<4),"DREAM",IF(J49>=8,"DO NOW",IF(J49>=6,"START PLANNING",IF(K49>=7,"BUILD TOWARDS","PARK"))))) | P49: =IF(A49="","",IF(J49>=9,"NONE",IF(G49<=H49,IF(G49<=11-I49,"MONEY","DIFFICULTY"),IF(H49<=11-I49,"TIME","DIFFICULTY")))) | R49: =IF(A49="","",MAX(0,D49-MAX(0,$E$4-$E$8))) | S49: =IF(A49="","",IF(R49=0,0,IF($E$6<=0,"NO SAVINGS",ROUNDUP(R49/$E$6,0)))) | T49: =IFERROR(__xludf.DUMMYFUNCTION("IF(A49="""","""",RANK(F49,FILTER($F$11:$F$100,$A$11:$A$100<>""""),0))"),"") | U49: =IFERROR(__xludf.DUMMYFUNCTION("IF(A49="""","""",RANK( (F49*0.5+K49*0.5), FILTER($F$11:$F$100*0.5+$K$11:$K$100*0.5,$A$11:$A$100<>""""), 0))"),"") | V49: =IFERROR(__xludf.DUMMYFUNCTION("IF(A49="""","""",RANK( (F49*0.65+L49*0.35), FILTER($F$11:$F$100*0.65+$L$11:$L$100*0.35,$A$11:$A$100<>""""), 0))"),"")
G50: =IF(A50="","",IF(D50<=0,10,ROUND(MAX(1,MIN(10,(MAX(0,$E$4-$E$8)/D50)*10)),1))) | H50: =IF(A50="","",IF(E50<=0,10,ROUND(MAX(1,MIN(10,10-(E50/MAX(1,$E$7)*10))),1))) | I50: =IF(A50="","",ROUND(MIN(10,MAX(1, ((11-G50)*0.45)+ ((11-H50)*0.25)+ (MIN(10,E50/2)*0.2)+ (IF(C50="NOW",1,IF(C50="THIS YEAR",2,IF(C50="1 YEAR",3,IF(C50="1-3 YEARS",5,IF(C50="3 YEARS",7,6)))))*0.1) )),1)) | J50: =IF(A50="","",ROUND((G50*0.4)+(H50*0.3)+((11-I50)*0.3),1)) | K50: =IF(A50="","",ROUND( (MAX(1,MIN(10,IF(D50<=0,10,(MAX(0,$E$4-$E$8)+($E$6*12))/D50*10)))*0.4) + (MIN(10,H50+0.5)*0.3) + (MIN(10,12-I50)*0.3) ,1)) | L50: =IF(A50="","",ROUND( (MAX(1,MIN(10,IF(D50<=0,10,(MAX(0,$E$4-$E$8)+($E$6*36))/D50*10)))*0.4) + (MIN(10,H50+1.5)*0.3) + (MIN(10,14-I50)*0.3) ,1)) | M50: =IF(A50="","",ROUND((F50*0.45)+(J50*0.4)+((11-I50)*0.15),2)) | N50: =IFERROR(__xludf.DUMMYFUNCTION("IF(A50="""","""",RANK(M50,FILTER($M$11:$M$100,$A$11:$A$100<>""""),0))"),"") | O50: =IF(A50="","",IF(AND(F50>=8,J50<4),"DREAM",IF(J50>=8,"DO NOW",IF(J50>=6,"START PLANNING",IF(K50>=7,"BUILD TOWARDS","PARK"))))) | P50: =IF(A50="","",IF(J50>=9,"NONE",IF(G50<=H50,IF(G50<=11-I50,"MONEY","DIFFICULTY"),IF(H50<=11-I50,"TIME","DIFFICULTY")))) | R50: =IF(A50="","",MAX(0,D50-MAX(0,$E$4-$E$8))) | S50: =IF(A50="","",IF(R50=0,0,IF($E$6<=0,"NO SAVINGS",ROUNDUP(R50/$E$6,0)))) | T50: =IFERROR(__xludf.DUMMYFUNCTION("IF(A50="""","""",RANK(F50,FILTER($F$11:$F$100,$A$11:$A$100<>""""),0))"),"") | U50: =IFERROR(__xludf.DUMMYFUNCTION("IF(A50="""","""",RANK( (F50*0.5+K50*0.5), FILTER($F$11:$F$100*0.5+$K$11:$K$100*0.5,$A$11:$A$100<>""""), 0))"),"") | V50: =IFERROR(__xludf.DUMMYFUNCTION("IF(A50="""","""",RANK( (F50*0.65+L50*0.35), FILTER($F$11:$F$100*0.65+$L$11:$L$100*0.35,$A$11:$A$100<>""""), 0))"),"")
G51: =IF(A51="","",IF(D51<=0,10,ROUND(MAX(1,MIN(10,(MAX(0,$E$4-$E$8)/D51)*10)),1))) | H51: =IF(A51="","",IF(E51<=0,10,ROUND(MAX(1,MIN(10,10-(E51/MAX(1,$E$7)*10))),1))) | I51: =IF(A51="","",ROUND(MIN(10,MAX(1, ((11-G51)*0.45)+ ((11-H51)*0.25)+ (MIN(10,E51/2)*0.2)+ (IF(C51="NOW",1,IF(C51="THIS YEAR",2,IF(C51="1 YEAR",3,IF(C51="1-3 YEARS",5,IF(C51="3 YEARS",7,6)))))*0.1) )),1)) | J51: =IF(A51="","",ROUND((G51*0.4)+(H51*0.3)+((11-I51)*0.3),1)) | K51: =IF(A51="","",ROUND( (MAX(1,MIN(10,IF(D51<=0,10,(MAX(0,$E$4-$E$8)+($E$6*12))/D51*10)))*0.4) + (MIN(10,H51+0.5)*0.3) + (MIN(10,12-I51)*0.3) ,1)) | L51: =IF(A51="","",ROUND( (MAX(1,MIN(10,IF(D51<=0,10,(MAX(0,$E$4-$E$8)+($E$6*36))/D51*10)))*0.4) + (MIN(10,H51+1.5)*0.3) + (MIN(10,14-I51)*0.3) ,1)) | M51: =IF(A51="","",ROUND((F51*0.45)+(J51*0.4)+((11-I51)*0.15),2)) | N51: =IFERROR(__xludf.DUMMYFUNCTION("IF(A51="""","""",RANK(M51,FILTER($M$11:$M$100,$A$11:$A$100<>""""),0))"),"") | O51: =IF(A51="","",IF(AND(F51>=8,J51<4),"DREAM",IF(J51>=8,"DO NOW",IF(J51>=6,"START PLANNING",IF(K51>=7,"BUILD TOWARDS","PARK"))))) | P51: =IF(A51="","",IF(J51>=9,"NONE",IF(G51<=H51,IF(G51<=11-I51,"MONEY","DIFFICULTY"),IF(H51<=11-I51,"TIME","DIFFICULTY")))) | R51: =IF(A51="","",MAX(0,D51-MAX(0,$E$4-$E$8))) | S51: =IF(A51="","",IF(R51=0,0,IF($E$6<=0,"NO SAVINGS",ROUNDUP(R51/$E$6,0)))) | T51: =IFERROR(__xludf.DUMMYFUNCTION("IF(A51="""","""",RANK(F51,FILTER($F$11:$F$100,$A$11:$A$100<>""""),0))"),"") | U51: =IFERROR(__xludf.DUMMYFUNCTION("IF(A51="""","""",RANK( (F51*0.5+K51*0.5), FILTER($F$11:$F$100*0.5+$K$11:$K$100*0.5,$A$11:$A$100<>""""), 0))"),"") | V51: =IFERROR(__xludf.DUMMYFUNCTION("IF(A51="""","""",RANK( (F51*0.65+L51*0.35), FILTER($F$11:$F$100*0.65+$L$11:$L$100*0.35,$A$11:$A$100<>""""), 0))"),"")
G52: =IF(A52="","",IF(D52<=0,10,ROUND(MAX(1,MIN(10,(MAX(0,$E$4-$E$8)/D52)*10)),1))) | H52: =IF(A52="","",IF(E52<=0,10,ROUND(MAX(1,MIN(10,10-(E52/MAX(1,$E$7)*10))),1))) | I52: =IF(A52="","",ROUND(MIN(10,MAX(1, ((11-G52)*0.45)+ ((11-H52)*0.25)+ (MIN(10,E52/2)*0.2)+ (IF(C52="NOW",1,IF(C52="THIS YEAR",2,IF(C52="1 YEAR",3,IF(C52="1-3 YEARS",5,IF(C52="3 YEARS",7,6)))))*0.1) )),1)) | J52: =IF(A52="","",ROUND((G52*0.4)+(H52*0.3)+((11-I52)*0.3),1)) | K52: =IF(A52="","",ROUND( (MAX(1,MIN(10,IF(D52<=0,10,(MAX(0,$E$4-$E$8)+($E$6*12))/D52*10)))*0.4) + (MIN(10,H52+0.5)*0.3) + (MIN(10,12-I52)*0.3) ,1)) | L52: =IF(A52="","",ROUND( (MAX(1,MIN(10,IF(D52<=0,10,(MAX(0,$E$4-$E$8)+($E$6*36))/D52*10)))*0.4) + (MIN(10,H52+1.5)*0.3) + (MIN(10,14-I52)*0.3) ,1)) | M52: =IF(A52="","",ROUND((F52*0.45)+(J52*0.4)+((11-I52)*0.15),2)) | N52: =IFERROR(__xludf.DUMMYFUNCTION("IF(A52="""","""",RANK(M52,FILTER($M$11:$M$100,$A$11:$A$100<>""""),0))"),"") | O52: =IF(A52="","",IF(AND(F52>=8,J52<4),"DREAM",IF(J52>=8,"DO NOW",IF(J52>=6,"START PLANNING",IF(K52>=7,"BUILD TOWARDS","PARK"))))) | P52: =IF(A52="","",IF(J52>=9,"NONE",IF(G52<=H52,IF(G52<=11-I52,"MONEY","DIFFICULTY"),IF(H52<=11-I52,"TIME","DIFFICULTY")))) | R52: =IF(A52="","",MAX(0,D52-MAX(0,$E$4-$E$8))) | S52: =IF(A52="","",IF(R52=0,0,IF($E$6<=0,"NO SAVINGS",ROUNDUP(R52/$E$6,0)))) | T52: =IFERROR(__xludf.DUMMYFUNCTION("IF(A52="""","""",RANK(F52,FILTER($F$11:$F$100,$A$11:$A$100<>""""),0))"),"") | U52: =IFERROR(__xludf.DUMMYFUNCTION("IF(A52="""","""",RANK( (F52*0.5+K52*0.5), FILTER($F$11:$F$100*0.5+$K$11:$K$100*0.5,$A$11:$A$100<>""""), 0))"),"") | V52: =IFERROR(__xludf.DUMMYFUNCTION("IF(A52="""","""",RANK( (F52*0.65+L52*0.35), FILTER($F$11:$F$100*0.65+$L$11:$L$100*0.35,$A$11:$A$100<>""""), 0))"),"")
G53: =IF(A53="","",IF(D53<=0,10,ROUND(MAX(1,MIN(10,(MAX(0,$E$4-$E$8)/D53)*10)),1))) | H53: =IF(A53="","",IF(E53<=0,10,ROUND(MAX(1,MIN(10,10-(E53/MAX(1,$E$7)*10))),1))) | I53: =IF(A53="","",ROUND(MIN(10,MAX(1, ((11-G53)*0.45)+ ((11-H53)*0.25)+ (MIN(10,E53/2)*0.2)+ (IF(C53="NOW",1,IF(C53="THIS YEAR",2,IF(C53="1 YEAR",3,IF(C53="1-3 YEARS",5,IF(C53="3 YEARS",7,6)))))*0.1) )),1)) | J53: =IF(A53="","",ROUND((G53*0.4)+(H53*0.3)+((11-I53)*0.3),1)) | K53: =IF(A53="","",ROUND( (MAX(1,MIN(10,IF(D53<=0,10,(MAX(0,$E$4-$E$8)+($E$6*12))/D53*10)))*0.4) + (MIN(10,H53+0.5)*0.3) + (MIN(10,12-I53)*0.3) ,1)) | L53: =IF(A53="","",ROUND( (MAX(1,MIN(10,IF(D53<=0,10,(MAX(0,$E$4-$E$8)+($E$6*36))/D53*10)))*0.4) + (MIN(10,H53+1.5)*0.3) + (MIN(10,14-I53)*0.3) ,1)) | M53: =IF(A53="","",ROUND((F53*0.45)+(J53*0.4)+((11-I53)*0.15),2)) | N53: =IFERROR(__xludf.DUMMYFUNCTION("IF(A53="""","""",RANK(M53,FILTER($M$11:$M$100,$A$11:$A$100<>""""),0))"),"") | O53: =IF(A53="","",IF(AND(F53>=8,J53<4),"DREAM",IF(J53>=8,"DO NOW",IF(J53>=6,"START PLANNING",IF(K53>=7,"BUILD TOWARDS","PARK"))))) | P53: =IF(A53="","",IF(J53>=9,"NONE",IF(G53<=H53,IF(G53<=11-I53,"MONEY","DIFFICULTY"),IF(H53<=11-I53,"TIME","DIFFICULTY")))) | R53: =IF(A53="","",MAX(0,D53-MAX(0,$E$4-$E$8))) | S53: =IF(A53="","",IF(R53=0,0,IF($E$6<=0,"NO SAVINGS",ROUNDUP(R53/$E$6,0)))) | T53: =IFERROR(__xludf.DUMMYFUNCTION("IF(A53="""","""",RANK(F53,FILTER($F$11:$F$100,$A$11:$A$100<>""""),0))"),"") | U53: =IFERROR(__xludf.DUMMYFUNCTION("IF(A53="""","""",RANK( (F53*0.5+K53*0.5), FILTER($F$11:$F$100*0.5+$K$11:$K$100*0.5,$A$11:$A$100<>""""), 0))"),"") | V53: =IFERROR(__xludf.DUMMYFUNCTION("IF(A53="""","""",RANK( (F53*0.65+L53*0.35), FILTER($F$11:$F$100*0.65+$L$11:$L$100*0.35,$A$11:$A$100<>""""), 0))"),"")
G54: =IF(A54="","",IF(D54<=0,10,ROUND(MAX(1,MIN(10,(MAX(0,$E$4-$E$8)/D54)*10)),1))) | H54: =IF(A54="","",IF(E54<=0,10,ROUND(MAX(1,MIN(10,10-(E54/MAX(1,$E$7)*10))),1))) | I54: =IF(A54="","",ROUND(MIN(10,MAX(1, ((11-G54)*0.45)+ ((11-H54)*0.25)+ (MIN(10,E54/2)*0.2)+ (IF(C54="NOW",1,IF(C54="THIS YEAR",2,IF(C54="1 YEAR",3,IF(C54="1-3 YEARS",5,IF(C54="3 YEARS",7,6)))))*0.1) )),1)) | J54: =IF(A54="","",ROUND((G54*0.4)+(H54*0.3)+((11-I54)*0.3),1)) | K54: =IF(A54="","",ROUND( (MAX(1,MIN(10,IF(D54<=0,10,(MAX(0,$E$4-$E$8)+($E$6*12))/D54*10)))*0.4) + (MIN(10,H54+0.5)*0.3) + (MIN(10,12-I54)*0.3) ,1)) | L54: =IF(A54="","",ROUND( (MAX(1,MIN(10,IF(D54<=0,10,(MAX(0,$E$4-$E$8)+($E$6*36))/D54*10)))*0.4) + (MIN(10,H54+1.5)*0.3) + (MIN(10,14-I54)*0.3) ,1)) | M54: =IF(A54="","",ROUND((F54*0.45)+(J54*0.4)+((11-I54)*0.15),2)) | N54: =IFERROR(__xludf.DUMMYFUNCTION("IF(A54="""","""",RANK(M54,FILTER($M$11:$M$100,$A$11:$A$100<>""""),0))"),"") | O54: =IF(A54="","",IF(AND(F54>=8,J54<4),"DREAM",IF(J54>=8,"DO NOW",IF(J54>=6,"START PLANNING",IF(K54>=7,"BUILD TOWARDS","PARK"))))) | P54: =IF(A54="","",IF(J54>=9,"NONE",IF(G54<=H54,IF(G54<=11-I54,"MONEY","DIFFICULTY"),IF(H54<=11-I54,"TIME","DIFFICULTY")))) | R54: =IF(A54="","",MAX(0,D54-MAX(0,$E$4-$E$8))) | S54: =IF(A54="","",IF(R54=0,0,IF($E$6<=0,"NO SAVINGS",ROUNDUP(R54/$E$6,0)))) | T54: =IFERROR(__xludf.DUMMYFUNCTION("IF(A54="""","""",RANK(F54,FILTER($F$11:$F$100,$A$11:$A$100<>""""),0))"),"") | U54: =IFERROR(__xludf.DUMMYFUNCTION("IF(A54="""","""",RANK( (F54*0.5+K54*0.5), FILTER($F$11:$F$100*0.5+$K$11:$K$100*0.5,$A$11:$A$100<>""""), 0))"),"") | V54: =IFERROR(__xludf.DUMMYFUNCTION("IF(A54="""","""",RANK( (F54*0.65+L54*0.35), FILTER($F$11:$F$100*0.65+$L$11:$L$100*0.35,$A$11:$A$100<>""""), 0))"),"")
G55: =IF(A55="","",IF(D55<=0,10,ROUND(MAX(1,MIN(10,(MAX(0,$E$4-$E$8)/D55)*10)),1))) | H55: =IF(A55="","",IF(E55<=0,10,ROUND(MAX(1,MIN(10,10-(E55/MAX(1,$E$7)*10))),1))) | I55: =IF(A55="","",ROUND(MIN(10,MAX(1, ((11-G55)*0.45)+ ((11-H55)*0.25)+ (MIN(10,E55/2)*0.2)+ (IF(C55="NOW",1,IF(C55="THIS YEAR",2,IF(C55="1 YEAR",3,IF(C55="1-3 YEARS",5,IF(C55="3 YEARS",7,6)))))*0.1) )),1)) | J55: =IF(A55="","",ROUND((G55*0.4)+(H55*0.3)+((11-I55)*0.3),1)) | K55: =IF(A55="","",ROUND( (MAX(1,MIN(10,IF(D55<=0,10,(MAX(0,$E$4-$E$8)+($E$6*12))/D55*10)))*0.4) + (MIN(10,H55+0.5)*0.3) + (MIN(10,12-I55)*0.3) ,1)) | L55: =IF(A55="","",ROUND( (MAX(1,MIN(10,IF(D55<=0,10,(MAX(0,$E$4-$E$8)+($E$6*36))/D55*10)))*0.4) + (MIN(10,H55+1.5)*0.3) + (MIN(10,14-I55)*0.3) ,1)) | M55: =IF(A55="","",ROUND((F55*0.45)+(J55*0.4)+((11-I55)*0.15),2)) | N55: =IFERROR(__xludf.DUMMYFUNCTION("IF(A55="""","""",RANK(M55,FILTER($M$11:$M$100,$A$11:$A$100<>""""),0))"),"") | O55: =IF(A55="","",IF(AND(F55>=8,J55<4),"DREAM",IF(J55>=8,"DO NOW",IF(J55>=6,"START PLANNING",IF(K55>=7,"BUILD TOWARDS","PARK"))))) | P55: =IF(A55="","",IF(J55>=9,"NONE",IF(G55<=H55,IF(G55<=11-I55,"MONEY","DIFFICULTY"),IF(H55<=11-I55,"TIME","DIFFICULTY")))) | R55: =IF(A55="","",MAX(0,D55-MAX(0,$E$4-$E$8))) | S55: =IF(A55="","",IF(R55=0,0,IF($E$6<=0,"NO SAVINGS",ROUNDUP(R55/$E$6,0)))) | T55: =IFERROR(__xludf.DUMMYFUNCTION("IF(A55="""","""",RANK(F55,FILTER($F$11:$F$100,$A$11:$A$100<>""""),0))"),"") | U55: =IFERROR(__xludf.DUMMYFUNCTION("IF(A55="""","""",RANK( (F55*0.5+K55*0.5), FILTER($F$11:$F$100*0.5+$K$11:$K$100*0.5,$A$11:$A$100<>""""), 0))"),"") | V55: =IFERROR(__xludf.DUMMYFUNCTION("IF(A55="""","""",RANK( (F55*0.65+L55*0.35), FILTER($F$11:$F$100*0.65+$L$11:$L$100*0.35,$A$11:$A$100<>""""), 0))"),"")
G56: =IF(A56="","",IF(D56<=0,10,ROUND(MAX(1,MIN(10,(MAX(0,$E$4-$E$8)/D56)*10)),1))) | H56: =IF(A56="","",IF(E56<=0,10,ROUND(MAX(1,MIN(10,10-(E56/MAX(1,$E$7)*10))),1))) | I56: =IF(A56="","",ROUND(MIN(10,MAX(1, ((11-G56)*0.45)+ ((11-H56)*0.25)+ (MIN(10,E56/2)*0.2)+ (IF(C56="NOW",1,IF(C56="THIS YEAR",2,IF(C56="1 YEAR",3,IF(C56="1-3 YEARS",5,IF(C56="3 YEARS",7,6)))))*0.1) )),1)) | J56: =IF(A56="","",ROUND((G56*0.4)+(H56*0.3)+((11-I56)*0.3),1)) | K56: =IF(A56="","",ROUND( (MAX(1,MIN(10,IF(D56<=0,10,(MAX(0,$E$4-$E$8)+($E$6*12))/D56*10)))*0.4) + (MIN(10,H56+0.5)*0.3) + (MIN(10,12-I56)*0.3) ,1)) | L56: =IF(A56="","",ROUND( (MAX(1,MIN(10,IF(D56<=0,10,(MAX(0,$E$4-$E$8)+($E$6*36))/D56*10)))*0.4) + (MIN(10,H56+1.5)*0.3) + (MIN(10,14-I56)*0.3) ,1)) | M56: =IF(A56="","",ROUND((F56*0.45)+(J56*0.4)+((11-I56)*0.15),2)) | N56: =IFERROR(__xludf.DUMMYFUNCTION("IF(A56="""","""",RANK(M56,FILTER($M$11:$M$100,$A$11:$A$100<>""""),0))"),"") | O56: =IF(A56="","",IF(AND(F56>=8,J56<4),"DREAM",IF(J56>=8,"DO NOW",IF(J56>=6,"START PLANNING",IF(K56>=7,"BUILD TOWARDS","PARK"))))) | P56: =IF(A56="","",IF(J56>=9,"NONE",IF(G56<=H56,IF(G56<=11-I56,"MONEY","DIFFICULTY"),IF(H56<=11-I56,"TIME","DIFFICULTY")))) | R56: =IF(A56="","",MAX(0,D56-MAX(0,$E$4-$E$8))) | S56: =IF(A56="","",IF(R56=0,0,IF($E$6<=0,"NO SAVINGS",ROUNDUP(R56/$E$6,0)))) | T56: =IFERROR(__xludf.DUMMYFUNCTION("IF(A56="""","""",RANK(F56,FILTER($F$11:$F$100,$A$11:$A$100<>""""),0))"),"") | U56: =IFERROR(__xludf.DUMMYFUNCTION("IF(A56="""","""",RANK( (F56*0.5+K56*0.5), FILTER($F$11:$F$100*0.5+$K$11:$K$100*0.5,$A$11:$A$100<>""""), 0))"),"") | V56: =IFERROR(__xludf.DUMMYFUNCTION("IF(A56="""","""",RANK( (F56*0.65+L56*0.35), FILTER($F$11:$F$100*0.65+$L$11:$L$100*0.35,$A$11:$A$100<>""""), 0))"),"")
G57: =IF(A57="","",IF(D57<=0,10,ROUND(MAX(1,MIN(10,(MAX(0,$E$4-$E$8)/D57)*10)),1))) | H57: =IF(A57="","",IF(E57<=0,10,ROUND(MAX(1,MIN(10,10-(E57/MAX(1,$E$7)*10))),1))) | I57: =IF(A57="","",ROUND(MIN(10,MAX(1, ((11-G57)*0.45)+ ((11-H57)*0.25)+ (MIN(10,E57/2)*0.2)+ (IF(C57="NOW",1,IF(C57="THIS YEAR",2,IF(C57="1 YEAR",3,IF(C57="1-3 YEARS",5,IF(C57="3 YEARS",7,6)))))*0.1) )),1)) | J57: =IF(A57="","",ROUND((G57*0.4)+(H57*0.3)+((11-I57)*0.3),1)) | K57: =IF(A57="","",ROUND( (MAX(1,MIN(10,IF(D57<=0,10,(MAX(0,$E$4-$E$8)+($E$6*12))/D57*10)))*0.4) + (MIN(10,H57+0.5)*0.3) + (MIN(10,12-I57)*0.3) ,1)) | L57: =IF(A57="","",ROUND( (MAX(1,MIN(10,IF(D57<=0,10,(MAX(0,$E$4-$E$8)+($E$6*36))/D57*10)))*0.4) + (MIN(10,H57+1.5)*0.3) + (MIN(10,14-I57)*0.3) ,1)) | M57: =IF(A57="","",ROUND((F57*0.45)+(J57*0.4)+((11-I57)*0.15),2)) | N57: =IFERROR(__xludf.DUMMYFUNCTION("IF(A57="""","""",RANK(M57,FILTER($M$11:$M$100,$A$11:$A$100<>""""),0))"),"") | O57: =IF(A57="","",IF(AND(F57>=8,J57<4),"DREAM",IF(J57>=8,"DO NOW",IF(J57>=6,"START PLANNING",IF(K57>=7,"BUILD TOWARDS","PARK"))))) | P57: =IF(A57="","",IF(J57>=9,"NONE",IF(G57<=H57,IF(G57<=11-I57,"MONEY","DIFFICULTY"),IF(H57<=11-I57,"TIME","DIFFICULTY")))) | R57: =IF(A57="","",MAX(0,D57-MAX(0,$E$4-$E$8))) | S57: =IF(A57="","",IF(R57=0,0,IF($E$6<=0,"NO SAVINGS",ROUNDUP(R57/$E$6,0)))) | T57: =IFERROR(__xludf.DUMMYFUNCTION("IF(A57="""","""",RANK(F57,FILTER($F$11:$F$100,$A$11:$A$100<>""""),0))"),"") | U57: =IFERROR(__xludf.DUMMYFUNCTION("IF(A57="""","""",RANK( (F57*0.5+K57*0.5), FILTER($F$11:$F$100*0.5+$K$11:$K$100*0.5,$A$11:$A$100<>""""), 0))"),"") | V57: =IFERROR(__xludf.DUMMYFUNCTION("IF(A57="""","""",RANK( (F57*0.65+L57*0.35), FILTER($F$11:$F$100*0.65+$L$11:$L$100*0.35,$A$11:$A$100<>""""), 0))"),"")
G58: =IF(A58="","",IF(D58<=0,10,ROUND(MAX(1,MIN(10,(MAX(0,$E$4-$E$8)/D58)*10)),1))) | H58: =IF(A58="","",IF(E58<=0,10,ROUND(MAX(1,MIN(10,10-(E58/MAX(1,$E$7)*10))),1))) | I58: =IF(A58="","",ROUND(MIN(10,MAX(1, ((11-G58)*0.45)+ ((11-H58)*0.25)+ (MIN(10,E58/2)*0.2)+ (IF(C58="NOW",1,IF(C58="THIS YEAR",2,IF(C58="1 YEAR",3,IF(C58="1-3 YEARS",5,IF(C58="3 YEARS",7,6)))))*0.1) )),1)) | J58: =IF(A58="","",ROUND((G58*0.4)+(H58*0.3)+((11-I58)*0.3),1)) | K58: =IF(A58="","",ROUND( (MAX(1,MIN(10,IF(D58<=0,10,(MAX(0,$E$4-$E$8)+($E$6*12))/D58*10)))*0.4) + (MIN(10,H58+0.5)*0.3) + (MIN(10,12-I58)*0.3) ,1)) | L58: =IF(A58="","",ROUND( (MAX(1,MIN(10,IF(D58<=0,10,(MAX(0,$E$4-$E$8)+($E$6*36))/D58*10)))*0.4) + (MIN(10,H58+1.5)*0.3) + (MIN(10,14-I58)*0.3) ,1)) | M58: =IF(A58="","",ROUND((F58*0.45)+(J58*0.4)+((11-I58)*0.15),2)) | N58: =IFERROR(__xludf.DUMMYFUNCTION("IF(A58="""","""",RANK(M58,FILTER($M$11:$M$100,$A$11:$A$100<>""""),0))"),"") | O58: =IF(A58="","",IF(AND(F58>=8,J58<4),"DREAM",IF(J58>=8,"DO NOW",IF(J58>=6,"START PLANNING",IF(K58>=7,"BUILD TOWARDS","PARK"))))) | P58: =IF(A58="","",IF(J58>=9,"NONE",IF(G58<=H58,IF(G58<=11-I58,"MONEY","DIFFICULTY"),IF(H58<=11-I58,"TIME","DIFFICULTY")))) | R58: =IF(A58="","",MAX(0,D58-MAX(0,$E$4-$E$8))) | S58: =IF(A58="","",IF(R58=0,0,IF($E$6<=0,"NO SAVINGS",ROUNDUP(R58/$E$6,0)))) | T58: =IFERROR(__xludf.DUMMYFUNCTION("IF(A58="""","""",RANK(F58,FILTER($F$11:$F$100,$A$11:$A$100<>""""),0))"),"") | U58: =IFERROR(__xludf.DUMMYFUNCTION("IF(A58="""","""",RANK( (F58*0.5+K58*0.5), FILTER($F$11:$F$100*0.5+$K$11:$K$100*0.5,$A$11:$A$100<>""""), 0))"),"") | V58: =IFERROR(__xludf.DUMMYFUNCTION("IF(A58="""","""",RANK( (F58*0.65+L58*0.35), FILTER($F$11:$F$100*0.65+$L$11:$L$100*0.35,$A$11:$A$100<>""""), 0))"),"")
G59: =IF(A59="","",IF(D59<=0,10,ROUND(MAX(1,MIN(10,(MAX(0,$E$4-$E$8)/D59)*10)),1))) | H59: =IF(A59="","",IF(E59<=0,10,ROUND(MAX(1,MIN(10,10-(E59/MAX(1,$E$7)*10))),1))) | I59: =IF(A59="","",ROUND(MIN(10,MAX(1, ((11-G59)*0.45)+ ((11-H59)*0.25)+ (MIN(10,E59/2)*0.2)+ (IF(C59="NOW",1,IF(C59="THIS YEAR",2,IF(C59="1 YEAR",3,IF(C59="1-3 YEARS",5,IF(C59="3 YEARS",7,6)))))*0.1) )),1)) | J59: =IF(A59="","",ROUND((G59*0.4)+(H59*0.3)+((11-I59)*0.3),1)) | K59: =IF(A59="","",ROUND( (MAX(1,MIN(10,IF(D59<=0,10,(MAX(0,$E$4-$E$8)+($E$6*12))/D59*10)))*0.4) + (MIN(10,H59+0.5)*0.3) + (MIN(10,12-I59)*0.3) ,1)) | L59: =IF(A59="","",ROUND( (MAX(1,MIN(10,IF(D59<=0,10,(MAX(0,$E$4-$E$8)+($E$6*36))/D59*10)))*0.4) + (MIN(10,H59+1.5)*0.3) + (MIN(10,14-I59)*0.3) ,1)) | M59: =IF(A59="","",ROUND((F59*0.45)+(J59*0.4)+((11-I59)*0.15),2)) | N59: =IFERROR(__xludf.DUMMYFUNCTION("IF(A59="""","""",RANK(M59,FILTER($M$11:$M$100,$A$11:$A$100<>""""),0))"),"") | O59: =IF(A59="","",IF(AND(F59>=8,J59<4),"DREAM",IF(J59>=8,"DO NOW",IF(J59>=6,"START PLANNING",IF(K59>=7,"BUILD TOWARDS","PARK"))))) | P59: =IF(A59="","",IF(J59>=9,"NONE",IF(G59<=H59,IF(G59<=11-I59,"MONEY","DIFFICULTY"),IF(H59<=11-I59,"TIME","DIFFICULTY")))) | R59: =IF(A59="","",MAX(0,D59-MAX(0,$E$4-$E$8))) | S59: =IF(A59="","",IF(R59=0,0,IF($E$6<=0,"NO SAVINGS",ROUNDUP(R59/$E$6,0)))) | T59: =IFERROR(__xludf.DUMMYFUNCTION("IF(A59="""","""",RANK(F59,FILTER($F$11:$F$100,$A$11:$A$100<>""""),0))"),"") | U59: =IFERROR(__xludf.DUMMYFUNCTION("IF(A59="""","""",RANK( (F59*0.5+K59*0.5), FILTER($F$11:$F$100*0.5+$K$11:$K$100*0.5,$A$11:$A$100<>""""), 0))"),"") | V59: =IFERROR(__xludf.DUMMYFUNCTION("IF(A59="""","""",RANK( (F59*0.65+L59*0.35), FILTER($F$11:$F$100*0.65+$L$11:$L$100*0.35,$A$11:$A$100<>""""), 0))"),"")
G60: =IF(A60="","",IF(D60<=0,10,ROUND(MAX(1,MIN(10,(MAX(0,$E$4-$E$8)/D60)*10)),1))) | H60: =IF(A60="","",IF(E60<=0,10,ROUND(MAX(1,MIN(10,10-(E60/MAX(1,$E$7)*10))),1))) | I60: =IF(A60="","",ROUND(MIN(10,MAX(1, ((11-G60)*0.45)+ ((11-H60)*0.25)+ (MIN(10,E60/2)*0.2)+ (IF(C60="NOW",1,IF(C60="THIS YEAR",2,IF(C60="1 YEAR",3,IF(C60="1-3 YEARS",5,IF(C60="3 YEARS",7,6)))))*0.1) )),1)) | J60: =IF(A60="","",ROUND((G60*0.4)+(H60*0.3)+((11-I60)*0.3),1)) | K60: =IF(A60="","",ROUND( (MAX(1,MIN(10,IF(D60<=0,10,(MAX(0,$E$4-$E$8)+($E$6*12))/D60*10)))*0.4) + (MIN(10,H60+0.5)*0.3) + (MIN(10,12-I60)*0.3) ,1)) | L60: =IF(A60="","",ROUND( (MAX(1,MIN(10,IF(D60<=0,10,(MAX(0,$E$4-$E$8)+($E$6*36))/D60*10)))*0.4) + (MIN(10,H60+1.5)*0.3) + (MIN(10,14-I60)*0.3) ,1)) | M60: =IF(A60="","",ROUND((F60*0.45)+(J60*0.4)+((11-I60)*0.15),2)) | N60: =IFERROR(__xludf.DUMMYFUNCTION("IF(A60="""","""",RANK(M60,FILTER($M$11:$M$100,$A$11:$A$100<>""""),0))"),"") | O60: =IF(A60="","",IF(AND(F60>=8,J60<4),"DREAM",IF(J60>=8,"DO NOW",IF(J60>=6,"START PLANNING",IF(K60>=7,"BUILD TOWARDS","PARK"))))) | P60: =IF(A60="","",IF(J60>=9,"NONE",IF(G60<=H60,IF(G60<=11-I60,"MONEY","DIFFICULTY"),IF(H60<=11-I60,"TIME","DIFFICULTY")))) | R60: =IF(A60="","",MAX(0,D60-MAX(0,$E$4-$E$8))) | S60: =IF(A60="","",IF(R60=0,0,IF($E$6<=0,"NO SAVINGS",ROUNDUP(R60/$E$6,0)))) | T60: =IFERROR(__xludf.DUMMYFUNCTION("IF(A60="""","""",RANK(F60,FILTER($F$11:$F$100,$A$11:$A$100<>""""),0))"),"") | U60: =IFERROR(__xludf.DUMMYFUNCTION("IF(A60="""","""",RANK( (F60*0.5+K60*0.5), FILTER($F$11:$F$100*0.5+$K$11:$K$100*0.5,$A$11:$A$100<>""""), 0))"),"") | V60: =IFERROR(__xludf.DUMMYFUNCTION("IF(A60="""","""",RANK( (F60*0.65+L60*0.35), FILTER($F$11:$F$100*0.65+$L$11:$L$100*0.35,$A$11:$A$100<>""""), 0))"),"")
G61: =IF(A61="","",IF(D61<=0,10,ROUND(MAX(1,MIN(10,(MAX(0,$E$4-$E$8)/D61)*10)),1))) | H61: =IF(A61="","",IF(E61<=0,10,ROUND(MAX(1,MIN(10,10-(E61/MAX(1,$E$7)*10))),1))) | I61: =IF(A61="","",ROUND(MIN(10,MAX(1, ((11-G61)*0.45)+ ((11-H61)*0.25)+ (MIN(10,E61/2)*0.2)+ (IF(C61="NOW",1,IF(C61="THIS YEAR",2,IF(C61="1 YEAR",3,IF(C61="1-3 YEARS",5,IF(C61="3 YEARS",7,6)))))*0.1) )),1)) | J61: =IF(A61="","",ROUND((G61*0.4)+(H61*0.3)+((11-I61)*0.3),1)) | K61: =IF(A61="","",ROUND( (MAX(1,MIN(10,IF(D61<=0,10,(MAX(0,$E$4-$E$8)+($E$6*12))/D61*10)))*0.4) + (MIN(10,H61+0.5)*0.3) + (MIN(10,12-I61)*0.3) ,1)) | L61: =IF(A61="","",ROUND( (MAX(1,MIN(10,IF(D61<=0,10,(MAX(0,$E$4-$E$8)+($E$6*36))/D61*10)))*0.4) + (MIN(10,H61+1.5)*0.3) + (MIN(10,14-I61)*0.3) ,1)) | M61: =IF(A61="","",ROUND((F61*0.45)+(J61*0.4)+((11-I61)*0.15),2)) | N61: =IFERROR(__xludf.DUMMYFUNCTION("IF(A61="""","""",RANK(M61,FILTER($M$11:$M$100,$A$11:$A$100<>""""),0))"),"") | O61: =IF(A61="","",IF(AND(F61>=8,J61<4),"DREAM",IF(J61>=8,"DO NOW",IF(J61>=6,"START PLANNING",IF(K61>=7,"BUILD TOWARDS","PARK"))))) | P61: =IF(A61="","",IF(J61>=9,"NONE",IF(G61<=H61,IF(G61<=11-I61,"MONEY","DIFFICULTY"),IF(H61<=11-I61,"TIME","DIFFICULTY")))) | R61: =IF(A61="","",MAX(0,D61-MAX(0,$E$4-$E$8))) | S61: =IF(A61="","",IF(R61=0,0,IF($E$6<=0,"NO SAVINGS",ROUNDUP(R61/$E$6,0)))) | T61: =IFERROR(__xludf.DUMMYFUNCTION("IF(A61="""","""",RANK(F61,FILTER($F$11:$F$100,$A$11:$A$100<>""""),0))"),"") | U61: =IFERROR(__xludf.DUMMYFUNCTION("IF(A61="""","""",RANK( (F61*0.5+K61*0.5), FILTER($F$11:$F$100*0.5+$K$11:$K$100*0.5,$A$11:$A$100<>""""), 0))"),"") | V61: =IFERROR(__xludf.DUMMYFUNCTION("IF(A61="""","""",RANK( (F61*0.65+L61*0.35), FILTER($F$11:$F$100*0.65+$L$11:$L$100*0.35,$A$11:$A$100<>""""), 0))"),"")
G62: =IF(A62="","",IF(D62<=0,10,ROUND(MAX(1,MIN(10,(MAX(0,$E$4-$E$8)/D62)*10)),1))) | H62: =IF(A62="","",IF(E62<=0,10,ROUND(MAX(1,MIN(10,10-(E62/MAX(1,$E$7)*10))),1))) | I62: =IF(A62="","",ROUND(MIN(10,MAX(1, ((11-G62)*0.45)+ ((11-H62)*0.25)+ (MIN(10,E62/2)*0.2)+ (IF(C62="NOW",1,IF(C62="THIS YEAR",2,IF(C62="1 YEAR",3,IF(C62="1-3 YEARS",5,IF(C62="3 YEARS",7,6)))))*0.1) )),1)) | J62: =IF(A62="","",ROUND((G62*0.4)+(H62*0.3)+((11-I62)*0.3),1)) | K62: =IF(A62="","",ROUND( (MAX(1,MIN(10,IF(D62<=0,10,(MAX(0,$E$4-$E$8)+($E$6*12))/D62*10)))*0.4) + (MIN(10,H62+0.5)*0.3) + (MIN(10,12-I62)*0.3) ,1)) | L62: =IF(A62="","",ROUND( (MAX(1,MIN(10,IF(D62<=0,10,(MAX(0,$E$4-$E$8)+($E$6*36))/D62*10)))*0.4) + (MIN(10,H62+1.5)*0.3) + (MIN(10,14-I62)*0.3) ,1)) | M62: =IF(A62="","",ROUND((F62*0.45)+(J62*0.4)+((11-I62)*0.15),2)) | N62: =IFERROR(__xludf.DUMMYFUNCTION("IF(A62="""","""",RANK(M62,FILTER($M$11:$M$100,$A$11:$A$100<>""""),0))"),"") | O62: =IF(A62="","",IF(AND(F62>=8,J62<4),"DREAM",IF(J62>=8,"DO NOW",IF(J62>=6,"START PLANNING",IF(K62>=7,"BUILD TOWARDS","PARK"))))) | P62: =IF(A62="","",IF(J62>=9,"NONE",IF(G62<=H62,IF(G62<=11-I62,"MONEY","DIFFICULTY"),IF(H62<=11-I62,"TIME","DIFFICULTY")))) | R62: =IF(A62="","",MAX(0,D62-MAX(0,$E$4-$E$8))) | S62: =IF(A62="","",IF(R62=0,0,IF($E$6<=0,"NO SAVINGS",ROUNDUP(R62/$E$6,0)))) | T62: =IFERROR(__xludf.DUMMYFUNCTION("IF(A62="""","""",RANK(F62,FILTER($F$11:$F$100,$A$11:$A$100<>""""),0))"),"") | U62: =IFERROR(__xludf.DUMMYFUNCTION("IF(A62="""","""",RANK( (F62*0.5+K62*0.5), FILTER($F$11:$F$100*0.5+$K$11:$K$100*0.5,$A$11:$A$100<>""""), 0))"),"") | V62: =IFERROR(__xludf.DUMMYFUNCTION("IF(A62="""","""",RANK( (F62*0.65+L62*0.35), FILTER($F$11:$F$100*0.65+$L$11:$L$100*0.35,$A$11:$A$100<>""""), 0))"),"")
G63: =IF(A63="","",IF(D63<=0,10,ROUND(MAX(1,MIN(10,(MAX(0,$E$4-$E$8)/D63)*10)),1))) | H63: =IF(A63="","",IF(E63<=0,10,ROUND(MAX(1,MIN(10,10-(E63/MAX(1,$E$7)*10))),1))) | I63: =IF(A63="","",ROUND(MIN(10,MAX(1, ((11-G63)*0.45)+ ((11-H63)*0.25)+ (MIN(10,E63/2)*0.2)+ (IF(C63="NOW",1,IF(C63="THIS YEAR",2,IF(C63="1 YEAR",3,IF(C63="1-3 YEARS",5,IF(C63="3 YEARS",7,6)))))*0.1) )),1)) | J63: =IF(A63="","",ROUND((G63*0.4)+(H63*0.3)+((11-I63)*0.3),1)) | K63: =IF(A63="","",ROUND( (MAX(1,MIN(10,IF(D63<=0,10,(MAX(0,$E$4-$E$8)+($E$6*12))/D63*10)))*0.4) + (MIN(10,H63+0.5)*0.3) + (MIN(10,12-I63)*0.3) ,1)) | L63: =IF(A63="","",ROUND( (MAX(1,MIN(10,IF(D63<=0,10,(MAX(0,$E$4-$E$8)+($E$6*36))/D63*10)))*0.4) + (MIN(10,H63+1.5)*0.3) + (MIN(10,14-I63)*0.3) ,1)) | M63: =IF(A63="","",ROUND((F63*0.45)+(J63*0.4)+((11-I63)*0.15),2)) | N63: =IFERROR(__xludf.DUMMYFUNCTION("IF(A63="""","""",RANK(M63,FILTER($M$11:$M$100,$A$11:$A$100<>""""),0))"),"") | O63: =IF(A63="","",IF(AND(F63>=8,J63<4),"DREAM",IF(J63>=8,"DO NOW",IF(J63>=6,"START PLANNING",IF(K63>=7,"BUILD TOWARDS","PARK"))))) | P63: =IF(A63="","",IF(J63>=9,"NONE",IF(G63<=H63,IF(G63<=11-I63,"MONEY","DIFFICULTY"),IF(H63<=11-I63,"TIME","DIFFICULTY")))) | R63: =IF(A63="","",MAX(0,D63-MAX(0,$E$4-$E$8))) | S63: =IF(A63="","",IF(R63=0,0,IF($E$6<=0,"NO SAVINGS",ROUNDUP(R63/$E$6,0)))) | T63: =IFERROR(__xludf.DUMMYFUNCTION("IF(A63="""","""",RANK(F63,FILTER($F$11:$F$100,$A$11:$A$100<>""""),0))"),"") | U63: =IFERROR(__xludf.DUMMYFUNCTION("IF(A63="""","""",RANK( (F63*0.5+K63*0.5), FILTER($F$11:$F$100*0.5+$K$11:$K$100*0.5,$A$11:$A$100<>""""), 0))"),"") | V63: =IFERROR(__xludf.DUMMYFUNCTION("IF(A63="""","""",RANK( (F63*0.65+L63*0.35), FILTER($F$11:$F$100*0.65+$L$11:$L$100*0.35,$A$11:$A$100<>""""), 0))"),"")
G64: =IF(A64="","",IF(D64<=0,10,ROUND(MAX(1,MIN(10,(MAX(0,$E$4-$E$8)/D64)*10)),1))) | H64: =IF(A64="","",IF(E64<=0,10,ROUND(MAX(1,MIN(10,10-(E64/MAX(1,$E$7)*10))),1))) | I64: =IF(A64="","",ROUND(MIN(10,MAX(1, ((11-G64)*0.45)+ ((11-H64)*0.25)+ (MIN(10,E64/2)*0.2)+ (IF(C64="NOW",1,IF(C64="THIS YEAR",2,IF(C64="1 YEAR",3,IF(C64="1-3 YEARS",5,IF(C64="3 YEARS",7,6)))))*0.1) )),1)) | J64: =IF(A64="","",ROUND((G64*0.4)+(H64*0.3)+((11-I64)*0.3),1)) | K64: =IF(A64="","",ROUND( (MAX(1,MIN(10,IF(D64<=0,10,(MAX(0,$E$4-$E$8)+($E$6*12))/D64*10)))*0.4) + (MIN(10,H64+0.5)*0.3) + (MIN(10,12-I64)*0.3) ,1)) | L64: =IF(A64="","",ROUND( (MAX(1,MIN(10,IF(D64<=0,10,(MAX(0,$E$4-$E$8)+($E$6*36))/D64*10)))*0.4) + (MIN(10,H64+1.5)*0.3) + (MIN(10,14-I64)*0.3) ,1)) | M64: =IF(A64="","",ROUND((F64*0.45)+(J64*0.4)+((11-I64)*0.15),2)) | N64: =IFERROR(__xludf.DUMMYFUNCTION("IF(A64="""","""",RANK(M64,FILTER($M$11:$M$100,$A$11:$A$100<>""""),0))"),"") | O64: =IF(A64="","",IF(AND(F64>=8,J64<4),"DREAM",IF(J64>=8,"DO NOW",IF(J64>=6,"START PLANNING",IF(K64>=7,"BUILD TOWARDS","PARK"))))) | P64: =IF(A64="","",IF(J64>=9,"NONE",IF(G64<=H64,IF(G64<=11-I64,"MONEY","DIFFICULTY"),IF(H64<=11-I64,"TIME","DIFFICULTY")))) | R64: =IF(A64="","",MAX(0,D64-MAX(0,$E$4-$E$8))) | S64: =IF(A64="","",IF(R64=0,0,IF($E$6<=0,"NO SAVINGS",ROUNDUP(R64/$E$6,0)))) | T64: =IFERROR(__xludf.DUMMYFUNCTION("IF(A64="""","""",RANK(F64,FILTER($F$11:$F$100,$A$11:$A$100<>""""),0))"),"") | U64: =IFERROR(__xludf.DUMMYFUNCTION("IF(A64="""","""",RANK( (F64*0.5+K64*0.5), FILTER($F$11:$F$100*0.5+$K$11:$K$100*0.5,$A$11:$A$100<>""""), 0))"),"") | V64: =IFERROR(__xludf.DUMMYFUNCTION("IF(A64="""","""",RANK( (F64*0.65+L64*0.35), FILTER($F$11:$F$100*0.65+$L$11:$L$100*0.35,$A$11:$A$100<>""""), 0))"),"")
G65: =IF(A65="","",IF(D65<=0,10,ROUND(MAX(1,MIN(10,(MAX(0,$E$4-$E$8)/D65)*10)),1))) | H65: =IF(A65="","",IF(E65<=0,10,ROUND(MAX(1,MIN(10,10-(E65/MAX(1,$E$7)*10))),1))) | I65: =IF(A65="","",ROUND(MIN(10,MAX(1, ((11-G65)*0.45)+ ((11-H65)*0.25)+ (MIN(10,E65/2)*0.2)+ (IF(C65="NOW",1,IF(C65="THIS YEAR",2,IF(C65="1 YEAR",3,IF(C65="1-3 YEARS",5,IF(C65="3 YEARS",7,6)))))*0.1) )),1)) | J65: =IF(A65="","",ROUND((G65*0.4)+(H65*0.3)+((11-I65)*0.3),1)) | K65: =IF(A65="","",ROUND( (MAX(1,MIN(10,IF(D65<=0,10,(MAX(0,$E$4-$E$8)+($E$6*12))/D65*10)))*0.4) + (MIN(10,H65+0.5)*0.3) + (MIN(10,12-I65)*0.3) ,1)) | L65: =IF(A65="","",ROUND( (MAX(1,MIN(10,IF(D65<=0,10,(MAX(0,$E$4-$E$8)+($E$6*36))/D65*10)))*0.4) + (MIN(10,H65+1.5)*0.3) + (MIN(10,14-I65)*0.3) ,1)) | M65: =IF(A65="","",ROUND((F65*0.45)+(J65*0.4)+((11-I65)*0.15),2)) | N65: =IFERROR(__xludf.DUMMYFUNCTION("IF(A65="""","""",RANK(M65,FILTER($M$11:$M$100,$A$11:$A$100<>""""),0))"),"") | O65: =IF(A65="","",IF(AND(F65>=8,J65<4),"DREAM",IF(J65>=8,"DO NOW",IF(J65>=6,"START PLANNING",IF(K65>=7,"BUILD TOWARDS","PARK"))))) | P65: =IF(A65="","",IF(J65>=9,"NONE",IF(G65<=H65,IF(G65<=11-I65,"MONEY","DIFFICULTY"),IF(H65<=11-I65,"TIME","DIFFICULTY")))) | R65: =IF(A65="","",MAX(0,D65-MAX(0,$E$4-$E$8))) | S65: =IF(A65="","",IF(R65=0,0,IF($E$6<=0,"NO SAVINGS",ROUNDUP(R65/$E$6,0)))) | T65: =IFERROR(__xludf.DUMMYFUNCTION("IF(A65="""","""",RANK(F65,FILTER($F$11:$F$100,$A$11:$A$100<>""""),0))"),"") | U65: =IFERROR(__xludf.DUMMYFUNCTION("IF(A65="""","""",RANK( (F65*0.5+K65*0.5), FILTER($F$11:$F$100*0.5+$K$11:$K$100*0.5,$A$11:$A$100<>""""), 0))"),"") | V65: =IFERROR(__xludf.DUMMYFUNCTION("IF(A65="""","""",RANK( (F65*0.65+L65*0.35), FILTER($F$11:$F$100*0.65+$L$11:$L$100*0.35,$A$11:$A$100<>""""), 0))"),"")
G66: =IF(A66="","",IF(D66<=0,10,ROUND(MAX(1,MIN(10,(MAX(0,$E$4-$E$8)/D66)*10)),1))) | H66: =IF(A66="","",IF(E66<=0,10,ROUND(MAX(1,MIN(10,10-(E66/MAX(1,$E$7)*10))),1))) | I66: =IF(A66="","",ROUND(MIN(10,MAX(1, ((11-G66)*0.45)+ ((11-H66)*0.25)+ (MIN(10,E66/2)*0.2)+ (IF(C66="NOW",1,IF(C66="THIS YEAR",2,IF(C66="1 YEAR",3,IF(C66="1-3 YEARS",5,IF(C66="3 YEARS",7,6)))))*0.1) )),1)) | J66: =IF(A66="","",ROUND((G66*0.4)+(H66*0.3)+((11-I66)*0.3),1)) | K66: =IF(A66="","",ROUND( (MAX(1,MIN(10,IF(D66<=0,10,(MAX(0,$E$4-$E$8)+($E$6*12))/D66*10)))*0.4) + (MIN(10,H66+0.5)*0.3) + (MIN(10,12-I66)*0.3) ,1)) | L66: =IF(A66="","",ROUND( (MAX(1,MIN(10,IF(D66<=0,10,(MAX(0,$E$4-$E$8)+($E$6*36))/D66*10)))*0.4) + (MIN(10,H66+1.5)*0.3) + (MIN(10,14-I66)*0.3) ,1)) | M66: =IF(A66="","",ROUND((F66*0.45)+(J66*0.4)+((11-I66)*0.15),2)) | N66: =IFERROR(__xludf.DUMMYFUNCTION("IF(A66="""","""",RANK(M66,FILTER($M$11:$M$100,$A$11:$A$100<>""""),0))"),"") | O66: =IF(A66="","",IF(AND(F66>=8,J66<4),"DREAM",IF(J66>=8,"DO NOW",IF(J66>=6,"START PLANNING",IF(K66>=7,"BUILD TOWARDS","PARK"))))) | P66: =IF(A66="","",IF(J66>=9,"NONE",IF(G66<=H66,IF(G66<=11-I66,"MONEY","DIFFICULTY"),IF(H66<=11-I66,"TIME","DIFFICULTY")))) | R66: =IF(A66="","",MAX(0,D66-MAX(0,$E$4-$E$8))) | S66: =IF(A66="","",IF(R66=0,0,IF($E$6<=0,"NO SAVINGS",ROUNDUP(R66/$E$6,0)))) | T66: =IFERROR(__xludf.DUMMYFUNCTION("IF(A66="""","""",RANK(F66,FILTER($F$11:$F$100,$A$11:$A$100<>""""),0))"),"") | U66: =IFERROR(__xludf.DUMMYFUNCTION("IF(A66="""","""",RANK( (F66*0.5+K66*0.5), FILTER($F$11:$F$100*0.5+$K$11:$K$100*0.5,$A$11:$A$100<>""""), 0))"),"") | V66: =IFERROR(__xludf.DUMMYFUNCTION("IF(A66="""","""",RANK( (F66*0.65+L66*0.35), FILTER($F$11:$F$100*0.65+$L$11:$L$100*0.35,$A$11:$A$100<>""""), 0))"),"")
G67: =IF(A67="","",IF(D67<=0,10,ROUND(MAX(1,MIN(10,(MAX(0,$E$4-$E$8)/D67)*10)),1))) | H67: =IF(A67="","",IF(E67<=0,10,ROUND(MAX(1,MIN(10,10-(E67/MAX(1,$E$7)*10))),1))) | I67: =IF(A67="","",ROUND(MIN(10,MAX(1, ((11-G67)*0.45)+ ((11-H67)*0.25)+ (MIN(10,E67/2)*0.2)+ (IF(C67="NOW",1,IF(C67="THIS YEAR",2,IF(C67="1 YEAR",3,IF(C67="1-3 YEARS",5,IF(C67="3 YEARS",7,6)))))*0.1) )),1)) | J67: =IF(A67="","",ROUND((G67*0.4)+(H67*0.3)+((11-I67)*0.3),1)) | K67: =IF(A67="","",ROUND( (MAX(1,MIN(10,IF(D67<=0,10,(MAX(0,$E$4-$E$8)+($E$6*12))/D67*10)))*0.4) + (MIN(10,H67+0.5)*0.3) + (MIN(10,12-I67)*0.3) ,1)) | L67: =IF(A67="","",ROUND( (MAX(1,MIN(10,IF(D67<=0,10,(MAX(0,$E$4-$E$8)+($E$6*36))/D67*10)))*0.4) + (MIN(10,H67+1.5)*0.3) + (MIN(10,14-I67)*0.3) ,1)) | M67: =IF(A67="","",ROUND((F67*0.45)+(J67*0.4)+((11-I67)*0.15),2)) | N67: =IFERROR(__xludf.DUMMYFUNCTION("IF(A67="""","""",RANK(M67,FILTER($M$11:$M$100,$A$11:$A$100<>""""),0))"),"") | O67: =IF(A67="","",IF(AND(F67>=8,J67<4),"DREAM",IF(J67>=8,"DO NOW",IF(J67>=6,"START PLANNING",IF(K67>=7,"BUILD TOWARDS","PARK"))))) | P67: =IF(A67="","",IF(J67>=9,"NONE",IF(G67<=H67,IF(G67<=11-I67,"MONEY","DIFFICULTY"),IF(H67<=11-I67,"TIME","DIFFICULTY")))) | R67: =IF(A67="","",MAX(0,D67-MAX(0,$E$4-$E$8))) | S67: =IF(A67="","",IF(R67=0,0,IF($E$6<=0,"NO SAVINGS",ROUNDUP(R67/$E$6,0)))) | T67: =IFERROR(__xludf.DUMMYFUNCTION("IF(A67="""","""",RANK(F67,FILTER($F$11:$F$100,$A$11:$A$100<>""""),0))"),"") | U67: =IFERROR(__xludf.DUMMYFUNCTION("IF(A67="""","""",RANK( (F67*0.5+K67*0.5), FILTER($F$11:$F$100*0.5+$K$11:$K$100*0.5,$A$11:$A$100<>""""), 0))"),"") | V67: =IFERROR(__xludf.DUMMYFUNCTION("IF(A67="""","""",RANK( (F67*0.45+L67*0.55), FILTER($F$11:$F$100*0.45+$L$11:$L$100*0.55,$A$11:$A$100<>""""), 0))"),"")
G68: =IF(A68="","",IF(D68<=0,10,ROUND(MAX(1,MIN(10,(MAX(0,$E$4-$E$8)/D68)*10)),1))) | H68: =IF(A68="","",IF(E68<=0,10,ROUND(MAX(1,MIN(10,10-(E68/MAX(1,$E$7)*10))),1))) | I68: =IF(A68="","",ROUND(MIN(10,MAX(1, ((11-G68)*0.45)+ ((11-H68)*0.25)+ (MIN(10,E68/2)*0.2)+ (IF(C68="NOW",1,IF(C68="THIS YEAR",2,IF(C68="1 YEAR",3,IF(C68="1-3 YEARS",5,IF(C68="3 YEARS",7,6)))))*0.1) )),1)) | J68: =IF(A68="","",ROUND((G68*0.4)+(H68*0.3)+((11-I68)*0.3),1)) | K68: =IF(A68="","",ROUND( (MAX(1,MIN(10,IF(D68<=0,10,(MAX(0,$E$4-$E$8)+($E$6*12))/D68*10)))*0.4) + (MIN(10,H68+0.5)*0.3) + (MIN(10,12-I68)*0.3) ,1)) | L68: =IF(A68="","",ROUND( (MAX(1,MIN(10,IF(D68<=0,10,(MAX(0,$E$4-$E$8)+($E$6*36))/D68*10)))*0.4) + (MIN(10,H68+1.5)*0.3) + (MIN(10,14-I68)*0.3) ,1)) | M68: =IF(A68="","",ROUND((F68*0.45)+(J68*0.4)+((11-I68)*0.15),2)) | N68: =IFERROR(__xludf.DUMMYFUNCTION("IF(A68="""","""",RANK(M68,FILTER($M$11:$M$100,$A$11:$A$100<>""""),0))"),"") | O68: =IF(A68="","",IF(AND(F68>=8,J68<4),"DREAM",IF(J68>=8,"DO NOW",IF(J68>=6,"START PLANNING",IF(K68>=7,"BUILD TOWARDS","PARK"))))) | P68: =IF(A68="","",IF(J68>=9,"NONE",IF(G68<=H68,IF(G68<=11-I68,"MONEY","DIFFICULTY"),IF(H68<=11-I68,"TIME","DIFFICULTY")))) | R68: =IF(A68="","",MAX(0,D68-MAX(0,$E$4-$E$8))) | S68: =IF(A68="","",IF(R68=0,0,IF($E$6<=0,"NO SAVINGS",ROUNDUP(R68/$E$6,0)))) | T68: =IFERROR(__xludf.DUMMYFUNCTION("IF(A68="""","""",RANK(F68,FILTER($F$11:$F$100,$A$11:$A$100<>""""),0))"),"") | U68: =IFERROR(__xludf.DUMMYFUNCTION("IF(A68="""","""",RANK( (F68*0.5+K68*0.5), FILTER($F$11:$F$100*0.5+$K$11:$K$100*0.5,$A$11:$A$100<>""""), 0))"),"") | V68: =IFERROR(__xludf.DUMMYFUNCTION("IF(A68="""","""",RANK( (F68*0.45+L68*0.55), FILTER($F$11:$F$100*0.45+$L$11:$L$100*0.55,$A$11:$A$100<>""""), 0))"),"")
G69: =IF(A69="","",IF(D69<=0,10,ROUND(MAX(1,MIN(10,(MAX(0,$E$4-$E$8)/D69)*10)),1))) | H69: =IF(A69="","",IF(E69<=0,10,ROUND(MAX(1,MIN(10,10-(E69/MAX(1,$E$7)*10))),1))) | I69: =IF(A69="","",ROUND(MIN(10,MAX(1, ((11-G69)*0.45)+ ((11-H69)*0.25)+ (MIN(10,E69/2)*0.2)+ (IF(C69="NOW",1,IF(C69="THIS YEAR",2,IF(C69="1 YEAR",3,IF(C69="1-3 YEARS",5,IF(C69="3 YEARS",7,6)))))*0.1) )),1)) | J69: =IF(A69="","",ROUND((G69*0.4)+(H69*0.3)+((11-I69)*0.3),1)) | K69: =IF(A69="","",ROUND( (MAX(1,MIN(10,IF(D69<=0,10,(MAX(0,$E$4-$E$8)+($E$6*12))/D69*10)))*0.4) + (MIN(10,H69+0.5)*0.3) + (MIN(10,12-I69)*0.3) ,1)) | L69: =IF(A69="","",ROUND( (MAX(1,MIN(10,IF(D69<=0,10,(MAX(0,$E$4-$E$8)+($E$6*36))/D69*10)))*0.4) + (MIN(10,H69+1.5)*0.3) + (MIN(10,14-I69)*0.3) ,1)) | M69: =IF(A69="","",ROUND((F69*0.45)+(J69*0.4)+((11-I69)*0.15),2)) | N69: =IFERROR(__xludf.DUMMYFUNCTION("IF(A69="""","""",RANK(M69,FILTER($M$11:$M$100,$A$11:$A$100<>""""),0))"),"") | O69: =IF(A69="","",IF(AND(F69>=8,J69<4),"DREAM",IF(J69>=8,"DO NOW",IF(J69>=6,"START PLANNING",IF(K69>=7,"BUILD TOWARDS","PARK"))))) | P69: =IF(A69="","",IF(J69>=9,"NONE",IF(G69<=H69,IF(G69<=11-I69,"MONEY","DIFFICULTY"),IF(H69<=11-I69,"TIME","DIFFICULTY")))) | R69: =IF(A69="","",MAX(0,D69-MAX(0,$E$4-$E$8))) | S69: =IF(A69="","",IF(R69=0,0,IF($E$6<=0,"NO SAVINGS",ROUNDUP(R69/$E$6,0)))) | T69: =IFERROR(__xludf.DUMMYFUNCTION("IF(A69="""","""",RANK(F69,FILTER($F$11:$F$100,$A$11:$A$100<>""""),0))"),"") | U69: =IFERROR(__xludf.DUMMYFUNCTION("IF(A69="""","""",RANK( (F69*0.5+K69*0.5), FILTER($F$11:$F$100*0.5+$K$11:$K$100*0.5,$A$11:$A$100<>""""), 0))"),"") | V69: =IFERROR(__xludf.DUMMYFUNCTION("IF(A69="""","""",RANK( (F69*0.45+L69*0.55), FILTER($F$11:$F$100*0.45+$L$11:$L$100*0.55,$A$11:$A$100<>""""), 0))"),"")
G70: =IF(A70="","",IF(D70<=0,10,ROUND(MAX(1,MIN(10,(MAX(0,$E$4-$E$8)/D70)*10)),1))) | H70: =IF(A70="","",IF(E70<=0,10,ROUND(MAX(1,MIN(10,10-(E70/MAX(1,$E$7)*10))),1))) | I70: =IF(A70="","",ROUND(MIN(10,MAX(1, ((11-G70)*0.45)+ ((11-H70)*0.25)+ (MIN(10,E70/2)*0.2)+ (IF(C70="NOW",1,IF(C70="THIS YEAR",2,IF(C70="1 YEAR",3,IF(C70="1-3 YEARS",5,IF(C70="3 YEARS",7,6)))))*0.1) )),1)) | J70: =IF(A70="","",ROUND((G70*0.4)+(H70*0.3)+((11-I70)*0.3),1)) | K70: =IF(A70="","",ROUND( (MAX(1,MIN(10,IF(D70<=0,10,(MAX(0,$E$4-$E$8)+($E$6*12))/D70*10)))*0.4) + (MIN(10,H70+0.5)*0.3) + (MIN(10,12-I70)*0.3) ,1)) | L70: =IF(A70="","",ROUND( (MAX(1,MIN(10,IF(D70<=0,10,(MAX(0,$E$4-$E$8)+($E$6*36))/D70*10)))*0.4) + (MIN(10,H70+1.5)*0.3) + (MIN(10,14-I70)*0.3) ,1)) | M70: =IF(A70="","",ROUND((F70*0.45)+(J70*0.4)+((11-I70)*0.15),2)) | N70: =IFERROR(__xludf.DUMMYFUNCTION("IF(A70="""","""",RANK(M70,FILTER($M$11:$M$100,$A$11:$A$100<>""""),0))"),"") | O70: =IF(A70="","",IF(AND(F70>=8,J70<4),"DREAM",IF(J70>=8,"DO NOW",IF(J70>=6,"START PLANNING",IF(K70>=7,"BUILD TOWARDS","PARK"))))) | P70: =IF(A70="","",IF(J70>=9,"NONE",IF(G70<=H70,IF(G70<=11-I70,"MONEY","DIFFICULTY"),IF(H70<=11-I70,"TIME","DIFFICULTY")))) | R70: =IF(A70="","",MAX(0,D70-MAX(0,$E$4-$E$8))) | S70: =IF(A70="","",IF(R70=0,0,IF($E$6<=0,"NO SAVINGS",ROUNDUP(R70/$E$6,0)))) | T70: =IFERROR(__xludf.DUMMYFUNCTION("IF(A70="""","""",RANK(F70,FILTER($F$11:$F$100,$A$11:$A$100<>""""),0))"),"") | U70: =IFERROR(__xludf.DUMMYFUNCTION("IF(A70="""","""",RANK( (F70*0.5+K70*0.5), FILTER($F$11:$F$100*0.5+$K$11:$K$100*0.5,$A$11:$A$100<>""""), 0))"),"") | V70: =IFERROR(__xludf.DUMMYFUNCTION("IF(A70="""","""",RANK( (F70*0.45+L70*0.55), FILTER($F$11:$F$100*0.45+$L$11:$L$100*0.55,$A$11:$A$100<>""""), 0))"),"")
G71: =IF(A71="","",IF(D71<=0,10,ROUND(MAX(1,MIN(10,(MAX(0,$E$4-$E$8)/D71)*10)),1))) | H71: =IF(A71="","",IF(E71<=0,10,ROUND(MAX(1,MIN(10,10-(E71/MAX(1,$E$7)*10))),1))) | I71: =IF(A71="","",ROUND(MIN(10,MAX(1, ((11-G71)*0.45)+ ((11-H71)*0.25)+ (MIN(10,E71/2)*0.2)+ (IF(C71="NOW",1,IF(C71="THIS YEAR",2,IF(C71="1 YEAR",3,IF(C71="1-3 YEARS",5,IF(C71="3 YEARS",7,6)))))*0.1) )),1)) | J71: =IF(A71="","",ROUND((G71*0.4)+(H71*0.3)+((11-I71)*0.3),1)) | K71: =IF(A71="","",ROUND( (MAX(1,MIN(10,IF(D71<=0,10,(MAX(0,$E$4-$E$8)+($E$6*12))/D71*10)))*0.4) + (MIN(10,H71+0.5)*0.3) + (MIN(10,12-I71)*0.3) ,1)) | L71: =IF(A71="","",ROUND( (MAX(1,MIN(10,IF(D71<=0,10,(MAX(0,$E$4-$E$8)+($E$6*36))/D71*10)))*0.4) + (MIN(10,H71+1.5)*0.3) + (MIN(10,14-I71)*0.3) ,1)) | M71: =IF(A71="","",ROUND((F71*0.45)+(J71*0.4)+((11-I71)*0.15),2)) | N71: =IFERROR(__xludf.DUMMYFUNCTION("IF(A71="""","""",RANK(M71,FILTER($M$11:$M$100,$A$11:$A$100<>""""),0))"),"") | O71: =IF(A71="","",IF(AND(F71>=8,J71<4),"DREAM",IF(J71>=8,"DO NOW",IF(J71>=6,"START PLANNING",IF(K71>=7,"BUILD TOWARDS","PARK"))))) | P71: =IF(A71="","",IF(J71>=9,"NONE",IF(G71<=H71,IF(G71<=11-I71,"MONEY","DIFFICULTY"),IF(H71<=11-I71,"TIME","DIFFICULTY")))) | R71: =IF(A71="","",MAX(0,D71-MAX(0,$E$4-$E$8))) | S71: =IF(A71="","",IF(R71=0,0,IF($E$6<=0,"NO SAVINGS",ROUNDUP(R71/$E$6,0)))) | T71: =IFERROR(__xludf.DUMMYFUNCTION("IF(A71="""","""",RANK(F71,FILTER($F$11:$F$100,$A$11:$A$100<>""""),0))"),"") | U71: =IFERROR(__xludf.DUMMYFUNCTION("IF(A71="""","""",RANK( (F71*0.5+K71*0.5), FILTER($F$11:$F$100*0.5+$K$11:$K$100*0.5,$A$11:$A$100<>""""), 0))"),"") | V71: =IFERROR(__xludf.DUMMYFUNCTION("IF(A71="""","""",RANK( (F71*0.45+L71*0.55), FILTER($F$11:$F$100*0.45+$L$11:$L$100*0.55,$A$11:$A$100<>""""), 0))"),"")
G72: =IF(A72="","",IF(D72<=0,10,ROUND(MAX(1,MIN(10,(MAX(0,$E$4-$E$8)/D72)*10)),1))) | H72: =IF(A72="","",IF(E72<=0,10,ROUND(MAX(1,MIN(10,10-(E72/MAX(1,$E$7)*10))),1))) | I72: =IF(A72="","",ROUND(MIN(10,MAX(1, ((11-G72)*0.45)+ ((11-H72)*0.25)+ (MIN(10,E72/2)*0.2)+ (IF(C72="NOW",1,IF(C72="THIS YEAR",2,IF(C72="1 YEAR",3,IF(C72="1-3 YEARS",5,IF(C72="3 YEARS",7,6)))))*0.1) )),1)) | J72: =IF(A72="","",ROUND((G72*0.4)+(H72*0.3)+((11-I72)*0.3),1)) | K72: =IF(A72="","",ROUND( (MAX(1,MIN(10,IF(D72<=0,10,(MAX(0,$E$4-$E$8)+($E$6*12))/D72*10)))*0.4) + (MIN(10,H72+0.5)*0.3) + (MIN(10,12-I72)*0.3) ,1)) | L72: =IF(A72="","",ROUND( (MAX(1,MIN(10,IF(D72<=0,10,(MAX(0,$E$4-$E$8)+($E$6*36))/D72*10)))*0.4) + (MIN(10,H72+1.5)*0.3) + (MIN(10,14-I72)*0.3) ,1)) | M72: =IF(A72="","",ROUND((F72*0.45)+(J72*0.4)+((11-I72)*0.15),2)) | N72: =IFERROR(__xludf.DUMMYFUNCTION("IF(A72="""","""",RANK(M72,FILTER($M$11:$M$100,$A$11:$A$100<>""""),0))"),"") | O72: =IF(A72="","",IF(AND(F72>=8,J72<4),"DREAM",IF(J72>=8,"DO NOW",IF(J72>=6,"START PLANNING",IF(K72>=7,"BUILD TOWARDS","PARK"))))) | P72: =IF(A72="","",IF(J72>=9,"NONE",IF(G72<=H72,IF(G72<=11-I72,"MONEY","DIFFICULTY"),IF(H72<=11-I72,"TIME","DIFFICULTY")))) | R72: =IF(A72="","",MAX(0,D72-MAX(0,$E$4-$E$8))) | S72: =IF(A72="","",IF(R72=0,0,IF($E$6<=0,"NO SAVINGS",ROUNDUP(R72/$E$6,0)))) | T72: =IFERROR(__xludf.DUMMYFUNCTION("IF(A72="""","""",RANK(F72,FILTER($F$11:$F$100,$A$11:$A$100<>""""),0))"),"") | U72: =IFERROR(__xludf.DUMMYFUNCTION("IF(A72="""","""",RANK( (F72*0.5+K72*0.5), FILTER($F$11:$F$100*0.5+$K$11:$K$100*0.5,$A$11:$A$100<>""""), 0))"),"") | V72: =IFERROR(__xludf.DUMMYFUNCTION("IF(A72="""","""",RANK( (F72*0.45+L72*0.55), FILTER($F$11:$F$100*0.45+$L$11:$L$100*0.55,$A$11:$A$100<>""""), 0))"),"")
G73: =IF(A73="","",IF(D73<=0,10,ROUND(MAX(1,MIN(10,(MAX(0,$E$4-$E$8)/D73)*10)),1))) | H73: =IF(A73="","",IF(E73<=0,10,ROUND(MAX(1,MIN(10,10-(E73/MAX(1,$E$7)*10))),1))) | I73: =IF(A73="","",ROUND(MIN(10,MAX(1, ((11-G73)*0.45)+ ((11-H73)*0.25)+ (MIN(10,E73/2)*0.2)+ (IF(C73="NOW",1,IF(C73="THIS YEAR",2,IF(C73="1 YEAR",3,IF(C73="1-3 YEARS",5,IF(C73="3 YEARS",7,6)))))*0.1) )),1)) | J73: =IF(A73="","",ROUND((G73*0.4)+(H73*0.3)+((11-I73)*0.3),1)) | K73: =IF(A73="","",ROUND( (MAX(1,MIN(10,IF(D73<=0,10,(MAX(0,$E$4-$E$8)+($E$6*12))/D73*10)))*0.4) + (MIN(10,H73+0.5)*0.3) + (MIN(10,12-I73)*0.3) ,1)) | L73: =IF(A73="","",ROUND( (MAX(1,MIN(10,IF(D73<=0,10,(MAX(0,$E$4-$E$8)+($E$6*36))/D73*10)))*0.4) + (MIN(10,H73+1.5)*0.3) + (MIN(10,14-I73)*0.3) ,1)) | M73: =IF(A73="","",ROUND((F73*0.45)+(J73*0.4)+((11-I73)*0.15),2)) | N73: =IFERROR(__xludf.DUMMYFUNCTION("IF(A73="""","""",RANK(M73,FILTER($M$11:$M$100,$A$11:$A$100<>""""),0))"),"") | O73: =IF(A73="","",IF(AND(F73>=8,J73<4),"DREAM",IF(J73>=8,"DO NOW",IF(J73>=6,"START PLANNING",IF(K73>=7,"BUILD TOWARDS","PARK"))))) | P73: =IF(A73="","",IF(J73>=9,"NONE",IF(G73<=H73,IF(G73<=11-I73,"MONEY","DIFFICULTY"),IF(H73<=11-I73,"TIME","DIFFICULTY")))) | R73: =IF(A73="","",MAX(0,D73-MAX(0,$E$4-$E$8))) | S73: =IF(A73="","",IF(R73=0,0,IF($E$6<=0,"NO SAVINGS",ROUNDUP(R73/$E$6,0)))) | T73: =IFERROR(__xludf.DUMMYFUNCTION("IF(A73="""","""",RANK(F73,FILTER($F$11:$F$100,$A$11:$A$100<>""""),0))"),"") | U73: =IFERROR(__xludf.DUMMYFUNCTION("IF(A73="""","""",RANK( (F73*0.5+K73*0.5), FILTER($F$11:$F$100*0.5+$K$11:$K$100*0.5,$A$11:$A$100<>""""), 0))"),"") | V73: =IFERROR(__xludf.DUMMYFUNCTION("IF(A73="""","""",RANK( (F73*0.45+L73*0.55), FILTER($F$11:$F$100*0.45+$L$11:$L$100*0.55,$A$11:$A$100<>""""), 0))"),"")
G74: =IF(A74="","",IF(D74<=0,10,ROUND(MAX(1,MIN(10,(MAX(0,$E$4-$E$8)/D74)*10)),1))) | H74: =IF(A74="","",IF(E74<=0,10,ROUND(MAX(1,MIN(10,10-(E74/MAX(1,$E$7)*10))),1))) | I74: =IF(A74="","",ROUND(MIN(10,MAX(1, ((11-G74)*0.45)+ ((11-H74)*0.25)+ (MIN(10,E74/2)*0.2)+ (IF(C74="NOW",1,IF(C74="THIS YEAR",2,IF(C74="1 YEAR",3,IF(C74="1-3 YEARS",5,IF(C74="3 YEARS",7,6)))))*0.1) )),1)) | J74: =IF(A74="","",ROUND((G74*0.4)+(H74*0.3)+((11-I74)*0.3),1)) | K74: =IF(A74="","",ROUND( (MAX(1,MIN(10,IF(D74<=0,10,(MAX(0,$E$4-$E$8)+($E$6*12))/D74*10)))*0.4) + (MIN(10,H74+0.5)*0.3) + (MIN(10,12-I74)*0.3) ,1)) | L74: =IF(A74="","",ROUND( (MAX(1,MIN(10,IF(D74<=0,10,(MAX(0,$E$4-$E$8)+($E$6*36))/D74*10)))*0.4) + (MIN(10,H74+1.5)*0.3) + (MIN(10,14-I74)*0.3) ,1)) | M74: =IF(A74="","",ROUND((F74*0.45)+(J74*0.4)+((11-I74)*0.15),2)) | N74: =IFERROR(__xludf.DUMMYFUNCTION("IF(A74="""","""",RANK(M74,FILTER($M$11:$M$100,$A$11:$A$100<>""""),0))"),"") | O74: =IF(A74="","",IF(AND(F74>=8,J74<4),"DREAM",IF(J74>=8,"DO NOW",IF(J74>=6,"START PLANNING",IF(K74>=7,"BUILD TOWARDS","PARK"))))) | P74: =IF(A74="","",IF(J74>=9,"NONE",IF(G74<=H74,IF(G74<=11-I74,"MONEY","DIFFICULTY"),IF(H74<=11-I74,"TIME","DIFFICULTY")))) | R74: =IF(A74="","",MAX(0,D74-MAX(0,$E$4-$E$8))) | S74: =IF(A74="","",IF(R74=0,0,IF($E$6<=0,"NO SAVINGS",ROUNDUP(R74/$E$6,0)))) | T74: =IFERROR(__xludf.DUMMYFUNCTION("IF(A74="""","""",RANK(F74,FILTER($F$11:$F$100,$A$11:$A$100<>""""),0))"),"") | U74: =IFERROR(__xludf.DUMMYFUNCTION("IF(A74="""","""",RANK( (F74*0.5+K74*0.5), FILTER($F$11:$F$100*0.5+$K$11:$K$100*0.5,$A$11:$A$100<>""""), 0))"),"") | V74: =IFERROR(__xludf.DUMMYFUNCTION("IF(A74="""","""",RANK( (F74*0.45+L74*0.55), FILTER($F$11:$F$100*0.45+$L$11:$L$100*0.55,$A$11:$A$100<>""""), 0))"),"")
G75: =IF(A75="","",IF(D75<=0,10,ROUND(MAX(1,MIN(10,(MAX(0,$E$4-$E$8)/D75)*10)),1))) | H75: =IF(A75="","",IF(E75<=0,10,ROUND(MAX(1,MIN(10,10-(E75/MAX(1,$E$7)*10))),1))) | I75: =IF(A75="","",ROUND(MIN(10,MAX(1, ((11-G75)*0.45)+ ((11-H75)*0.25)+ (MIN(10,E75/2)*0.2)+ (IF(C75="NOW",1,IF(C75="THIS YEAR",2,IF(C75="1 YEAR",3,IF(C75="1-3 YEARS",5,IF(C75="3 YEARS",7,6)))))*0.1) )),1)) | J75: =IF(A75="","",ROUND((G75*0.4)+(H75*0.3)+((11-I75)*0.3),1)) | K75: =IF(A75="","",ROUND( (MAX(1,MIN(10,IF(D75<=0,10,(MAX(0,$E$4-$E$8)+($E$6*12))/D75*10)))*0.4) + (MIN(10,H75+0.5)*0.3) + (MIN(10,12-I75)*0.3) ,1)) | L75: =IF(A75="","",ROUND( (MAX(1,MIN(10,IF(D75<=0,10,(MAX(0,$E$4-$E$8)+($E$6*36))/D75*10)))*0.4) + (MIN(10,H75+1.5)*0.3) + (MIN(10,14-I75)*0.3) ,1)) | M75: =IF(A75="","",ROUND((F75*0.45)+(J75*0.4)+((11-I75)*0.15),2)) | N75: =IFERROR(__xludf.DUMMYFUNCTION("IF(A75="""","""",RANK(M75,FILTER($M$11:$M$100,$A$11:$A$100<>""""),0))"),"") | O75: =IF(A75="","",IF(AND(F75>=8,J75<4),"DREAM",IF(J75>=8,"DO NOW",IF(J75>=6,"START PLANNING",IF(K75>=7,"BUILD TOWARDS","PARK"))))) | P75: =IF(A75="","",IF(J75>=9,"NONE",IF(G75<=H75,IF(G75<=11-I75,"MONEY","DIFFICULTY"),IF(H75<=11-I75,"TIME","DIFFICULTY")))) | R75: =IF(A75="","",MAX(0,D75-MAX(0,$E$4-$E$8))) | S75: =IF(A75="","",IF(R75=0,0,IF($E$6<=0,"NO SAVINGS",ROUNDUP(R75/$E$6,0)))) | T75: =IFERROR(__xludf.DUMMYFUNCTION("IF(A75="""","""",RANK(F75,FILTER($F$11:$F$100,$A$11:$A$100<>""""),0))"),"") | U75: =IFERROR(__xludf.DUMMYFUNCTION("IF(A75="""","""",RANK( (F75*0.5+K75*0.5), FILTER($F$11:$F$100*0.5+$K$11:$K$100*0.5,$A$11:$A$100<>""""), 0))"),"") | V75: =IFERROR(__xludf.DUMMYFUNCTION("IF(A75="""","""",RANK( (F75*0.45+L75*0.55), FILTER($F$11:$F$100*0.45+$L$11:$L$100*0.55,$A$11:$A$100<>""""), 0))"),"")
G76: =IF(A76="","",IF(D76<=0,10,ROUND(MAX(1,MIN(10,(MAX(0,$E$4-$E$8)/D76)*10)),1))) | H76: =IF(A76="","",IF(E76<=0,10,ROUND(MAX(1,MIN(10,10-(E76/MAX(1,$E$7)*10))),1))) | I76: =IF(A76="","",ROUND(MIN(10,MAX(1, ((11-G76)*0.45)+ ((11-H76)*0.25)+ (MIN(10,E76/2)*0.2)+ (IF(C76="NOW",1,IF(C76="THIS YEAR",2,IF(C76="1 YEAR",3,IF(C76="1-3 YEARS",5,IF(C76="3 YEARS",7,6)))))*0.1) )),1)) | J76: =IF(A76="","",ROUND((G76*0.4)+(H76*0.3)+((11-I76)*0.3),1)) | K76: =IF(A76="","",ROUND( (MAX(1,MIN(10,IF(D76<=0,10,(MAX(0,$E$4-$E$8)+($E$6*12))/D76*10)))*0.4) + (MIN(10,H76+0.5)*0.3) + (MIN(10,12-I76)*0.3) ,1)) | L76: =IF(A76="","",ROUND( (MAX(1,MIN(10,IF(D76<=0,10,(MAX(0,$E$4-$E$8)+($E$6*36))/D76*10)))*0.4) + (MIN(10,H76+1.5)*0.3) + (MIN(10,14-I76)*0.3) ,1)) | M76: =IF(A76="","",ROUND((F76*0.45)+(J76*0.4)+((11-I76)*0.15),2)) | N76: =IFERROR(__xludf.DUMMYFUNCTION("IF(A76="""","""",RANK(M76,FILTER($M$11:$M$100,$A$11:$A$100<>""""),0))"),"") | O76: =IF(A76="","",IF(AND(F76>=8,J76<4),"DREAM",IF(J76>=8,"DO NOW",IF(J76>=6,"START PLANNING",IF(K76>=7,"BUILD TOWARDS","PARK"))))) | P76: =IF(A76="","",IF(J76>=9,"NONE",IF(G76<=H76,IF(G76<=11-I76,"MONEY","DIFFICULTY"),IF(H76<=11-I76,"TIME","DIFFICULTY")))) | R76: =IF(A76="","",MAX(0,D76-MAX(0,$E$4-$E$8))) | S76: =IF(A76="","",IF(R76=0,0,IF($E$6<=0,"NO SAVINGS",ROUNDUP(R76/$E$6,0)))) | T76: =IFERROR(__xludf.DUMMYFUNCTION("IF(A76="""","""",RANK(F76,FILTER($F$11:$F$100,$A$11:$A$100<>""""),0))"),"") | U76: =IFERROR(__xludf.DUMMYFUNCTION("IF(A76="""","""",RANK( (F76*0.5+K76*0.5), FILTER($F$11:$F$100*0.5+$K$11:$K$100*0.5,$A$11:$A$100<>""""), 0))"),"") | V76: =IFERROR(__xludf.DUMMYFUNCTION("IF(A76="""","""",RANK( (F76*0.45+L76*0.55), FILTER($F$11:$F$100*0.45+$L$11:$L$100*0.55,$A$11:$A$100<>""""), 0))"),"")
G77: =IF(A77="","",IF(D77<=0,10,ROUND(MAX(1,MIN(10,(MAX(0,$E$4-$E$8)/D77)*10)),1))) | H77: =IF(A77="","",IF(E77<=0,10,ROUND(MAX(1,MIN(10,10-(E77/MAX(1,$E$7)*10))),1))) | I77: =IF(A77="","",ROUND(MIN(10,MAX(1, ((11-G77)*0.45)+ ((11-H77)*0.25)+ (MIN(10,E77/2)*0.2)+ (IF(C77="NOW",1,IF(C77="THIS YEAR",2,IF(C77="1 YEAR",3,IF(C77="1-3 YEARS",5,IF(C77="3 YEARS",7,6)))))*0.1) )),1)) | J77: =IF(A77="","",ROUND((G77*0.4)+(H77*0.3)+((11-I77)*0.3),1)) | K77: =IF(A77="","",ROUND( (MAX(1,MIN(10,IF(D77<=0,10,(MAX(0,$E$4-$E$8)+($E$6*12))/D77*10)))*0.4) + (MIN(10,H77+0.5)*0.3) + (MIN(10,12-I77)*0.3) ,1)) | L77: =IF(A77="","",ROUND( (MAX(1,MIN(10,IF(D77<=0,10,(MAX(0,$E$4-$E$8)+($E$6*36))/D77*10)))*0.4) + (MIN(10,H77+1.5)*0.3) + (MIN(10,14-I77)*0.3) ,1)) | M77: =IF(A77="","",ROUND((F77*0.45)+(J77*0.4)+((11-I77)*0.15),2)) | N77: =IFERROR(__xludf.DUMMYFUNCTION("IF(A77="""","""",RANK(M77,FILTER($M$11:$M$100,$A$11:$A$100<>""""),0))"),"") | O77: =IF(A77="","",IF(AND(F77>=8,J77<4),"DREAM",IF(J77>=8,"DO NOW",IF(J77>=6,"START PLANNING",IF(K77>=7,"BUILD TOWARDS","PARK"))))) | P77: =IF(A77="","",IF(J77>=9,"NONE",IF(G77<=H77,IF(G77<=11-I77,"MONEY","DIFFICULTY"),IF(H77<=11-I77,"TIME","DIFFICULTY")))) | R77: =IF(A77="","",MAX(0,D77-MAX(0,$E$4-$E$8))) | S77: =IF(A77="","",IF(R77=0,0,IF($E$6<=0,"NO SAVINGS",ROUNDUP(R77/$E$6,0)))) | T77: =IFERROR(__xludf.DUMMYFUNCTION("IF(A77="""","""",RANK(F77,FILTER($F$11:$F$100,$A$11:$A$100<>""""),0))"),"") | U77: =IFERROR(__xludf.DUMMYFUNCTION("IF(A77="""","""",RANK( (F77*0.5+K77*0.5), FILTER($F$11:$F$100*0.5+$K$11:$K$100*0.5,$A$11:$A$100<>""""), 0))"),"") | V77: =IFERROR(__xludf.DUMMYFUNCTION("IF(A77="""","""",RANK( (F77*0.45+L77*0.55), FILTER($F$11:$F$100*0.45+$L$11:$L$100*0.55,$A$11:$A$100<>""""), 0))"),"")
G78: =IF(A78="","",IF(D78<=0,10,ROUND(MAX(1,MIN(10,(MAX(0,$E$4-$E$8)/D78)*10)),1))) | H78: =IF(A78="","",IF(E78<=0,10,ROUND(MAX(1,MIN(10,10-(E78/MAX(1,$E$7)*10))),1))) | I78: =IF(A78="","",ROUND(MIN(10,MAX(1, ((11-G78)*0.45)+ ((11-H78)*0.25)+ (MIN(10,E78/2)*0.2)+ (IF(C78="NOW",1,IF(C78="THIS YEAR",2,IF(C78="1 YEAR",3,IF(C78="1-3 YEARS",5,IF(C78="3 YEARS",7,6)))))*0.1) )),1)) | J78: =IF(A78="","",ROUND((G78*0.4)+(H78*0.3)+((11-I78)*0.3),1)) | K78: =IF(A78="","",ROUND( (MAX(1,MIN(10,IF(D78<=0,10,(MAX(0,$E$4-$E$8)+($E$6*12))/D78*10)))*0.4) + (MIN(10,H78+0.5)*0.3) + (MIN(10,12-I78)*0.3) ,1)) | L78: =IF(A78="","",ROUND( (MAX(1,MIN(10,IF(D78<=0,10,(MAX(0,$E$4-$E$8)+($E$6*36))/D78*10)))*0.4) + (MIN(10,H78+1.5)*0.3) + (MIN(10,14-I78)*0.3) ,1)) | M78: =IF(A78="","",ROUND((F78*0.45)+(J78*0.4)+((11-I78)*0.15),2)) | N78: =IFERROR(__xludf.DUMMYFUNCTION("IF(A78="""","""",RANK(M78,FILTER($M$11:$M$100,$A$11:$A$100<>""""),0))"),"") | O78: =IF(A78="","",IF(AND(F78>=8,J78<4),"DREAM",IF(J78>=8,"DO NOW",IF(J78>=6,"START PLANNING",IF(K78>=7,"BUILD TOWARDS","PARK"))))) | P78: =IF(A78="","",IF(J78>=9,"NONE",IF(G78<=H78,IF(G78<=11-I78,"MONEY","DIFFICULTY"),IF(H78<=11-I78,"TIME","DIFFICULTY")))) | R78: =IF(A78="","",MAX(0,D78-MAX(0,$E$4-$E$8))) | S78: =IF(A78="","",IF(R78=0,0,IF($E$6<=0,"NO SAVINGS",ROUNDUP(R78/$E$6,0)))) | T78: =IFERROR(__xludf.DUMMYFUNCTION("IF(A78="""","""",RANK(F78,FILTER($F$11:$F$100,$A$11:$A$100<>""""),0))"),"") | U78: =IFERROR(__xludf.DUMMYFUNCTION("IF(A78="""","""",RANK( (F78*0.5+K78*0.5), FILTER($F$11:$F$100*0.5+$K$11:$K$100*0.5,$A$11:$A$100<>""""), 0))"),"") | V78: =IFERROR(__xludf.DUMMYFUNCTION("IF(A78="""","""",RANK( (F78*0.45+L78*0.55), FILTER($F$11:$F$100*0.45+$L$11:$L$100*0.55,$A$11:$A$100<>""""), 0))"),"")
G79: =IF(A79="","",IF(D79<=0,10,ROUND(MAX(1,MIN(10,(MAX(0,$E$4-$E$8)/D79)*10)),1))) | H79: =IF(A79="","",IF(E79<=0,10,ROUND(MAX(1,MIN(10,10-(E79/MAX(1,$E$7)*10))),1))) | I79: =IF(A79="","",ROUND(MIN(10,MAX(1, ((11-G79)*0.45)+ ((11-H79)*0.25)+ (MIN(10,E79/2)*0.2)+ (IF(C79="NOW",1,IF(C79="THIS YEAR",2,IF(C79="1 YEAR",3,IF(C79="1-3 YEARS",5,IF(C79="3 YEARS",7,6)))))*0.1) )),1)) | J79: =IF(A79="","",ROUND((G79*0.4)+(H79*0.3)+((11-I79)*0.3),1)) | K79: =IF(A79="","",ROUND( (MAX(1,MIN(10,IF(D79<=0,10,(MAX(0,$E$4-$E$8)+($E$6*12))/D79*10)))*0.4) + (MIN(10,H79+0.5)*0.3) + (MIN(10,12-I79)*0.3) ,1)) | L79: =IF(A79="","",ROUND( (MAX(1,MIN(10,IF(D79<=0,10,(MAX(0,$E$4-$E$8)+($E$6*36))/D79*10)))*0.4) + (MIN(10,H79+1.5)*0.3) + (MIN(10,14-I79)*0.3) ,1)) | M79: =IF(A79="","",ROUND((F79*0.45)+(J79*0.4)+((11-I79)*0.15),2)) | N79: =IFERROR(__xludf.DUMMYFUNCTION("IF(A79="""","""",RANK(M79,FILTER($M$11:$M$100,$A$11:$A$100<>""""),0))"),"") | O79: =IF(A79="","",IF(AND(F79>=8,J79<4),"DREAM",IF(J79>=8,"DO NOW",IF(J79>=6,"START PLANNING",IF(K79>=7,"BUILD TOWARDS","PARK"))))) | P79: =IF(A79="","",IF(J79>=9,"NONE",IF(G79<=H79,IF(G79<=11-I79,"MONEY","DIFFICULTY"),IF(H79<=11-I79,"TIME","DIFFICULTY")))) | R79: =IF(A79="","",MAX(0,D79-MAX(0,$E$4-$E$8))) | S79: =IF(A79="","",IF(R79=0,0,IF($E$6<=0,"NO SAVINGS",ROUNDUP(R79/$E$6,0)))) | T79: =IFERROR(__xludf.DUMMYFUNCTION("IF(A79="""","""",RANK(F79,FILTER($F$11:$F$100,$A$11:$A$100<>""""),0))"),"") | U79: =IFERROR(__xludf.DUMMYFUNCTION("IF(A79="""","""",RANK( (F79*0.5+K79*0.5), FILTER($F$11:$F$100*0.5+$K$11:$K$100*0.5,$A$11:$A$100<>""""), 0))"),"") | V79: =IFERROR(__xludf.DUMMYFUNCTION("IF(A79="""","""",RANK( (F79*0.45+L79*0.55), FILTER($F$11:$F$100*0.45+$L$11:$L$100*0.55,$A$11:$A$100<>""""), 0))"),"")
G80: =IF(A80="","",IF(D80<=0,10,ROUND(MAX(1,MIN(10,(MAX(0,$E$4-$E$8)/D80)*10)),1))) | H80: =IF(A80="","",IF(E80<=0,10,ROUND(MAX(1,MIN(10,10-(E80/MAX(1,$E$7)*10))),1))) | I80: =IF(A80="","",ROUND(MIN(10,MAX(1, ((11-G80)*0.45)+ ((11-H80)*0.25)+ (MIN(10,E80/2)*0.2)+ (IF(C80="NOW",1,IF(C80="THIS YEAR",2,IF(C80="1 YEAR",3,IF(C80="1-3 YEARS",5,IF(C80="3 YEARS",7,6)))))*0.1) )),1)) | J80: =IF(A80="","",ROUND((G80*0.4)+(H80*0.3)+((11-I80)*0.3),1)) | K80: =IF(A80="","",ROUND( (MAX(1,MIN(10,IF(D80<=0,10,(MAX(0,$E$4-$E$8)+($E$6*12))/D80*10)))*0.4) + (MIN(10,H80+0.5)*0.3) + (MIN(10,12-I80)*0.3) ,1)) | L80: =IF(A80="","",ROUND( (MAX(1,MIN(10,IF(D80<=0,10,(MAX(0,$E$4-$E$8)+($E$6*36))/D80*10)))*0.4) + (MIN(10,H80+1.5)*0.3) + (MIN(10,14-I80)*0.3) ,1)) | M80: =IF(A80="","",ROUND((F80*0.45)+(J80*0.4)+((11-I80)*0.15),2)) | N80: =IFERROR(__xludf.DUMMYFUNCTION("IF(A80="""","""",RANK(M80,FILTER($M$11:$M$100,$A$11:$A$100<>""""),0))"),"") | O80: =IF(A80="","",IF(AND(F80>=8,J80<4),"DREAM",IF(J80>=8,"DO NOW",IF(J80>=6,"START PLANNING",IF(K80>=7,"BUILD TOWARDS","PARK"))))) | P80: =IF(A80="","",IF(J80>=9,"NONE",IF(G80<=H80,IF(G80<=11-I80,"MONEY","DIFFICULTY"),IF(H80<=11-I80,"TIME","DIFFICULTY")))) | R80: =IF(A80="","",MAX(0,D80-MAX(0,$E$4-$E$8))) | S80: =IF(A80="","",IF(R80=0,0,IF($E$6<=0,"NO SAVINGS",ROUNDUP(R80/$E$6,0)))) | T80: =IFERROR(__xludf.DUMMYFUNCTION("IF(A80="""","""",RANK(F80,FILTER($F$11:$F$100,$A$11:$A$100<>""""),0))"),"") | U80: =IFERROR(__xludf.DUMMYFUNCTION("IF(A80="""","""",RANK( (F80*0.5+K80*0.5), FILTER($F$11:$F$100*0.5+$K$11:$K$100*0.5,$A$11:$A$100<>""""), 0))"),"") | V80: =IFERROR(__xludf.DUMMYFUNCTION("IF(A80="""","""",RANK( (F80*0.45+L80*0.55), FILTER($F$11:$F$100*0.45+$L$11:$L$100*0.55,$A$11:$A$100<>""""), 0))"),"")
G81: =IF(A81="","",IF(D81<=0,10,ROUND(MAX(1,MIN(10,(MAX(0,$E$4-$E$8)/D81)*10)),1))) | H81: =IF(A81="","",IF(E81<=0,10,ROUND(MAX(1,MIN(10,10-(E81/MAX(1,$E$7)*10))),1))) | I81: =IF(A81="","",ROUND(MIN(10,MAX(1, ((11-G81)*0.45)+ ((11-H81)*0.25)+ (MIN(10,E81/2)*0.2)+ (IF(C81="NOW",1,IF(C81="THIS YEAR",2,IF(C81="1 YEAR",3,IF(C81="1-3 YEARS",5,IF(C81="3 YEARS",7,6)))))*0.1) )),1)) | J81: =IF(A81="","",ROUND((G81*0.4)+(H81*0.3)+((11-I81)*0.3),1)) | K81: =IF(A81="","",ROUND( (MAX(1,MIN(10,IF(D81<=0,10,(MAX(0,$E$4-$E$8)+($E$6*12))/D81*10)))*0.4) + (MIN(10,H81+0.5)*0.3) + (MIN(10,12-I81)*0.3) ,1)) | L81: =IF(A81="","",ROUND( (MAX(1,MIN(10,IF(D81<=0,10,(MAX(0,$E$4-$E$8)+($E$6*36))/D81*10)))*0.4) + (MIN(10,H81+1.5)*0.3) + (MIN(10,14-I81)*0.3) ,1)) | M81: =IF(A81="","",ROUND((F81*0.45)+(J81*0.4)+((11-I81)*0.15),2)) | N81: =IFERROR(__xludf.DUMMYFUNCTION("IF(A81="""","""",RANK(M81,FILTER($M$11:$M$100,$A$11:$A$100<>""""),0))"),"") | O81: =IF(A81="","",IF(AND(F81>=8,J81<4),"DREAM",IF(J81>=8,"DO NOW",IF(J81>=6,"START PLANNING",IF(K81>=7,"BUILD TOWARDS","PARK"))))) | P81: =IF(A81="","",IF(J81>=9,"NONE",IF(G81<=H81,IF(G81<=11-I81,"MONEY","DIFFICULTY"),IF(H81<=11-I81,"TIME","DIFFICULTY")))) | R81: =IF(A81="","",MAX(0,D81-MAX(0,$E$4-$E$8))) | S81: =IF(A81="","",IF(R81=0,0,IF($E$6<=0,"NO SAVINGS",ROUNDUP(R81/$E$6,0)))) | T81: =IFERROR(__xludf.DUMMYFUNCTION("IF(A81="""","""",RANK(F81,FILTER($F$11:$F$100,$A$11:$A$100<>""""),0))"),"") | U81: =IFERROR(__xludf.DUMMYFUNCTION("IF(A81="""","""",RANK( (F81*0.5+K81*0.5), FILTER($F$11:$F$100*0.5+$K$11:$K$100*0.5,$A$11:$A$100<>""""), 0))"),"") | V81: =IFERROR(__xludf.DUMMYFUNCTION("IF(A81="""","""",RANK( (F81*0.45+L81*0.55), FILTER($F$11:$F$100*0.45+$L$11:$L$100*0.55,$A$11:$A$100<>""""), 0))"),"")
G82: =IF(A82="","",IF(D82<=0,10,ROUND(MAX(1,MIN(10,(MAX(0,$E$4-$E$8)/D82)*10)),1))) | H82: =IF(A82="","",IF(E82<=0,10,ROUND(MAX(1,MIN(10,10-(E82/MAX(1,$E$7)*10))),1))) | I82: =IF(A82="","",ROUND(MIN(10,MAX(1, ((11-G82)*0.45)+ ((11-H82)*0.25)+ (MIN(10,E82/2)*0.2)+ (IF(C82="NOW",1,IF(C82="THIS YEAR",2,IF(C82="1 YEAR",3,IF(C82="1-3 YEARS",5,IF(C82="3 YEARS",7,6)))))*0.1) )),1)) | J82: =IF(A82="","",ROUND((G82*0.4)+(H82*0.3)+((11-I82)*0.3),1)) | K82: =IF(A82="","",ROUND( (MAX(1,MIN(10,IF(D82<=0,10,(MAX(0,$E$4-$E$8)+($E$6*12))/D82*10)))*0.4) + (MIN(10,H82+0.5)*0.3) + (MIN(10,12-I82)*0.3) ,1)) | L82: =IF(A82="","",ROUND( (MAX(1,MIN(10,IF(D82<=0,10,(MAX(0,$E$4-$E$8)+($E$6*36))/D82*10)))*0.4) + (MIN(10,H82+1.5)*0.3) + (MIN(10,14-I82)*0.3) ,1)) | M82: =IF(A82="","",ROUND((F82*0.45)+(J82*0.4)+((11-I82)*0.15),2)) | N82: =IFERROR(__xludf.DUMMYFUNCTION("IF(A82="""","""",RANK(M82,FILTER($M$11:$M$100,$A$11:$A$100<>""""),0))"),"") | O82: =IF(A82="","",IF(AND(F82>=8,J82<4),"DREAM",IF(J82>=8,"DO NOW",IF(J82>=6,"START PLANNING",IF(K82>=7,"BUILD TOWARDS","PARK"))))) | P82: =IF(A82="","",IF(J82>=9,"NONE",IF(G82<=H82,IF(G82<=11-I82,"MONEY","DIFFICULTY"),IF(H82<=11-I82,"TIME","DIFFICULTY")))) | R82: =IF(A82="","",MAX(0,D82-MAX(0,$E$4-$E$8))) | S82: =IF(A82="","",IF(R82=0,0,IF($E$6<=0,"NO SAVINGS",ROUNDUP(R82/$E$6,0)))) | T82: =IFERROR(__xludf.DUMMYFUNCTION("IF(A82="""","""",RANK(F82,FILTER($F$11:$F$100,$A$11:$A$100<>""""),0))"),"") | U82: =IFERROR(__xludf.DUMMYFUNCTION("IF(A82="""","""",RANK( (F82*0.5+K82*0.5), FILTER($F$11:$F$100*0.5+$K$11:$K$100*0.5,$A$11:$A$100<>""""), 0))"),"") | V82: =IFERROR(__xludf.DUMMYFUNCTION("IF(A82="""","""",RANK( (F82*0.45+L82*0.55), FILTER($F$11:$F$100*0.45+$L$11:$L$100*0.55,$A$11:$A$100<>""""), 0))"),"")
G83: =IF(A83="","",IF(D83<=0,10,ROUND(MAX(1,MIN(10,(MAX(0,$E$4-$E$8)/D83)*10)),1))) | H83: =IF(A83="","",IF(E83<=0,10,ROUND(MAX(1,MIN(10,10-(E83/MAX(1,$E$7)*10))),1))) | I83: =IF(A83="","",ROUND(MAX(1,MIN(10,(11-G83)*0.4+(11-H83)*0.4+(E83/10*10)*0.2)),1)) | J83: =IF(A83="","",ROUND((G83*0.4)+(H83*0.3)+((11-I83)*0.3),1)) | K83: =IF(A83="","",ROUND( (MAX(1,MIN(10,IF(D83<=0,10,(MAX(0,$E$4-$E$8)+($E$6*12))/D83*10)))*0.4) + (MIN(10,H83+0.5)*0.3) + (MIN(10,12-I83)*0.3) ,1)) | L83: =IF(A83="","",ROUND( (MAX(1,MIN(10,IF(D83<=0,10,(MAX(0,$E$4-$E$8)+($E$6*36))/D83*10)))*0.4) + (MIN(10,H83+1.5)*0.3) + (MIN(10,14-I83)*0.3) ,1)) | M83: =IF(A83="","",ROUND((F83*0.45)+(J83*0.4)+((11-I83)*0.15),2)) | N83: =IFERROR(__xludf.DUMMYFUNCTION("IF(A83="""","""",RANK(M83,FILTER($M$11:$M$100,$A$11:$A$100<>""""),0))"),"") | O83: =IF(A83="","",IF(AND(F83>=8,J83<4),"DREAM",IF(J83>=8,"DO NOW",IF(J83>=6,"START PLANNING",IF(K83>=7,"BUILD TOWARDS","PARK"))))) | P83: =IF(A83="","",IF(J83>=9,"NONE",IF(G83<=H83,IF(G83<=11-I83,"MONEY","DIFFICULTY"),IF(H83<=11-I83,"TIME","DIFFICULTY")))) | R83: =IF(A83="","",MAX(0,D83-MAX(0,$E$4-$E$8))) | S83: =IF(A83="","",IF(R83=0,0,IF($E$6<=0,"NO SAVINGS",ROUNDUP(R83/$E$6,0)))) | T83: =IFERROR(__xludf.DUMMYFUNCTION("IF(A83="""","""",RANK(F83,FILTER($F$11:$F$100,$A$11:$A$100<>""""),0))"),"") | U83: =IFERROR(__xludf.DUMMYFUNCTION("IF(A83="""","""",RANK( (F83*0.5+K83*0.5), FILTER($F$11:$F$100*0.5+$K$11:$K$100*0.5,$A$11:$A$100<>""""), 0))"),"") | V83: =IFERROR(__xludf.DUMMYFUNCTION("IF(A83="""","""",RANK( (F83*0.45+L83*0.55), FILTER($F$11:$F$100*0.45+$L$11:$L$100*0.55,$A$11:$A$100<>""""), 0))"),"")
G84: =IF(A84="","",IF(D84<=0,10,ROUND(MAX(1,MIN(10,(MAX(0,$E$4-$E$8)/D84)*10)),1))) | H84: =IF(A84="","",IF(E84<=0,10,ROUND(MAX(1,MIN(10,10-(E84/MAX(1,$E$7)*10))),1))) | I84: =IF(A84="","",ROUND(MAX(1,MIN(10,(11-G84)*0.4+(11-H84)*0.4+(E84/10*10)*0.2)),1)) | J84: =IF(A84="","",ROUND((G84*0.4)+(H84*0.3)+((11-I84)*0.3),1)) | K84: =IF(A84="","",ROUND( (MAX(1,MIN(10,IF(D84<=0,10,(MAX(0,$E$4-$E$8)+($E$6*12))/D84*10)))*0.4) + (MIN(10,H84+0.5)*0.3) + (MIN(10,12-I84)*0.3) ,1)) | L84: =IF(A84="","",ROUND( (MAX(1,MIN(10,IF(D84<=0,10,(MAX(0,$E$4-$E$8)+($E$6*36))/D84*10)))*0.4) + (MIN(10,H84+1.5)*0.3) + (MIN(10,14-I84)*0.3) ,1)) | M84: =IF(A84="","",ROUND((F84*0.45)+(J84*0.4)+((11-I84)*0.15),2)) | N84: =IFERROR(__xludf.DUMMYFUNCTION("IF(A84="""","""",RANK(M84,FILTER($M$11:$M$100,$A$11:$A$100<>""""),0))"),"") | O84: =IF(A84="","",IF(AND(F84>=8,J84<4),"DREAM",IF(J84>=8,"DO NOW",IF(J84>=6,"START PLANNING",IF(K84>=7,"BUILD TOWARDS","PARK"))))) | P84: =IF(A84="","",IF(J84>=9,"NONE",IF(G84<=H84,IF(G84<=11-I84,"MONEY","DIFFICULTY"),IF(H84<=11-I84,"TIME","DIFFICULTY")))) | R84: =IF(A84="","",MAX(0,D84-MAX(0,$E$4-$E$8))) | S84: =IF(A84="","",IF(R84=0,0,IF($E$6<=0,"NO SAVINGS",ROUNDUP(R84/$E$6,0)))) | T84: =IFERROR(__xludf.DUMMYFUNCTION("IF(A84="""","""",RANK(F84,FILTER($F$11:$F$100,$A$11:$A$100<>""""),0))"),"") | U84: =IFERROR(__xludf.DUMMYFUNCTION("IF(A84="""","""",RANK( (F84*0.5+K84*0.5), FILTER($F$11:$F$100*0.5+$K$11:$K$100*0.5,$A$11:$A$100<>""""), 0))"),"") | V84: =IFERROR(__xludf.DUMMYFUNCTION("IF(A84="""","""",RANK( (F84*0.45+L84*0.55), FILTER($F$11:$F$100*0.45+$L$11:$L$100*0.55,$A$11:$A$100<>""""), 0))"),"")
G85: =IF(A85="","",IF(D85<=0,10,ROUND(MAX(1,MIN(10,(MAX(0,$E$4-$E$8)/D85)*10)),1))) | H85: =IF(A85="","",IF(E85<=0,10,ROUND(MAX(1,MIN(10,10-(E85/MAX(1,$E$7)*10))),1))) | I85: =IF(A85="","",ROUND(MAX(1,MIN(10,(11-G85)*0.4+(11-H85)*0.4+(E85/10*10)*0.2)),1)) | J85: =IF(A85="","",ROUND((G85*0.4)+(H85*0.3)+((11-I85)*0.3),1)) | K85: =IF(A85="","",ROUND( (MAX(1,MIN(10,IF(D85<=0,10,(MAX(0,$E$4-$E$8)+($E$6*12))/D85*10)))*0.4) + (MIN(10,H85+0.5)*0.3) + (MIN(10,12-I85)*0.3) ,1)) | L85: =IF(A85="","",ROUND( (MAX(1,MIN(10,IF(D85<=0,10,(MAX(0,$E$4-$E$8)+($E$6*36))/D85*10)))*0.4) + (MIN(10,H85+1.5)*0.3) + (MIN(10,14-I85)*0.3) ,1)) | M85: =IF(A85="","",ROUND((F85*0.45)+(J85*0.4)+((11-I85)*0.15),2)) | N85: =IFERROR(__xludf.DUMMYFUNCTION("IF(A85="""","""",RANK(M85,FILTER($M$11:$M$100,$A$11:$A$100<>""""),0))"),"") | O85: =IF(A85="","",IF(AND(F85>=8,J85<4),"DREAM",IF(J85>=8,"DO NOW",IF(J85>=6,"START PLANNING",IF(K85>=7,"BUILD TOWARDS","PARK"))))) | P85: =IF(A85="","",IF(J85>=9,"NONE",IF(G85<=H85,IF(G85<=11-I85,"MONEY","DIFFICULTY"),IF(H85<=11-I85,"TIME","DIFFICULTY")))) | R85: =IF(A85="","",MAX(0,D85-MAX(0,$E$4-$E$8))) | S85: =IF(A85="","",IF(R85=0,0,IF($E$6<=0,"NO SAVINGS",ROUNDUP(R85/$E$6,0)))) | T85: =IFERROR(__xludf.DUMMYFUNCTION("IF(A85="""","""",RANK(F85,FILTER($F$11:$F$100,$A$11:$A$100<>""""),0))"),"") | U85: =IFERROR(__xludf.DUMMYFUNCTION("IF(A85="""","""",RANK( (F85*0.5+K85*0.5), FILTER($F$11:$F$100*0.5+$K$11:$K$100*0.5,$A$11:$A$100<>""""), 0))"),"") | V85: =IFERROR(__xludf.DUMMYFUNCTION("IF(A85="""","""",RANK( (F85*0.45+L85*0.55), FILTER($F$11:$F$100*0.45+$L$11:$L$100*0.55,$A$11:$A$100<>""""), 0))"),"")
G86: =IF(A86="","",IF(D86<=0,10,ROUND(MAX(1,MIN(10,(MAX(0,$E$4-$E$8)/D86)*10)),1))) | H86: =IF(A86="","",IF(E86<=0,10,ROUND(MAX(1,MIN(10,10-(E86/MAX(1,$E$7)*10))),1))) | I86: =IF(A86="","",ROUND(MAX(1,MIN(10,(11-G86)*0.4+(11-H86)*0.4+(E86/10*10)*0.2)),1)) | J86: =IF(A86="","",ROUND((G86*0.4)+(H86*0.3)+((11-I86)*0.3),1)) | K86: =IF(A86="","",ROUND( (MAX(1,MIN(10,IF(D86<=0,10,(MAX(0,$E$4-$E$8)+($E$6*12))/D86*10)))*0.4) + (MIN(10,H86+0.5)*0.3) + (MIN(10,12-I86)*0.3) ,1)) | L86: =IF(A86="","",ROUND( (MAX(1,MIN(10,IF(D86<=0,10,(MAX(0,$E$4-$E$8)+($E$6*36))/D86*10)))*0.4) + (MIN(10,H86+1.5)*0.3) + (MIN(10,14-I86)*0.3) ,1)) | M86: =IF(A86="","",ROUND((F86*0.45)+(J86*0.4)+((11-I86)*0.15),2)) | N86: =IFERROR(__xludf.DUMMYFUNCTION("IF(A86="""","""",RANK(M86,FILTER($M$11:$M$100,$A$11:$A$100<>""""),0))"),"") | O86: =IF(A86="","",IF(AND(F86>=8,J86<4),"DREAM",IF(J86>=8,"DO NOW",IF(J86>=6,"START PLANNING",IF(K86>=7,"BUILD TOWARDS","PARK"))))) | P86: =IF(A86="","",IF(J86>=9,"NONE",IF(G86<=H86,IF(G86<=11-I86,"MONEY","DIFFICULTY"),IF(H86<=11-I86,"TIME","DIFFICULTY")))) | R86: =IF(A86="","",MAX(0,D86-MAX(0,$E$4-$E$8))) | S86: =IF(A86="","",IF(R86=0,0,IF($E$6<=0,"NO SAVINGS",ROUNDUP(R86/$E$6,0)))) | T86: =IFERROR(__xludf.DUMMYFUNCTION("IF(A86="""","""",RANK(F86,FILTER($F$11:$F$100,$A$11:$A$100<>""""),0))"),"") | U86: =IFERROR(__xludf.DUMMYFUNCTION("IF(A86="""","""",RANK( (F86*0.5+K86*0.5), FILTER($F$11:$F$100*0.5+$K$11:$K$100*0.5,$A$11:$A$100<>""""), 0))"),"") | V86: =IFERROR(__xludf.DUMMYFUNCTION("IF(A86="""","""",RANK( (F86*0.45+L86*0.55), FILTER($F$11:$F$100*0.45+$L$11:$L$100*0.55,$A$11:$A$100<>""""), 0))"),"")
G87: =IF(A87="","",MAX(1,MIN(10,ROUND(10-(MAX(0,D87-$E$4)/MAX(1,$E$6))*0.5,0)))) | H87: =IF(A87="","",IF(E87<=0,10,ROUND(MAX(1,MIN(10,10-(E87/MAX(1,$E$7)*10))),1))) | I87: =IF(A87="","",ROUND(MAX(1,MIN(10,(11-G87)*0.4+(11-H87)*0.4+(E87/10*10)*0.2)),1)) | J87: =IF(A87="","",ROUND((G87*0.4)+(H87*0.3)+((11-I87)*0.3),1)) | K87: =IF(A87="","",ROUND( (MAX(1,MIN(10,IF(D87<=0,10,(MAX(0,$E$4-$E$8)+($E$6*12))/D87*10)))*0.4) + (MIN(10,H87+0.5)*0.3) + (MIN(10,12-I87)*0.3) ,1)) | L87: =IF(A87="","",ROUND( (MAX(1,MIN(10,IF(D87<=0,10,(MAX(0,$E$4-$E$8)+($E$6*36))/D87*10)))*0.4) + (MIN(10,H87+1.5)*0.3) + (MIN(10,14-I87)*0.3) ,1)) | M87: =IF(A87="","",ROUND((F87*0.45)+(J87*0.4)+((11-I87)*0.15),2)) | N87: =IFERROR(__xludf.DUMMYFUNCTION("IF(A87="""","""",RANK(M87,FILTER($M$11:$M$100,$A$11:$A$100<>""""),0))"),"") | O87: =IF(A87="","",IF(AND(F87>=8,J87<4),"DREAM",IF(J87>=8,"DO NOW",IF(J87>=6,"START PLANNING",IF(K87>=7,"BUILD TOWARDS","PARK"))))) | P87: =IF(A87="","",IF(J87>=9,"NONE",IF(G87<=H87,IF(G87<=11-I87,"MONEY","DIFFICULTY"),IF(H87<=11-I87,"TIME","DIFFICULTY")))) | R87: =IF(A87="","",MAX(0,D87-MAX(0,$E$4-$E$8))) | S87: =IF(A87="","",IF(R87=0,0,IF($E$6<=0,"NO SAVINGS",ROUNDUP(R87/$E$6,0)))) | T87: =IFERROR(__xludf.DUMMYFUNCTION("IF(A87="""","""",RANK(F87,FILTER($F$11:$F$100,$A$11:$A$100<>""""),0))"),"") | U87: =IFERROR(__xludf.DUMMYFUNCTION("IF(A87="""","""",RANK( (F87*0.5+K87*0.5), FILTER($F$11:$F$100*0.5+$K$11:$K$100*0.5,$A$11:$A$100<>""""), 0))"),"") | V87: =IFERROR(__xludf.DUMMYFUNCTION("IF(A87="""","""",RANK( (F87*0.45+L87*0.55), FILTER($F$11:$F$100*0.45+$L$11:$L$100*0.55,$A$11:$A$100<>""""), 0))"),"")
G88: =IF(A88="","",MAX(1,MIN(10,ROUND(10-(MAX(0,D88-$E$4)/MAX(1,$E$6))*0.5,0)))) | H88: =IF(A88="","",IF(E88<=0,10,ROUND(MAX(1,MIN(10,10-(E88/MAX(1,$E$7)*10))),1))) | I88: =IF(A88="","",ROUND(MAX(1,MIN(10,(11-G88)*0.4+(11-H88)*0.4+(E88/10*10)*0.2)),1)) | J88: =IF(A88="","",ROUND((G88*0.4)+(H88*0.3)+((11-I88)*0.3),1)) | K88: =IF(A88="","",ROUND( (MAX(1,MIN(10,IF(D88<=0,10,(MAX(0,$E$4-$E$8)+($E$6*12))/D88*10)))*0.4) + (MIN(10,H88+0.5)*0.3) + (MIN(10,12-I88)*0.3) ,1)) | L88: =IF(A88="","",ROUND( (MAX(1,MIN(10,IF(D88<=0,10,(MAX(0,$E$4-$E$8)+($E$6*36))/D88*10)))*0.4) + (MIN(10,H88+1.5)*0.3) + (MIN(10,14-I88)*0.3) ,1)) | M88: =IF(A88="","",ROUND((F88*0.45)+(J88*0.4)+((11-I88)*0.15),2)) | N88: =IFERROR(__xludf.DUMMYFUNCTION("IF(A88="""","""",RANK(M88,FILTER($M$11:$M$100,$A$11:$A$100<>""""),0))"),"") | O88: =IF(A88="","",IF(AND(F88>=8,J88<4),"DREAM",IF(J88>=8,"DO NOW",IF(J88>=6,"START PLANNING",IF(K88>=7,"BUILD TOWARDS","PARK"))))) | P88: =IF(A88="","",IF(J88>=9,"NONE",IF(G88<=H88,IF(G88<=11-I88,"MONEY","DIFFICULTY"),IF(H88<=11-I88,"TIME","DIFFICULTY")))) | R88: =IF(A88="","",MAX(0,D88-MAX(0,$E$4-$E$8))) | S88: =IF(A88="","",IF(R88=0,0,IF($E$6<=0,"NO SAVINGS",ROUNDUP(R88/$E$6,0)))) | T88: =IFERROR(__xludf.DUMMYFUNCTION("IF(A88="""","""",RANK(F88,FILTER($F$11:$F$100,$A$11:$A$100<>""""),0))"),"") | U88: =IFERROR(__xludf.DUMMYFUNCTION("IF(A88="""","""",RANK( (F88*0.5+K88*0.5), FILTER($F$11:$F$100*0.5+$K$11:$K$100*0.5,$A$11:$A$100<>""""), 0))"),"") | V88: =IFERROR(__xludf.DUMMYFUNCTION("IF(A88="""","""",RANK( (F88*0.45+L88*0.55), FILTER($F$11:$F$100*0.45+$L$11:$L$100*0.55,$A$11:$A$100<>""""), 0))"),"")
G89: =IF(A89="","",MAX(1,MIN(10,ROUND(10-(MAX(0,D89-$E$4)/MAX(1,$E$6))*0.5,0)))) | H89: =IF(A89="","",IF(E89<=0,10,ROUND(MAX(1,MIN(10,10-(E89/MAX(1,$E$7)*10))),1))) | J89: =IF(A89="","",ROUND((G89*0.4)+(H89*0.3)+((11-I89)*0.3),1)) | K89: =IF(A89="","",ROUND( (MAX(1,MIN(10,IF(D89<=0,10,(MAX(0,$E$4-$E$8)+($E$6*12))/D89*10)))*0.4) + (MIN(10,H89+0.5)*0.3) + (MIN(10,12-I89)*0.3) ,1)) | L89: =IF(A89="","",ROUND( (MAX(1,MIN(10,IF(D89<=0,10,(MAX(0,$E$4-$E$8)+($E$6*36))/D89*10)))*0.4) + (MIN(10,H89+1.5)*0.3) + (MIN(10,14-I89)*0.3) ,1)) | M89: =IF(A89="","",ROUND((F89*0.45)+(J89*0.4)+((11-I89)*0.15),2)) | N89: =IFERROR(__xludf.DUMMYFUNCTION("IF(A89="""","""",RANK(M89,FILTER($M$11:$M$100,$A$11:$A$100<>""""),0))"),"") | O89: =IF(A89="","",IF(AND(F89>=8,J89<4),"DREAM",IF(J89>=8,"DO NOW",IF(J89>=6,"START PLANNING",IF(K89>=7,"BUILD TOWARDS","PARK"))))) | P89: =IF(A89="","",IF(J89>=9,"NONE",IF(G89<=H89,IF(G89<=11-I89,"MONEY","DIFFICULTY"),IF(H89<=11-I89,"TIME","DIFFICULTY")))) | R89: =IF(A89="","",MAX(0,D89-MAX(0,$E$4-$E$8))) | S89: =IF(A89="","",IF(R89=0,0,IF($E$6<=0,"NO SAVINGS",ROUNDUP(R89/$E$6,0)))) | T89: =IFERROR(__xludf.DUMMYFUNCTION("IF(A89="""","""",RANK(F89,FILTER($F$11:$F$100,$A$11:$A$100<>""""),0))"),"") | U89: =IFERROR(__xludf.DUMMYFUNCTION("IF(A89="""","""",RANK( (F89*0.5+K89*0.5), FILTER($F$11:$F$100*0.5+$K$11:$K$100*0.5,$A$11:$A$100<>""""), 0))"),"") | V89: =IFERROR(__xludf.DUMMYFUNCTION("IF(A89="""","""",RANK( (F89*0.45+L89*0.55), FILTER($F$11:$F$100*0.45+$L$11:$L$100*0.55,$A$11:$A$100<>""""), 0))"),"")
G90: =IF(A90="","",MAX(1,MIN(10,ROUND(10-(MAX(0,D90-$E$4)/MAX(1,$E$6))*0.5,0)))) | H90: =IF(A90="","",IF(E90<=0,10,ROUND(MAX(1,MIN(10,10-(E90/MAX(1,$E$7)*10))),1))) | J90: =IF(A90="","",ROUND((G90*0.4)+(H90*0.3)+((11-I90)*0.3),1)) | K90: =IF(A90="","",ROUND( (MAX(1,MIN(10,IF(D90<=0,10,(MAX(0,$E$4-$E$8)+($E$6*12))/D90*10)))*0.4) + (MIN(10,H90+0.5)*0.3) + (MIN(10,12-I90)*0.3) ,1)) | L90: =IF(A90="","",ROUND( (MAX(1,MIN(10,IF(D90<=0,10,(MAX(0,$E$4-$E$8)+($E$6*36))/D90*10)))*0.4) + (MIN(10,H90+1.5)*0.3) + (MIN(10,14-I90)*0.3) ,1)) | M90: =IF(A90="","",ROUND((F90*0.45)+(J90*0.4)+((11-I90)*0.15),2)) | N90: =IFERROR(__xludf.DUMMYFUNCTION("IF(A90="""","""",RANK(M90,FILTER($M$11:$M$100,$A$11:$A$100<>""""),0))"),"") | O90: =IF(A90="","",IF(AND(F90>=8,J90<4),"DREAM",IF(J90>=8,"DO NOW",IF(J90>=6,"START PLANNING",IF(K90>=7,"BUILD TOWARDS","PARK"))))) | P90: =IF(A90="","",IF(J90>=9,"NONE",IF(G90<=H90,IF(G90<=11-I90,"MONEY","DIFFICULTY"),IF(H90<=11-I90,"TIME","DIFFICULTY")))) | R90: =IF(A90="","",MAX(0,D90-MAX(0,$E$4-$E$8))) | S90: =IF(A90="","",IF(R90=0,0,IF($E$6<=0,"NO SAVINGS",ROUNDUP(R90/$E$6,0)))) | T90: =IFERROR(__xludf.DUMMYFUNCTION("IF(A90="""","""",RANK(F90,FILTER($F$11:$F$100,$A$11:$A$100<>""""),0))"),"") | U90: =IFERROR(__xludf.DUMMYFUNCTION("IF(A90="""","""",RANK( (F90*0.45+K90*0.55), FILTER($F$11:$F$100*0.45+$K$11:$K$100*0.55,$A$11:$A$100<>""""), 0))"),"") | V90: =IFERROR(__xludf.DUMMYFUNCTION("IF(A90="""","""",RANK( (F90*0.45+L90*0.55), FILTER($F$11:$F$100*0.45+$L$11:$L$100*0.55,$A$11:$A$100<>""""), 0))"),"")
G91: =IF(A91="","",MAX(1,MIN(10,ROUND(10-(MAX(0,D91-$E$4)/MAX(1,$E$6))*0.5,0)))) | H91: =IF(A91="","",IF(E91<=0,10,ROUND(MAX(1,MIN(10,10-(E91/MAX(1,$E$7)*10))),1))) | J91: =IF(A91="","",ROUND((G91*0.4)+(H91*0.3)+((11-I91)*0.3),1)) | K91: =IF(A91="","",ROUND( (MAX(1,MIN(10,IF(D91<=0,10,(MAX(0,$E$4-$E$8)+($E$6*12))/D91*10)))*0.4) + (MIN(10,H91+0.5)*0.3) + (MIN(10,12-I91)*0.3) ,1)) | L91: =IF(A91="","",ROUND( (MAX(1,MIN(10,IF(D91<=0,10,(MAX(0,$E$4-$E$8)+($E$6*36))/D91*10)))*0.4) + (MIN(10,H91+1.5)*0.3) + (MIN(10,14-I91)*0.3) ,1)) | M91: =IF(A91="","",ROUND((F91*0.45)+(J91*0.4)+((11-I91)*0.15),2)) | N91: =IFERROR(__xludf.DUMMYFUNCTION("IF(A91="""","""",RANK(M91,FILTER($M$11:$M$100,$A$11:$A$100<>""""),0))"),"") | O91: =IF(A91="","",IF(AND(F91>=8,J91<4),"DREAM",IF(J91>=8,"DO NOW",IF(J91>=6,"START PLANNING",IF(K91>=7,"BUILD TOWARDS","PARK"))))) | P91: =IF(A91="","",IF(J91>=9,"NONE",IF(G91<=H91,IF(G91<=11-I91,"MONEY","DIFFICULTY"),IF(H91<=11-I91,"TIME","DIFFICULTY")))) | R91: =IF(A91="","",MAX(0,D91-MAX(0,$E$4-$E$8))) | S91: =IF(A91="","",IF(R91=0,0,IF($E$6<=0,"NO SAVINGS",ROUNDUP(R91/$E$6,0)))) | T91: =IFERROR(__xludf.DUMMYFUNCTION("IF(A91="""","""",RANK(F91,FILTER($F$11:$F$100,$A$11:$A$100<>""""),0))"),"") | U91: =IFERROR(__xludf.DUMMYFUNCTION("IF(A91="""","""",RANK( (F91*0.45+K91*0.55), FILTER($F$11:$F$100*0.45+$K$11:$K$100*0.55,$A$11:$A$100<>""""), 0))"),"")
G92: =IF(A92="","",MAX(1,MIN(10,ROUND(10-(MAX(0,D92-$E$4)/MAX(1,$E$6))*0.5,0)))) | H92: =IF(A92="","",IF(E92<=0,10,ROUND(MAX(1,MIN(10,10-(E92/MAX(1,$E$7)*10))),1))) | J92: =IF(A92="","",ROUND((G92*0.4)+(H92*0.3)+((11-I92)*0.3),1)) | K92: =IF(A92="","",ROUND( (MAX(1,MIN(10,IF(D92<=0,10,(MAX(0,$E$4-$E$8)+($E$6*12))/D92*10)))*0.4) + (MIN(10,H92+0.5)*0.3) + (MIN(10,12-I92)*0.3) ,1)) | L92: =IF(A92="","",ROUND( (MAX(1,MIN(10,IF(D92<=0,10,(MAX(0,$E$4-$E$8)+($E$6*36))/D92*10)))*0.4) + (MIN(10,H92+1.5)*0.3) + (MIN(10,14-I92)*0.3) ,1)) | M92: =IF(A92="","",ROUND((F92*0.45)+(J92*0.4)+((11-I92)*0.15),2)) | N92: =IFERROR(__xludf.DUMMYFUNCTION("IF(A92="""","""",RANK(M92,FILTER($M$11:$M$100,$A$11:$A$100<>""""),0))"),"") | O92: =IF(A92="","",IF(AND(F92>=8,J92<4),"DREAM",IF(J92>=8,"DO NOW",IF(J92>=6,"START PLANNING",IF(K92>=7,"BUILD TOWARDS","PARK"))))) | P92: =IF(A92="","",IF(J92>=9,"NONE",IF(G92<=H92,IF(G92<=11-I92,"MONEY","DIFFICULTY"),IF(H92<=11-I92,"TIME","DIFFICULTY")))) | R92: =IF(A92="","",MAX(0,D92-MAX(0,$E$4-$E$8))) | S92: =IF(A92="","",IF(R92=0,0,IF($E$6<=0,"NO SAVINGS",ROUNDUP(R92/$E$6,0)))) | T92: =IFERROR(__xludf.DUMMYFUNCTION("IF(A92="""","""",RANK(F92,FILTER($F$11:$F$100,$A$11:$A$100<>""""),0))"),"") | U92: =IFERROR(__xludf.DUMMYFUNCTION("IF(A92="""","""",RANK( (F92*0.45+K92*0.55), FILTER($F$11:$F$100*0.45+$K$11:$K$100*0.55,$A$11:$A$100<>""""), 0))"),"")
G93: =IF(A93="","",MAX(1,MIN(10,ROUND(10-(MAX(0,D93-$E$4)/MAX(1,$E$6))*0.5,0)))) | H93: =IF(A93="","",IF(E93<=0,10,ROUND(MAX(1,MIN(10,10-(E93/MAX(1,$E$7)*10))),1))) | J93: =IF(A93="","",ROUND((G93*0.4)+(H93*0.3)+((11-I93)*0.3),1)) | K93: =IF(A93="","",ROUND( (MAX(1,MIN(10,IF(D93<=0,10,(MAX(0,$E$4-$E$8)+($E$6*12))/D93*10)))*0.4) + (MIN(10,H93+0.5)*0.3) + (MIN(10,12-I93)*0.3) ,1)) | L93: =IF(A93="","",ROUND( (MAX(1,MIN(10,IF(D93<=0,10,(MAX(0,$E$4-$E$8)+($E$6*36))/D93*10)))*0.4) + (MIN(10,H93+1.5)*0.3) + (MIN(10,14-I93)*0.3) ,1)) | M93: =IF(A93="","",ROUND((F93*0.45)+(J93*0.4)+((11-I93)*0.15),2)) | N93: =IFERROR(__xludf.DUMMYFUNCTION("IF(A93="""","""",RANK(M93,FILTER($M$11:$M$100,$A$11:$A$100<>""""),0))"),"") | O93: =IF(A93="","",IF(AND(F93>=8,J93<4),"DREAM",IF(J93>=8,"DO NOW",IF(J93>=6,"START PLANNING",IF(K93>=7,"BUILD TOWARDS","PARK"))))) | P93: =IF(A93="","",IF(J93>=9,"NONE",IF(G93<=H93,IF(G93<=11-I93,"MONEY","DIFFICULTY"),IF(H93<=11-I93,"TIME","DIFFICULTY")))) | R93: =IF(A93="","",MAX(0,D93-$E$4)) | S93: =IF(A93="","",IF(R93=0,0,IF($E$6<=0,"N/A",ROUNDUP(R93/$E$6,0)))) | T93: =IFERROR(__xludf.DUMMYFUNCTION("IF(A93="""","""",RANK(F93,FILTER($F$11:$F$100,$A$11:$A$100<>""""),0))"),"") | U93: =IFERROR(__xludf.DUMMYFUNCTION("IF(A93="""","""",RANK( (F93*0.45+K93*0.55), FILTER($F$11:$F$100*0.45+$K$11:$K$100*0.55,$A$11:$A$100<>""""), 0))"),"")
G94: =IF(A94="","",MAX(1,MIN(10,ROUND(10-(MAX(0,D94-$E$4)/MAX(1,$E$6))*0.5,0)))) | H94: =IF(A94="","",IF(E94<=0,10,ROUND(MAX(1,MIN(10,10-(E94/MAX(1,$E$7)*10))),1))) | J94: =IF(A94="","",ROUND((G94*0.4)+(H94*0.3)+((11-I94)*0.3),1)) | K94: =IF(A94="","",ROUND( (MAX(1,MIN(10,IF(D94<=0,10,(MAX(0,$E$4-$E$8)+($E$6*12))/D94*10)))*0.4) + (MIN(10,H94+0.5)*0.3) + (MIN(10,12-I94)*0.3) ,1)) | L94: =IF(A94="","",ROUND( (MAX(1,MIN(10,IF(D94<=0,10,(MAX(0,$E$4-$E$8)+($E$6*36))/D94*10)))*0.4) + (MIN(10,H94+1.5)*0.3) + (MIN(10,14-I94)*0.3) ,1)) | M94: =IF(A94="","",ROUND((F94*0.45)+(J94*0.4)+((11-I94)*0.15),2)) | N94: =IFERROR(__xludf.DUMMYFUNCTION("IF(A94="""","""",RANK(M94,FILTER($M$11:$M$100,$A$11:$A$100<>""""),0))"),"") | O94: =IF(A94="","",IF(AND(F94>=8,J94<4),"DREAM",IF(J94>=8,"DO NOW",IF(J94>=6,"START PLANNING",IF(K94>=7,"BUILD TOWARDS","PARK"))))) | P94: =IF(A94="","",IF(J94>=9,"NONE",IF(G94<=H94,IF(G94<=11-I94,"MONEY","DIFFICULTY"),IF(H94<=11-I94,"TIME","DIFFICULTY")))) | R94: =IF(A94="","",MAX(0,D94-$E$4)) | S94: =IF(A94="","",IF(R94=0,0,IF($E$6<=0,"N/A",ROUNDUP(R94/$E$6,0)))) | T94: =IFERROR(__xludf.DUMMYFUNCTION("IF(A94="""","""",RANK(F94,FILTER($F$11:$F$100,$A$11:$A$100<>""""),0))"),"") | U94: =IFERROR(__xludf.DUMMYFUNCTION("IF(A94="""","""",RANK( (F94*0.45+K94*0.55), FILTER($F$11:$F$100*0.45+$K$11:$K$100*0.55,$A$11:$A$100<>""""), 0))"),"")
G95: =IF(A95="","",MAX(1,MIN(10,ROUND(10-(MAX(0,D95-$E$4)/MAX(1,$E$6))*0.5,0)))) | H95: =IF(A95="","",IF(E95<=0,10,ROUND(MAX(1,MIN(10,10-(E95/MAX(1,$E$7)*10))),1))) | J95: =IF(A95="","",ROUND((G95*0.4)+(H95*0.3)+((11-I95)*0.3),1)) | K95: =IF(A95="","",ROUND( (MAX(1,MIN(10,IF(D95<=0,10,(MAX(0,$E$4-$E$8)+($E$6*12))/D95*10)))*0.4) + (MIN(10,H95+0.5)*0.3) + (MIN(10,12-I95)*0.3) ,1)) | L95: =IF(A95="","",ROUND( (MAX(1,MIN(10,IF(D95<=0,10,(MAX(0,$E$4-$E$8)+($E$6*36))/D95*10)))*0.4) + (MIN(10,H95+1.5)*0.3) + (MIN(10,14-I95)*0.3) ,1)) | M95: =IF(A95="","",ROUND((F95*0.45)+(J95*0.4)+((11-I95)*0.15),2)) | N95: =IFERROR(__xludf.DUMMYFUNCTION("IF(A95="""","""",RANK(M95,FILTER($M$11:$M$100,$A$11:$A$100<>""""),0))"),"") | O95: =IF(A95="","",IF(AND(F95>=8,J95<4),"DREAM",IF(J95>=8,"DO NOW",IF(J95>=6,"START PLANNING",IF(K95>=7,"BUILD TOWARDS","PARK"))))) | P95: =IF(A95="","",IF(J95>=9,"NONE",IF(G95<=H95,IF(G95<=11-I95,"MONEY","DIFFICULTY"),IF(H95<=11-I95,"TIME","DIFFICULTY")))) | R95: =IF(A95="","",MAX(0,D95-$E$4)) | S95: =IF(A95="","",IF(R95=0,0,IF($E$6<=0,"N/A",ROUNDUP(R95/$E$6,0)))) | T95: =IFERROR(__xludf.DUMMYFUNCTION("IF(A95="""","""",RANK(F95,FILTER($F$11:$F$100,$A$11:$A$100<>""""),0))"),"") | U95: =IFERROR(__xludf.DUMMYFUNCTION("IF(A95="""","""",RANK( (F95*0.45+K95*0.55), FILTER($F$11:$F$100*0.45+$K$11:$K$100*0.55,$A$11:$A$100<>""""), 0))"),"")
G96: =IF(A96="","",MAX(1,MIN(10,ROUND(10-(MAX(0,D96-$E$4)/MAX(1,$E$6))*0.5,0)))) | H96: =IF(A96="","",IF(E96<=0,10,ROUND(MAX(1,MIN(10,10-(E96/MAX(1,$E$7)*10))),1))) | J96: =IF(A96="","",ROUND((G96*0.4)+(H96*0.3)+((11-I96)*0.3),1)) | K96: =IF(A96="","",ROUND( (MAX(1,MIN(10,IF(D96<=0,10,(MAX(0,$E$4-$E$8)+($E$6*12))/D96*10)))*0.4) + (MIN(10,H96+0.5)*0.3) + (MIN(10,12-I96)*0.3) ,1)) | L96: =IF(A96="","",ROUND( (MAX(1,MIN(10,IF(D96<=0,10,(MAX(0,$E$4-$E$8)+($E$6*36))/D96*10)))*0.4) + (MIN(10,H96+1.5)*0.3) + (MIN(10,14-I96)*0.3) ,1)) | M96: =IF(A96="","",ROUND((F96*0.45)+(J96*0.4)+((11-I96)*0.15),2)) | N96: =IFERROR(__xludf.DUMMYFUNCTION("IF(A96="""","""",RANK(M96,FILTER($M$11:$M$100,$A$11:$A$100<>""""),0))"),"") | O96: =IF(A96="","",IF(AND(F96>=8,J96<4),"DREAM",IF(J96>=8,"DO NOW",IF(J96>=6,"START PLANNING",IF(K96>=7,"BUILD TOWARDS","PARK"))))) | P96: =IF(A96="","",IF(J96>=9,"NONE",IF(G96<=H96,IF(G96<=11-I96,"MONEY","DIFFICULTY"),IF(H96<=11-I96,"TIME","DIFFICULTY")))) | R96: =IF(A96="","",MAX(0,D96-$E$4)) | S96: =IF(A96="","",IF(R96=0,0,IF($E$6<=0,"N/A",ROUNDUP(R96/$E$6,0)))) | T96: =IFERROR(__xludf.DUMMYFUNCTION("IF(A96="""","""",RANK(F96,FILTER($F$11:$F$100,$A$11:$A$100<>""""),0))"),"") | U96: =IFERROR(__xludf.DUMMYFUNCTION("IF(A96="""","""",RANK( (F96*0.45+K96*0.55), FILTER($F$11:$F$100*0.45+$K$11:$K$100*0.55,$A$11:$A$100<>""""), 0))"),"")
G97: =IF(A97="","",MAX(1,MIN(10,ROUND(10-(MAX(0,D97-$E$4)/MAX(1,$E$6))*0.5,0)))) | H97: =IF(A97="","",IF(E97<=0,10,ROUND(MAX(1,MIN(10,10-(E97/MAX(1,$E$7)*10))),1))) | J97: =IF(A97="","",ROUND((G97*0.4)+(H97*0.3)+((11-I97)*0.3),1)) | K97: =IF(A97="","",ROUND( (MAX(1,MIN(10,IF(D97<=0,10,(MAX(0,$E$4-$E$8)+($E$6*12))/D97*10)))*0.4) + (MIN(10,H97+0.5)*0.3) + (MIN(10,12-I97)*0.3) ,1)) | L97: =IF(A97="","",ROUND( (MAX(1,MIN(10,IF(D97<=0,10,(MAX(0,$E$4-$E$8)+($E$6*36))/D97*10)))*0.4) + (MIN(10,H97+1.5)*0.3) + (MIN(10,14-I97)*0.3) ,1)) | M97: =IF(A97="","",ROUND((F97*0.45)+(J97*0.4)+((11-I97)*0.15),2)) | N97: =IFERROR(__xludf.DUMMYFUNCTION("IF(A97="""","""",RANK(M97,FILTER($M$11:$M$100,$A$11:$A$100<>""""),0))"),"") | O97: =IF(A97="","",IF(AND(F97>=8,J97<4),"DREAM",IF(J97>=8,"DO NOW",IF(J97>=6,"START PLANNING",IF(K97>=7,"BUILD TOWARDS","PARK"))))) | P97: =IF(A97="","",IF(J97>=9,"NONE",IF(G97<=H97,IF(G97<=11-I97,"MONEY","DIFFICULTY"),IF(H97<=11-I97,"TIME","DIFFICULTY")))) | R97: =IF(A97="","",MAX(0,D97-$E$4)) | S97: =IF(A97="","",IF(R97=0,0,IF($E$6<=0,"N/A",ROUNDUP(R97/$E$6,0)))) | T97: =IFERROR(__xludf.DUMMYFUNCTION("IF(A97="""","""",RANK(F97,FILTER($F$11:$F$100,$A$11:$A$100<>""""),0))"),"") | U97: =IFERROR(__xludf.DUMMYFUNCTION("IF(A97="""","""",RANK( (F97*0.45+K97*0.55), FILTER($F$11:$F$100*0.45+$K$11:$K$100*0.55,$A$11:$A$100<>""""), 0))"),"")
G98: =IF(A98="","",MAX(1,MIN(10,ROUND(10-(MAX(0,D98-$E$4)/MAX(1,$E$6))*0.5,0)))) | H98: =IF(A98="","",IF(E98<=0,10,ROUND(MAX(1,MIN(10,10-(E98/MAX(1,$E$7)*10))),1))) | J98: =IF(A98="","",ROUND((G98*0.4)+(H98*0.3)+((11-I98)*0.3),1)) | K98: =IF(A98="","",ROUND( (MAX(1,MIN(10,IF(D98<=0,10,(MAX(0,$E$4-$E$8)+($E$6*12))/D98*10)))*0.4) + (MIN(10,H98+0.5)*0.3) + (MIN(10,12-I98)*0.3) ,1)) | L98: =IF(A98="","",ROUND( (MAX(1,MIN(10,IF(D98<=0,10,(MAX(0,$E$4-$E$8)+($E$6*36))/D98*10)))*0.4) + (MIN(10,H98+1.5)*0.3) + (MIN(10,14-I98)*0.3) ,1)) | M98: =IF(A98="","",ROUND((F98*0.45)+(J98*0.4)+((11-I98)*0.15),2)) | N98: =IFERROR(__xludf.DUMMYFUNCTION("IF(A98="""","""",RANK(M98,FILTER($M$11:$M$100,$A$11:$A$100<>""""),0))"),"") | O98: =IF(A98="","",IF(AND(F98>=8,J98<4),"DREAM",IF(J98>=8,"DO NOW",IF(J98>=6,"START PLANNING",IF(K98>=7,"BUILD TOWARDS","PARK"))))) | P98: =IF(A98="","",IF(J98>=9,"NONE",IF(G98<=H98,IF(G98<=11-I98,"MONEY","DIFFICULTY"),IF(H98<=11-I98,"TIME","DIFFICULTY")))) | R98: =IF(A98="","",MAX(0,D98-$E$4)) | S98: =IF(A98="","",IF(R98=0,0,IF($E$6<=0,"N/A",ROUNDUP(R98/$E$6,0)))) | T98: =IFERROR(__xludf.DUMMYFUNCTION("IF(A98="""","""",RANK(F98,FILTER($F$11:$F$100,$A$11:$A$100<>""""),0))"),"") | U98: =IFERROR(__xludf.DUMMYFUNCTION("IF(A98="""","""",RANK( (F98*0.45+K98*0.55), FILTER($F$11:$F$100*0.45+$K$11:$K$100*0.55,$A$11:$A$100<>""""), 0))"),"")
G99: =IF(A99="","",MAX(1,MIN(10,ROUND(10-(MAX(0,D99-$E$4)/MAX(1,$E$6))*0.5,0)))) | H99: =IF(A99="","",IF(E99<=0,10,ROUND(MAX(1,MIN(10,10-(E99/MAX(1,$E$7)*10))),1))) | J99: =IF(A99="","",ROUND((G99*0.4)+(H99*0.3)+((11-I99)*0.3),1)) | K99: =IF(A99="","",ROUND( (MAX(1,MIN(10,IF(D99<=0,10,(MAX(0,$E$4-$E$8)+($E$6*12))/D99*10)))*0.4) + (MIN(10,H99+0.5)*0.3) + (MIN(10,12-I99)*0.3) ,1)) | L99: =IF(A99="","",ROUND( (MAX(1,MIN(10,IF(D99<=0,10,(MAX(0,$E$4-$E$8)+($E$6*36))/D99*10)))*0.4) + (MIN(10,H99+1.5)*0.3) + (MIN(10,14-I99)*0.3) ,1)) | M99: =IF(A99="","",ROUND((F99*0.45)+(J99*0.4)+((11-I99)*0.15),2)) | N99: =IFERROR(__xludf.DUMMYFUNCTION("IF(A99="""","""",RANK(M99,FILTER($M$11:$M$100,$A$11:$A$100<>""""),0))"),"") | O99: =IF(A99="","",IF(AND(F99>=8,J99<4),"DREAM",IF(J99>=8,"DO NOW",IF(J99>=6,"START PLANNING",IF(K99>=7,"BUILD TOWARDS","PARK"))))) | P99: =IF(A99="","",IF(J99>=9,"NONE",IF(G99<=H99,IF(G99<=11-I99,"MONEY","DIFFICULTY"),IF(H99<=11-I99,"TIME","DIFFICULTY")))) | R99: =IF(A99="","",MAX(0,D99-$E$4)) | S99: =IF(A99="","",IF(R99=0,0,IF($E$6<=0,"N/A",ROUNDUP(R99/$E$6,0)))) | T99: =IFERROR(__xludf.DUMMYFUNCTION("IF(A99="""","""",RANK(F99,FILTER($F$11:$F$100,$A$11:$A$100<>""""),0))"),"") | U99: =IFERROR(__xludf.DUMMYFUNCTION("IF(A99="""","""",RANK( (F99*0.45+K99*0.55), FILTER($F$11:$F$100*0.45+$K$11:$K$100*0.55,$A$11:$A$100<>""""), 0))"),"")
G100: =IF(A100="","",MAX(1,MIN(10,ROUND(10-(MAX(0,D100-$E$4)/MAX(1,$E$6))*0.5,0)))) | H100: =IF(A100="","",IF(E100<=0,10,ROUND(MAX(1,MIN(10,10-(E100/MAX(1,$E$7)*10))),1))) | J100: =IF(A100="","",ROUND((G100*0.4)+(H100*0.3)+((11-I100)*0.3),1)) | K100: =IF(A100="","",ROUND( (MAX(1,MIN(10,IF(D100<=0,10,(MAX(0,$E$4-$E$8)+($E$6*12))/D100*10)))*0.4) + (MIN(10,H100+0.5)*0.3) + (MIN(10,12-I100)*0.3) ,1)) | L100: =IF(A100="","",ROUND( (MAX(1,MIN(10,IF(D100<=0,10,(MAX(0,$E$4-$E$8)+($E$6*36))/D100*10)))*0.4) + (MIN(10,H100+1.5)*0.3) + (MIN(10,14-I100)*0.3) ,1)) | M100: =IF(A100="","",ROUND((F100*0.45)+(J100*0.4)+((11-I100)*0.15),2)) | N100: =IFERROR(__xludf.DUMMYFUNCTION("IF(A100="""","""",RANK(M100,FILTER($M$11:$M$100,$A$11:$A$100<>""""),0))"),"") | O100: =IF(A100="","",IF(AND(F100>=8,J100<4),"DREAM",IF(J100>=8,"DO NOW",IF(J100>=6,"START PLANNING",IF(K100>=7,"BUILD TOWARDS","PARK"))))) | P100: =IF(A100="","",IF(J100>=9,"NONE",IF(G100<=H100,IF(G100<=11-I100,"MONEY","DIFFICULTY"),IF(H100<=11-I100,"TIME","DIFFICULTY")))) | R100: =IF(A100="","",MAX(0,D100-$E$4)) | S100: =IF(A100="","",IF(R100=0,0,IF($E$6<=0,"N/A",ROUNDUP(R100/$E$6,0)))) | T100: =IFERROR(__xludf.DUMMYFUNCTION("IF(A100="""","""",RANK(F100,FILTER($F$11:$F$100,$A$11:$A$100<>""""),0))"),"") | U100: =IFERROR(__xludf.DUMMYFUNCTION("IF(A100="""","""",RANK( (F100*0.45+K100*0.55), FILTER($F$11:$F$100*0.45+$K$11:$K$100*0.55,$A$11:$A$100<>""""), 0))"),"")
H101: =IF(A101="","",IF(E101<=0,10,ROUND(MAX(1,MIN(10,10-(E101/MAX(1,$E$7)*10))),1))) | L101: =IF(A101="","",ROUND( (MAX(1,MIN(10,IF(D101<=0,10,(MAX(0,$E$4-$E$8)+($E$6*36))/D101*10)))*0.4) + (MIN(10,H101+1.5)*0.3) + (MIN(10,14-I101)*0.3) ,1)) | N101: =IFERROR(__xludf.DUMMYFUNCTION("IF(A101="""","""",RANK(M101,FILTER($M$11:$M$100,$A$11:$A$100<>""""),0))"),"") | O101: =IF(A101="","",IF(AND(F101>=8,J101<4),"DREAM",IF(J101>=8,"DO NOW",IF(J101>=6,"START PLANNING",IF(K101>=7,"BUILD TOWARDS","PARK"))))) | P101: =IF(A101="","",IF(J101>=9,"NONE",IF(G101<=H101,IF(G101<=11-I101,"MONEY","DIFFICULTY"),IF(H101<=11-I101,"TIME","DIFFICULTY")))) | U101: =IFERROR(__xludf.DUMMYFUNCTION("IF(A101="""","""",RANK( (F101*0.45+K101*0.55), FILTER($F$11:$F$100*0.45+$K$11:$K$100*0.55,$A$11:$A$100<>""""), 0))"),"")
...

Sheet JOB
A1: THE HOLIDAY JOB | D1: WHY LAST TIME FAILED
A2: GOAL | B2: GET PAID CHRISTMAS WORK | D2: PROBLEM | E2: ANSWER
